Workbook
Name Cc: Cover!$H$3:$H$3
Name period: Cover!$H$2:$H$2
Name ticker: Cover!$C$8:$C$8

Sheet Cover
C4: Financial Analysis and Presentation
C6: =TODAY() -> 45641
C7: Amazon.com Inc.
C8: NASDAQ:AMZN
C10: Team 12:
C11: Alessandro FRULLANI
C12: Felipe MIGUEL BERTI
C13: Giada SIMBARI
C14: Ivan SERDAROV
C15: Maria Jose Castañeda

Sheet Summary
B1: Amazon.com Inc. (AMZN)
G3: Forecast
B4: Income Statement | D4: 2021 | E4: 2022 | F4: 2023 | G4: 2024E | H4: 2025E | I4: 2026E | J4: 2027E | K4: 2028E
B6: Revenue | D6: =Model!C6 -> 469822 | E6: =Model!D6 -> 513983 | F6: =Model!E6 -> 574785 | G6: =Model!F6 -> 638043.37 | H6: =Model!G6 -> 701356.64 | I6: =Model!H6 -> 766881.78 | J6: =Model!I6 -> 839695.3 | K6: =Model!J6 -> 920707.8
B7: Gross Profit | D7: =Model!C8 -> 197478 | E7: =Model!D8 -> 225152 | F7: =Model!E8 -> 270046 | G7: =Model!F8 -> 311073.89 | H7: =Model!G8 -> 336651.19 | I7: =Model!H8 -> 375772.07 | J7: =Model!I8 -> 419847.65 | K7: =Model!J8 -> 469560.98
B8: EBITDA | D8: =IS!AP94 -> 73945 | E8: =IS!AU94 -> 37363 | F8: =IS!AZ94 -> 86453 | G8: =IS!BE94 -> 115373.54 | H8: =IS!BJ94 -> 133193.95 | I8: =IS!BK94 -> 157977.65 | J8: =IS!BL94 -> 172977.23 | K8: =IS!BM94 -> 194269.34
B9: Operating Income | D9: =Model!C11 -> 24879 | E9: =Model!D11 -> 12248 | F9: =Model!E11 -> 36852 | G9: =Model!F11 -> 65238.255 | H9: =Model!G11 -> 73642.447 | I9: =Model!H11 -> 79755.705 | J9: =Model!I11 -> 83129.834 | K9: =Model!J11 -> 91150.072
B10: Net Income | D10: =Model!C16 -> 33364 | E10: =Model!D16 -> -2722 | F10: =Model!E16 -> 30425 | G10: =Model!F16 -> 52898.854 | H10: =Model!G16 -> 56515.318 | I10: =Model!H16 -> 61189.497 | J10: =Model!I16 -> 63682.491 | K10: =Model!J16 -> 69826.479
B11: EPS | D11: =Model!C19 -> 3.2404817 | E11: =Model!D19 -> -0.26715085 | F11: =Model!E19 -> 2.8998284 | G11: =Model!F19 -> 4.9354003 | H11: =Model!G19 -> 5.2159961 | I11: =Model!H19 -> 5.5855314 | J11: =Model!I19 -> 5.7501121 | K11: =Model!J19 -> 6.2372916
B13: Growth (% YoY)
B14: Revenue | D14: =IS!AP46 -> 0.21695367 | E14: =E6/ABS(D6)-1 -> 0.093995173 | F14: =F6/ABS(E6)-1 -> 0.11829574 | G14: =G6/ABS(F6)-1 -> 0.11005571 | H14: =H6/ABS(G6)-1 -> 0.099230361 | I14: =I6/ABS(H6)-1 -> 0.093426267 | J14: =J6/ABS(I6)-1 -> 0.094947516 | K14: =K6/ABS(J6)-1 -> 0.096478448
B15: Gross Profit | D15: =IS!AP48 -> 0.29275909 | E15: =E7/ABS(D7)-1 -> 0.14013713 | F15: =F7/ABS(E7)-1 -> 0.19939419 | G15: =G7/ABS(F7)-1 -> 0.15192928 | H15: =H7/ABS(G7)-1 -> 0.082222571 | I15: =I7/ABS(H7)-1 -> 0.11620598 | J15: =J7/ABS(I7)-1 -> 0.11729338 | K15: =K7/ABS(J7)-1 -> 0.11840802
B16: Operating Income | D16: =IS!AP55 -> 0.086466658 | E16: =E9/ABS(D9)-1 -> -0.50769725 | F16: =F9/ABS(E9)-1 -> 2.0088178 | G16: =G9/ABS(F9)-1 -> 0.77027719 | H16: =H9/ABS(G9)-1 -> 0.12882307 | I16: =I9/ABS(H9)-1 -> 0.083012684 | J16: =J9/ABS(I9)-1 -> 0.042305809 | K16: =K9/ABS(J9)-1 -> 0.096478448
B17: Net Income | D17: =IS!AP62 -> 0.56410857 | E17: =E10/ABS(D10)-1 -> -1.0815849 | F17: =F10/ABS(E10)-1 -> 10.177443 | G17: =G10/ABS(F10)-1 -> 0.73866407 | H17: =H10/ABS(G10)-1 -> 0.068365635 | I17: =I10/ABS(H10)-1 -> 0.082706402 | J17: =J10/ABS(I10)-1 -> 0.040742194 | K17: =K10/ABS(J10)-1 -> 0.096478448
B18: EPS | D18: =IS!AP63 -> 0.55023923 | E18: =E11/ABS(D11)-1 -> -1.0824417 | F18: =F11/ABS(E11)-1 -> 9.854648 | G18: =G11/ABS(F11)-1 -> 0.70196286 | H18: =H11/ABS(G11)-1 -> 0.056853712 | I18: =I11/ABS(H11)-1 -> 0.070846542 | J18: =J11/ABS(I11)-1 -> 0.029465529 | K18: =K11/ABS(J11)-1 -> 0.084725218
B20: Profitability (%)
B21: Gross Margin | D21: =D7/D6 -> 0.42032514 | E21: =E7/E6 -> 0.4380534 | F21: =F7/F6 -> 0.46982089 | G21: =G7/G6 -> 0.48754349 | H21: =H7/H6 -> 0.48 | I21: =I7/I6 -> 0.49 | J21: =J7/J6 -> 0.5 | K21: =K7/K6 -> 0.51
B22: EBITDA Margin | D22: =D8/D6 -> 0.15738939 | E22: =E8/E6 -> 0.072693066 | F22: =F8/F6 -> 0.15040928 | G22: =G8/G6 -> 0.18082398 | H22: =H8/H6 -> 0.18990902 | I22: =I8/I6 -> 0.206 | J22: =J8/J6 -> 0.206 | K22: =K8/K6 -> 0.211
B23: Operating Margin | D23: =D9/D6 -> 0.052954098 | E23: =E9/E6 -> 0.023829582 | F23: =F9/F6 -> 0.064114408 | G23: =G9/G6 -> 0.10224737 | H23: =H9/H6 -> 0.105 | I23: =I9/I6 -> 0.104 | J23: =J9/J6 -> 0.099 | K23: =K9/K6 -> 0.099
B24: Net Profit Margin | D24: =D10/D6 -> 0.071014129 | E24: =E10/E6 -> -0.005295895 | F24: =F10/F6 -> 0.052932836 | G24: =G10/G6 -> 0.082907929 | H24: =H10/H6 -> 0.08058 | I24: =I10/I6 -> 0.07979 | J24: =J10/J6 -> 0.07584 | K24: =K10/K6 -> 0.07584
B25: Return on Equity | D25: =Ratios!C45 -> 0.29249425 | E25: =Ratios!D45 -> -0.019805582 | F25: =Ratios!E45 -> 0.17812836 | G25: =Ratios!F45 -> 0.22307237 | H25: =Ratios!G45 -> 0.18918224 | I25: =Ratios!H45 -> 0.17042761 | J25: =Ratios!I45 -> 0.1510376 | K25: =Ratios!J45 -> 0.14289881
B26: ROIC | D26: =Ratios!C47 -> 0.16048767 | E26: =Ratios!D47 -> -0.0079813361 | F26: =Ratios!E47 -> 0.098945665 | G26: =Ratios!F47 -> 0.14030744 | H26: =Ratios!G47 -> 0.13557033 | I26: =Ratios!H47 -> 0.12666076 | J26: =Ratios!I47 -> 0.11655192 | K26: =Ratios!J47 -> 0.11346814
B28: Leverage
B30: Degree of Operational Leverage | D30: =Ratios!C51 -> 8.6342798 | E30: =Ratios!D51 -> -59.536137 | F30: =Ratios!E51 -> 16.086679 | G30: =Ratios!F51 -> 2.8122308 | H30: =Ratios!G51 -> 2.0043467 | I30: =Ratios!H51 -> 0.8906203 | J30: =Ratios!I51 -> 0.4560314 | K30: =Ratios!J51 -> 1
B31: Degree of Financial Leverage | D31: =Ratios!C52 -> 1.2095018 | E31: =Ratios!D52 -> 0.88728071 | F31: =Ratios!E52 -> 0.85493114 | G31: =Ratios!F52 -> 0.74807952 | H31: =Ratios!G52 -> 1.0252438 | I31: =Ratios!H52 -> 0.99397976 | J31: =Ratios!I52 -> 0.94094894 | K31: =Ratios!J52 -> 1
B32: Degree of Combined Leverage | D32: =Ratios!C53 -> 10.443177 | E32: =Ratios!D53 -> -52.825266 | F32: =Ratios!E53 -> 13.753003 | G32: =Ratios!F53 -> 2.1037723 | H32: =Ratios!G53 -> 2.054944 | I32: =Ratios!H53 -> 0.88525855 | J32: =Ratios!I53 -> 0.42910226 | K32: =Ratios!J53 -> 1
B33: Debt -to-Equity | D33: =Ratios!C54 -> 0.84194727 | E33: =Ratios!D54 -> 0.95942976 | F33: =Ratios!E54 -> 0.67175728 | G33: =Ratios!F54 -> 0.50878464 | H33: =Ratios!G54 -> 0.46034304 | I33: =Ratios!H54 -> 0.40418507 | J33: =Ratios!I54 -> 0.36166564 | K33: =Ratios!J54 -> 0.32572294
B35: Cash Flow
B36: Dividends per Share | D36: - | E36: - | F36: - | G36: - | H36: - | I36: - | J36: - | K36: -
B37: Free Cash Flow to the Firm | D37: =CF!AP46 -> -9069 | E37: =CF!AU46 -> -11569 | F37: =CF!AZ46 -> 36813 | G37: =CF!BE46 -> 32516.456 | H37: =CF!BJ46 -> 42853.701 | I37: =CF!BK46 -> 56636.788 | J37: =CF!BL46 -> 57614.428 | K37: =CF!BM46 -> 62528.289

Sheet Assumptions + Estimates
B1: Amazon.com Inc. (AMZN)
C3: Assumptions | F3: Estimates
C4: 2021 | D4: 2022 | E4: 2023 | F4: 45382 | G4: 45473 | H4: 45565 | I4: 45657 | J4: 2024 | K4: 45747 | L4: 45838 | M4: 45930 | N4: 46022 | O4: 2025 | P4: 2026 | Q4: 2027 | R4: 2028
B5: USA GDP Growth | C5: 0.058 | D5: 0.0194 | E5: 0.0254 | J5: 0.027 | O5: 0.02 | P5: 0.02 | Q5: 0.02 | R5: 0.018
B6: Unemployment Rate (USA) | C6: 0.067 | D6: 0.035 | E6: 0.037 | J6: 0.044 | O6: 0.044 | P6: 0.043 | Q6: 0.042 | R6: 0.042
B7: PCE Inflation (USA) | C7: 0.047 | D7: 0.08 | E7: 0.041 | J7: 0.026 | O7: 0.021 | P7: 0.02 | Q7: 0.02 | R7: 0.02
B8: Fed Funds Rate | C8: 0.0008 | D8: 0.0168 | E8: 0.0503 | J8: 0.044 | O8: 0.034 | P8: 0.029 | Q8: 0.029 | R8: 0.029
B10: Revenue Growth | C10: 2021 | D10: 2022 | E10: 2023 | F10: 45382 | G10: 45473 | H10: 45565 | I10: 45657 | J10: 2024 | K10: 45747 | L10: 45838 | M10: 45930 | N10: 46022 | O10: 2025 | P10: 2026 | Q10: 2027 | R10: 2028
B11: Online Stores | C11: =IS!AP39 -> 0.12529073 | D11: =IS!AU39 -> -0.0093256783 | E11: =IS!AZ39 -> 0.053944474 | F11: 0.02 | G11: 0.02 | H11: 0.07 | I11: 0.08 | J11: =IS!BE102/IS!$AZ8-1 -> 0.050602789 | K11: 0.05 | L11: 0.05 | M11: 0.05 | N11: 0.05 | O11: =IS!BJ102/IS!BE102-1 -> 0.058535599 | P11: 0.05 | Q11: 0.05 | R11: 0.05
B12: Physical Stores | C12: =IS!AP40 -> 0.052453156 | D12: =IS!AU40 -> 0.11057101 | E12: =IS!AZ40 -> 0.056267468 | F12: 0.04 | G12: 0.04 | H12: 0.06 | I12: 0.06 | J12: =IS!BE103/IS!$AZ9-1 -> 0.050095856 | K12: 0.05 | L12: 0.05 | M12: 0.05 | N12: 0.05 | O12: =IS!BJ103/IS!BE103-1 -> 0.050632686 | P12: 0.05 | Q12: 0.05 | R12: 0.05
B13: Third-Party Seller Services | C13: =IS!AP41 -> 0.28505538 | D13: =IS!AU41 -> 0.13882708 | E13: =IS!AZ41 -> 0.1897533 | F13: 0.1 | G13: 0.1 | H13: 0.15 | I13: 0.15 | J13: =IS!BE104/IS!$AZ10-1 -> 0.12781126 | K13: 0.1 | L13: 0.1 | M13: 0.1 | N13: 0.1 | O13: =IS!BJ104/IS!BE104-1 -> 0.098843827 | P13: 0.1 | Q13: 0.1 | R13: 0.1
B14: Subscription Services | C14: =IS!AP42 -> 0.26028484 | D14: =IS!AU42 -> 0.10859985 | E14: =IS!AZ42 -> 0.1417173 | F14: 0.1 | G14: 0.1 | H14: 0.14 | I14: 0.12 | J14: =IS!BE105/IS!$AZ11-1 -> 0.11533388 | K14: 0.1 | L14: 0.1 | M14: 0.1 | N14: 0.1 | O14: =IS!BJ105/IS!BE105-1 -> 0.093062505 | P14: 0.1 | Q14: 0.1 | R14: 0.1
B15: Advertising Services | C15: =IS!AP43 -> 1.5267596 | D15: =IS!AU43 -> 0.21113607 | E15: =IS!AZ43 -> 0.24290522 | F15: 0.18 | G15: 0.18 | H15: 0.2 | I15: 0.2 | J15: =IS!BE106/IS!$AZ12-1 -> 0.19139044 | K15: 0.18 | L15: 0.18 | M15: 0.18 | N15: 0.18 | O15: =IS!BJ106/IS!BE106-1 -> 0.19058464 | P15: 0.15 | Q15: 0.15 | R15: 0.15
B16: AWS | C16: =IS!AP44 -> 0.37099405 | D16: =IS!AU44 -> 0.28767564 | E16: =IS!AZ44 -> 0.13310278 | F16: 0.15 | G16: 0.18 | H16: 0.2 | I16: 0.2 | J16: =IS!BE107/IS!$AZ13-1 -> 0.18335666 | K16: 0.18 | L16: 0.18 | M16: 0.18 | N16: 0.18 | O16: =IS!BJ107/IS!BE107-1 -> 0.18015453 | P16: 0.15 | Q16: 0.15 | R16: 0.15
B17: Other | C17: =IS!AP45 -> -0.76205577 | D17: =IS!AU45 -> 0.95174632 | E17: =IS!AZ45 -> 0.16741229 | F17: 0.05 | G17: 0.05 | H17: 0.05 | I17: 0.05 | J17: =IS!BE108/IS!$AZ14-1 -> 0.05 | K17: 0.05 | L17: 0.05 | M17: 0.05 | N17: 0.05 | O17: =IS!BJ108/IS!BE108-1 -> 0.06172852 | P17: 0.05 | Q17: 0.05 | R17: 0.05
B18: Total Revenue | C18: =IS!AP46 -> 0.21695367 | D18: =IS!AU46 -> 0.093995173 | E18: =IS!AZ46 -> 0.11829574 | J18: =IS!BE109/IS!$AZ15-1 -> 0.10637153 | O18: =IS!BJ109/IS!BE109-1 -> 0.10289076 | P18: =IS!BK15/IS!BJ15-1 -> 0.093426267 | Q18: =IS!BL15/IS!BK15-1 -> 0.094947516 | R18: =IS!BM15/IS!BL15-1 -> 0.096478448
B20: Net Income Margin | C20: =Ratios!C44 -> 0.071014129 | D20: =Ratios!D44 -> -0.005295895 | E20: =Ratios!E44 -> 0.052932836 | F20: 0.05 | G20: 0.07 | H20: 0.09 | I20: 0.08 | J20: =IS!BE110/IS!BE109 -> 0.07375304 | K20: 0.08 | L20: 0.08 | M20: 0.08 | N20: 0.08 | O20: 0.08 | P20: 0.08 | Q20: 0.076 | R20: 0.076
B22: % of Revenue | C22: 2021 | D22: 2022 | E22: 2023 | F22: 45382 | G22: 45473 | H22: 45565 | I22: 45657 | J22: 2024 | K22: 45747 | L22: 45838 | M22: 45930 | N22: 46022 | O22: 2025 | P22: 2026 | Q22: 2027 | R22: 2028
B23: Total Cost of Goods Sold | C23: =IS!AP74 -> 0.57967486 | D23: =IS!AU74 -> 0.5619466 | E23: =IS!AZ74 -> 0.53017911 | J23: 0.53 | O23: 0.52 | P23: 0.51 | Q23: 0.5 | R23: 0.49
B25: Fulfillment | C25: =IS!AP76 -> 0.15987119 | D25: =IS!AU76 -> 0.16401126 | E25: =IS!AZ76 -> 0.15765721 | J25: 0.154 | O25: 0.154 | P25: 0.15 | Q25: 0.15 | R25: 0.15
B26: Technology and Content | C26: =IS!AP77 -> 0.11930476 | D26: =IS!AU77 -> 0.14244245 | E26: =IS!AZ77 -> 0.14896353 | J26: 0.13 | O26: 0.13 | P26: 0.13 | Q26: 0.14 | R26: 0.15
B27: Marketing | C27: =IS!AP78 -> 0.069283686 | D27: =IS!AU78 -> 0.082177815 | E27: =IS!AZ78 -> 0.077194081 | J27: 0.07 | O27: 0.07 | P27: 0.08 | Q27: 0.08 | R27: 0.08
B28: General & Administrative | C28: =IS!AP79 -> 0.018779453 | D28: =IS!AU79 -> 0.023135006 | E28: =IS!AZ79 -> 0.020557252 | J28: 0.02 | O28: 0.02 | P28: 0.025 | Q28: 0.03 | R28: 0.03
B29: Other Operating Expenses (Income) | C29: =IS!AP80 -> 0.00013196487 | D29: =IS!AU80 -> 0.0024572797 | E29: =IS!AZ80 -> 0.001334412 | J29: 0.001 | O29: 0.001 | P29: 0.001 | Q29: 0.001 | R29: 0.001
B32: Interest Income | C32: =IS!AP83 -> 0.00095355262 | D32: =IS!AU83 -> 0.0019241882 | E32: =IS!AZ83 -> 0.0051306141 | J32: 0.005 | O32: 0.005 | P32: 0.005 | Q32: 0.005 | R32: 0.005
B33: Interest Expense | C33: =IS!AP84 -> -0.0038503944 | D33: =IS!AU84 -> -0.0046052107 | E33: =IS!AZ84 -> -0.005535983 | J33: -0.01 | O33: -0.01 | P33: -0.01 | Q33: -0.01 | R33: -0.01
B34: Other Income, Net | C34: =IS!AP85 -> 0.031145838 | D34: =IS!AU85 -> -0.032697579 | E34: =IS!AZ85 -> 0.0016319145 | J34: 0.002 | O34: 0.002 | P34: 0.002 | Q34: 0.002 | R34: 0.002
B39: Effective Tax Rate | C39: =IS!AP90 -> 0.12557993 | D39: =IS!AU90 -> 0.54194744 | E39: =IS!AZ90 -> 0.18957851 | J39: 0.21 | O39: 0.21 | P39: 0.21 | Q39: 0.21 | R39: 0.21
B41: Depreciation | C41: =CF!AP9/IS!AP15 -> 0.072997859 | D41: =CF!AU9/IS!AU15 -> 0.080666092 | E41: =CF!AZ9/IS!AZ15 -> 0.084662961 | J41: 0.09 | O41: 0.095 | P41: 0.1 | Q41: 0.105 | R41: 0.11
B42: Purchases of PP&E | C42: =CF!AP22/IS!AP15 -> -0.12994921 | D42: =CF!AU22/IS!AU15 -> -0.12382705 | E42: =CF!AZ22/IS!AZ15 -> -0.09173691 | J42: -0.1 | O42: -0.12 | P42: -0.12 | Q42: -0.12 | R42: -0.12

Sheet Model
B1: Amazon.com Inc. (AMZN)
F3: Forecast
B4: Income Statement | C4: 2021 | D4: 2022 | E4: 2023 | F4: 2024E | G4: 2025E | H4: 2026E | I4: 2027E | J4: 2028E
B6: Revenue | C6: =IS!AP15 -> 469822 | D6: =IS!AU15 -> 513983 | E6: =IS!AZ15 -> 574785 | F6: =IS!BE15 -> 638043.37 | G6: =IS!BJ15 -> 701356.64 | H6: =IS!BK15 -> 766881.78 | I6: =IS!BL15 -> 839695.3 | J6: =IS!BM15 -> 920707.8
B7: Cost of Goods Sold | C7: =IS!AP16 -> 272344 | D7: =IS!AU16 -> 288831 | E7: =IS!AZ16 -> 304739 | F7: =IS!BE16 -> 326969.48 | G7: =IS!BJ16 -> 364705.45 | H7: =IS!BK16 -> 391109.71 | I7: =IS!BL16 -> 419847.65 | J7: =IS!BM16 -> 451146.82
B8: Gross Profit | C8: =C6-C7 -> 197478 | D8: =D6-D7 -> 225152 | E8: =E6-E7 -> 270046 | F8: =F6-F7 -> 311073.89 | G8: =G6-G7 -> 336651.19 | H8: =H6-H7 -> 375772.07 | I8: =I6-I7 -> 419847.65 | J8: =J6-J7 -> 469560.98
B10: Selling, General, and Admin. Expenses | C10: =SUM(IS!AP18:AP22) -> 172599 | D10: =SUM(IS!AU18:AU22) -> 212904 | E10: =SUM(IS!AZ18:AZ22) -> 233194 | F10: =SUM(IS!BE18:BE22) -> 245835.64 | G10: =SUM(IS!BJ18:BJ22) -> 263008.74 | H10: =SUM(IS!BK18:BK22) -> 296016.37 | I10: =SUM(IS!BL18:BL22) -> 336717.81 | J10: =SUM(IS!BM18:BM22) -> 378410.9
B11: Operating Income | C11: =C8-C10 -> 24879 | D11: =D8-D10 -> 12248 | E11: =E8-E10 -> 36852 | F11: =F8-F10 -> 65238.255 | G11: =G8-G10 -> 73642.447 | H11: =H8-H10 -> 79755.705 | I11: =I8-I10 -> 83129.834 | J11: =J8-J10 -> 91150.072
B13: Net Interest Expense | C13: =-SUM(IS!AP25:AP27) -> -13272 | D13: =-SUM(IS!AU25:AU27) -> 18184 | E13: =-SUM(IS!AZ25:AZ27) -> -705 | F13: =-SUM(IS!BE25:BE27) -> 1688.6291 | G13: =-SUM(IS!BJ25:BJ27) -> 2104.0699 | H13: =-SUM(IS!BK25:BK27) -> 2300.6453 | I13: =-SUM(IS!BL25:BL27) -> 2519.0859 | J13: =-SUM(IS!BM25:BM27) -> 2762.1234
B14: Income Tax Expense | C14: =-IS!AP29 -> 4791 | D14: =-IS!AU29 -> -3217 | E14: =-IS!AZ29 -> 7120 | F14: =-IS!BE29 -> 10569.771 | G14: =-IS!BJ29 -> 15023.059 | H14: =-IS!BK29 -> 16265.562 | I14: =-IS!BL29 -> 16928.257 | J14: =-IS!BM29 -> 18561.469
B15: After-tax items | C15: =IS!AP30 -> 4 | D15: =IS!AU30 -> -3 | E15: =IS!AZ30 -> -12 | F15: =IS!BE30 -> -81 | G15: =IS!BJ30 -> 0 | H15: =IS!BK30 -> 0 | I15: =IS!BL30 -> 0 | J15: =IS!BM30 -> 0
B16: Net Income | C16: =C11-C13-C14+C15 -> 33364 | D16: =D11-D13-D14+D15 -> -2722 | E16: =E11-E13-E14+E15 -> 30425 | F16: =F11-F13-F14+F15 -> 52898.854 | G16: =G11-G13-G14+G15 -> 56515.318 | H16: =H11-H13-H14+H15 -> 61189.497 | I16: =I11-I13-I14+I15 -> 63682.491 | J16: =J11-J13-J14+J15 -> 69826.479
B18: Weighted Avg Diluted Shares Outstanding | C18: =IS!AP36 -> 10296 | D18: =IS!AU36 -> 10189 | E18: =IS!AZ36 -> 10492 | F18: =IS!BE36 -> 10718.25 | G18: =IS!BJ36 -> 10835 | H18: =IS!BK36 -> 10955 | I18: =IS!BL36 -> 11075 | J18: =IS!BM36 -> 11195
B19: Diluted Earnings Per Share (GAAP) | C19: =C16/C18 -> 3.2404817 | D19: =D16/D18 -> -0.26715085 | E19: =E16/E18 -> 2.8998284 | F19: =F16/F18 -> 4.9354003 | G19: =G16/G18 -> 5.2159961 | H19: =H16/H18 -> 5.5855314 | I19: =I16/I18 -> 5.7501121 | J19: =J16/J18 -> 6.2372916
F21: Forecast
B22: Balance Sheet | C22: 2021 | D22: 2022 | E22: 2023 | F22: 2024E | G22: 2025E | H22: 2026E | I22: 2027E | J22: 2028E
B24: Cash & Equivalents | C24: =BS!AP8+BS!AP9 -> 96049 | D24: =BS!AU8+BS!AU9 -> 70026 | E24: =BS!AZ8+BS!AZ9 -> 86780 | F24: =BS!BE8+BS!BE9 -> 99206.958 | G24: =BS!BJ8+BS!BJ9 -> 134795.19 | H24: =BS!BK8+BS!BK9 -> 178919.6 | I24: =BS!BL8+BS!BL9 -> 225059.43 | J24: =BS!BM8+BS!BM9 -> 277519.38
B25: Inventories | C25: =BS!AP10 -> 32640 | D25: =BS!AU10 -> 34405 | E25: =BS!AZ10 -> 33318 | F25: =BS!BE10 -> 37041.678 | G25: =BS!BJ10 -> 40252.571 | H25: =BS!BK10 -> 41057.622 | I25: =BS!BL10 -> 41878.774 | J25: =BS!BM10 -> 42716.35
B26: Accounts Receivable, Net, & Other | C26: =BS!AP11 -> 32891 | D26: =BS!AU11 -> 42360 | E26: =BS!AZ11 -> 52253 | F26: =BS!BE11 -> 62142.801 | G26: =BS!BJ11 -> 73904.421 | H26: =BS!BK11 -> 87892.135 | I26: =BS!BL11 -> 104527.27 | J26: =BS!BM11 -> 124310.9
B27: PP&E | C27: =BS!AP14 -> 160281 | D27: =BS!AU14 -> 186715 | E27: =BS!AZ14 -> 204177 | F27: =BS!BE14 -> 239987.74 | G27: =BS!BJ14 -> 260543.15 | H27: =BS!BK14 -> 269876.33 | I27: =BS!BL14 -> 275866.86 | J27: =BS!BM14 -> 277808.54
B28: Operating Leases | C28: =BS!AP15 -> 56082 | D28: =BS!AU15 -> 66123 | E28: =BS!AZ15 -> 72513 | F28: =BS!BE15 -> 78425.088 | G28: =BS!BJ15 -> 84819.196 | H28: =BS!BK15 -> 91734.625 | I28: =BS!BL15 -> 99213.879 | J28: =BS!BM15 -> 107302.93
B29: Goodwill | C29: =BS!AP16 -> 15371 | D29: =BS!AU16 -> 20288 | E29: =BS!AZ16 -> 22789 | F29: =BS!BE16 -> 22910 | G29: =BS!BJ16 -> 22943.778 | H29: =BS!BK16 -> 22940.963 | I29: =BS!BL16 -> 22942.84 | J29: =BS!BM16 -> 22942.527
B30: Other Assets | C30: =BS!AP17 -> 27235 | D30: =BS!AU17 -> 42758 | E30: =BS!AZ17 -> 56024 | F30: =BS!BE17 -> 74101.152 | G30: =BS!BJ17 -> 80026.035 | H30: =BS!BK17 -> 86424.652 | I30: =BS!BL17 -> 93334.882 | J30: =BS!BM17 -> 100797.63
B31: Total Assets | C31: =SUM(C24:C30) -> 420549 | D31: =SUM(D24:D30) -> 462675 | E31: =SUM(E24:E30) -> 527854 | F31: =SUM(F24:F30) -> 613815.42 | G31: =SUM(G24:G30) -> 697284.35 | H31: =SUM(H24:H30) -> 778845.93 | I31: =SUM(I24:I30) -> 862823.93 | J31: =SUM(J24:J30) -> 953398.25
B33: Accounts Payable | C33: =BS!AP22 -> 78664 | D33: =BS!AU22 -> 79600 | E33: =BS!AZ22 -> 84981 | F33: =BS!BE22 -> 87415.634 | G33: =BS!BJ22 -> 89850.267 | H33: =BS!BK22 -> 92284.901 | I33: =BS!BL22 -> 94719.535 | J33: =BS!BM22 -> 97154.168
B34: Accrued Expenses & Other | C34: =BS!AP23 -> 51775 | D34: =BS!AU23 -> 62566 | E34: =BS!AZ23 -> 64709 | F34: =BS!BE23 -> 66499 | G34: =BS!BJ23 -> 68289 | H34: =BS!BK23 -> 70079 | I34: =BS!BL23 -> 71869 | J34: =BS!BM23 -> 73659
B35: Unearned Revenue | C35: =BS!AP24 -> 11827 | D35: =BS!AU24 -> 13227 | E35: =BS!AZ24 -> 15227 | F35: =BS!BE24 -> 17134 | G35: =BS!BJ24 -> 19041 | H35: =BS!BK24 -> 20948 | I35: =BS!BL24 -> 22855 | J35: =BS!BM24 -> 24762
B36: Long-Term Lease Liabilities | C36: =BS!AP27 -> 67651 | D36: =BS!AU27 -> 72968 | E36: =BS!AZ27 -> 77297 | F36: =BS!BE27 -> 81208 | G36: =BS!BJ27 -> 85119 | H36: =BS!BK27 -> 89030 | I36: =BS!BL27 -> 92941 | J36: =BS!BM27 -> 96852
B37: Long-Term Debt | C37: =BS!AP28 -> 48744 | D37: =BS!AU28 -> 67150 | E37: =BS!AZ28 -> 58314 | F37: =BS!BE28 -> 56954.6 | G37: =BS!BJ28 -> 66019.33 | H37: =BS!BK28 -> 68502.542 | I37: =BS!BL28 -> 71079.157 | J37: =BS!BM28 -> 73752.686
B38: Other Long-Term Liabilities | C38: =BS!AP29 -> 23643 | D38: =BS!AU29 -> 21121 | E38: =BS!AZ29 -> 25451 | F38: =BS!BE29 -> 33050 | G38: =BS!BJ29 -> 40649 | H38: =BS!BK29 -> 48248 | I38: =BS!BL29 -> 55847 | J38: =BS!BM29 -> 63446
B39: Total Liabilities | C39: =SUM(C33:C38) -> 282304 | D39: =SUM(D33:D38) -> 316632 | E39: =SUM(E33:E38) -> 325979 | F39: =SUM(F33:F38) -> 342261.23 | G39: =SUM(G33:G38) -> 368967.6 | H39: =SUM(H33:H38) -> 389092.44 | I39: =SUM(I33:I38) -> 409310.69 | J39: =SUM(J33:J38) -> 429625.85
B41: Shareholder's Equity | C41: =BS!AP40 -> 138245 | D41: =BS!AU40 -> 146043 | E41: =BS!AZ40 -> 201875 | F41: =BS!BE40 -> 271554.19 | G41: =BS!BJ40 -> 328316.75 | H41: =BS!BK40 -> 389753.49 | I41: =BS!BL40 -> 453513.24 | J41: =BS!BM40 -> 523772.4
B42: Total Equity | C42: =C41 -> 138245 | D42: =D41 -> 146043 | E42: =E41 -> 201875 | F42: =F41 -> 271554.19 | G42: =G41 -> 328316.75 | H42: =H41 -> 389753.49 | I42: =I41 -> 453513.24 | J42: =J41 -> 523772.4
F44: Forecast
B45: Statement of Cash Flows | C45: 2021 | D45: 2022 | E45: 2023 | F45: 2024E | G45: 2025E | H45: 2026E | I45: 2027E | J45: 2028E
B47: Cash Flow from Operations (CFO) | C47: =CF!AP20 -> 46327 | D47: =CF!AU20 -> 46752 | E47: =CF!AZ20 -> 84946 | F47: =CF!BE20 -> 101506.73 | G47: =CF!BJ20 -> 121557.9 | H47: =CF!BK20 -> 142658.14 | I47: =CF!BL20 -> 151772.96 | J47: =CF!BM20 -> 165747.83
B48: Cash Flow from Investing | C48: =CF!AP27 -> -58154 | D48: =CF!AU27 -> -37601 | E48: =CF!AZ27 -> -49833 | F48: =CF!BE27 -> -71440.031 | G48: =CF!BJ27 -> -81398.931 | H48: =CF!BK27 -> -88985.561 | I48: =CF!BL27 -> -97419.158 | J48: =CF!BM27 -> -106806.23
B49: Cash Flow from Financing | C49: =CF!AP36 -> 6291 | D49: =CF!AU36 -> 9718 | E49: =CF!AZ36 -> -15879 | F49: =CF!BE36 -> -11987.286 | G49: =CF!BJ36 -> -13186.014 | H49: =CF!BK36 -> -14504.616 | I49: =CF!BL36 -> -15955.077 | J49: =CF!BM36 -> -17550.585
B50: Foreign Exchange Impact | C50: =CF!AP38 -> -364 | D50: =CF!AU38 -> -1093 | E50: =CF!AZ38 -> 403 | F50: =CF!BE38 -> -68 | G50: =CF!BJ38 -> 0 | H50: =CF!BK38 -> 0 | I50: =CF!BL38 -> 0 | J50: =CF!BM38 -> 0
B52: Cash Balance, Beginning of Period | C52: =CF!AP40 -> 42377 | D52: =C54 -> 36477 | E52: =D54 -> 54253 | F52: =E54 -> 73890 | G52: =F54 -> 91901.414 | H52: =G54 -> 118874.37 | I52: =H54 -> 158042.34 | J52: =I54 -> 196441.06
B53: Change in Cash | C53: =SUM(C47:C50) -> -5900 | D53: =SUM(D47:D50) -> 17776 | E53: =SUM(E47:E50) -> 19637 | F53: =SUM(F47:F50) -> 18011.414 | G53: =SUM(G47:G50) -> 26972.955 | H53: =SUM(H47:H50) -> 39167.967 | I53: =SUM(I47:I50) -> 38398.725 | J53: =SUM(J47:J50) -> 41391.016
B54: Cash Balance, Ending of Period | C54: =C52+C53 -> 36477 | D54: =D52+D53 -> 54253 | E54: =E52+E53 -> 73890 | F54: =F52+F53 -> 91901.414 | G54: =G52+G53 -> 118874.37 | H54: =H52+H53 -> 158042.34 | I54: =I52+I53 -> 196441.06 | J54: =J52+J53 -> 237832.08

Sheet IS
A1: Amazon.com Inc. (AMZN)
A2: Income Statement
A3: In millions except per share data
BD5: Estimates | BE5: Estimates | BF5: Estimates | BG5: Estimates | BH5: Estimates | BI5: Estimates | BJ5: Estimates | BK5: Estimates | BL5: Estimates | BM5: Estimates
E6: 2008 | F6: 2009 | G6: 2010 | H6: 2011 | I6: 2012 | J6: 2013 | K6: 2014 | L6: 2015 | M6: 42460 | N6: 42551 | O6: 42643 | P6: 42735 | Q6: 2016 | R6: 42825 | S6: 42916 | T6: 43008 | U6: 43100 | V6: 2017 | W6: 43190 | X6: 43281 | Y6: 43373 | Z6: 43465 | AA6: 2018 | AB6: 43555 | AC6: 43646 | AD6: 43738 | AE6: 43830 | AF6: 2019 | AG6: 43921 | AH6: 44012 | AI6: 44104 | AJ6: 44196 | AK6: 2020 | AL6: 44286 | AM6: 44377 | AN6: 44469 | AO6: 44561 | AP6: 2021 | AQ6: 44651 | AR6: 44742 | AS6: 44834 | AT6: 44926 | AU6: 2022 | AV6: 45016 | AW6: 45107 | AX6: 45199 | AY6: 45291 | AZ6: 2023 | BA6: 45382 | BB6: 45473 | BC6: 45565 | BD6: 45657 | BE6: 2024 | BF6: 45747 | BG6: 45838 | BH6: 45930 | BI6: 46022 | BJ6: 2025 | BK6: 2026 | BL6: 2027 | BM6: 2028
A8: Online Stores | K8: 68513 | L8: 76863 | M8: 19916 | N8: 20378 | O8: 21590 | P8: 29548 | Q8: =SUM(M8:P8) -> 91432 | R8: 22826 | S8: 23754 | T8: 26392 | U8: 35383 | V8: =SUM(R8:U8) -> 108355 | W8: 26939 | X8: 27165 | Y8: 29061 | Z8: 39822 | AA8: =SUM(W8:Z8) -> 122987 | AB8: 29498 | AC8: 31053 | AD8: 35039 | AE8: 45657 | AF8: =SUM(AB8:AE8) -> 141247 | AG8: 36652 | AH8: 45896 | AI8: 48350 | AJ8: 66451 | AK8: =SUM(AG8:AJ8) -> 197349 | AL8: 52901 | AM8: 53157 | AN8: 49942 | AO8: 66075 | AP8: =SUM(AL8:AO8) -> 222075 | AQ8: 51129 | AR8: 50855 | AS8: 53489 | AT8: 64531 | AU8: =SUM(AQ8:AT8) -> 220004 | AV8: 51096 | AW8: 52966 | AX8: 57267 | AY8: 70543 | AZ8: =SUM(AV8:AY8) -> 231872 | BA8: 54670 | BB8: 55392 | BC8: 61411 | BD8: =AY8*(1+'Assumptions + Estimates'!J11) -> 74112.673 | BE8: =SUM(BA8:BD8) -> 245585.67 | BF8: =BA8*(1+'Assumptions + Estimates'!K11) -> 57403.5 | BG8: =BB8*(1+'Assumptions + Estimates'!L11) -> 58161.6 | BH8: =BC8*(1+'Assumptions + Estimates'!M11) -> 64481.55 | BI8: =BD8*(1+'Assumptions + Estimates'!N11) -> 77818.306 | BJ8: =SUM(BF8:BI8) -> 257864.96 | BK8: =BJ8*(1+'Assumptions + Estimates'!P11) -> 270758.2 | BL8: =BK8*(1+'Assumptions + Estimates'!Q11) -> 284296.11 | BM8: =BL8*(1+'Assumptions + Estimates'!R11) -> 298510.92
A9: Physical Stores | K9: 0 | L9: 0 | M9: 0 | N9: 0 | O9: 0 | P9: 0 | Q9: =SUM(M9:P9) -> 0 | R9: 0 | S9: 0 | T9: 1276 | U9: 4522 | V9: =SUM(R9:U9) -> 5798 | W9: 4263 | X9: 4312 | Y9: 4248 | Z9: 4401 | AA9: =SUM(W9:Z9) -> 17224 | AB9: 4307 | AC9: 4330 | AD9: 4192 | AE9: 4363 | AF9: =SUM(AB9:AE9) -> 17192 | AG9: 4640 | AH9: 3774 | AI9: 3788 | AJ9: 4022 | AK9: =SUM(AG9:AJ9) -> 16224 | AL9: 3920 | AM9: 4198 | AN9: 4269 | AO9: 4688 | AP9: =SUM(AL9:AO9) -> 17075 | AQ9: 4591 | AR9: 4721 | AS9: 4694 | AT9: 4957 | AU9: =SUM(AQ9:AT9) -> 18963 | AV9: 4895 | AW9: 5024 | AX9: 4959 | AY9: 5152 | AZ9: =SUM(AV9:AY9) -> 20030 | BA9: 5202 | BB9: 5206 | BC9: 5228 | BD9: =AY9*(1+'Assumptions + Estimates'!J12) -> 5410.0939 | BE9: =SUM(BA9:BD9) -> 21046.094 | BF9: =BA9*(1+'Assumptions + Estimates'!K12) -> 5462.1 | BG9: =BB9*(1+'Assumptions + Estimates'!L12) -> 5466.3 | BH9: =BC9*(1+'Assumptions + Estimates'!M12) -> 5489.4 | BI9: =BD9*(1+'Assumptions + Estimates'!N12) -> 5680.5985 | BJ9: =SUM(BF9:BI9) -> 22098.399 | BK9: =BJ9*(1+'Assumptions + Estimates'!P12) -> 23203.318 | BL9: =BK9*(1+'Assumptions + Estimates'!Q12) -> 24363.484 | BM9: =BL9*(1+'Assumptions + Estimates'!R12) -> 25581.659
A10: Third-Party Seller Services | K10: 11747 | L10: 16086 | M10: 4801 | N10: 5083 | O10: 5652 | P10: 7456 | Q10: =SUM(M10:P10) -> 22992 | R10: 6438 | S10: 6991 | T10: 7928 | U10: 10523 | V10: =SUM(R10:U10) -> 31880 | W10: 9265 | X10: 9702 | Y10: 10395 | Z10: 13383 | AA10: =SUM(W10:Z10) -> 42745 | AB10: 11141 | AC10: 11962 | AD10: 13212 | AE10: 17446 | AF10: =SUM(AB10:AE10) -> 53761 | AG10: 14479 | AH10: 18195 | AI10: 20436 | AJ10: 27327 | AK10: =SUM(AG10:AJ10) -> 80437 | AL10: 23709 | AM10: 25085 | AN10: 24252 | AO10: 30320 | AP10: =SUM(AL10:AO10) -> 103366 | AQ10: 25335 | AR10: 27376 | AS10: 28666 | AT10: 36339 | AU10: =SUM(AQ10:AT10) -> 117716 | AV10: 29820 | AW10: 32332 | AX10: 34342 | AY10: 43559 | AZ10: =SUM(AV10:AY10) -> 140053 | BA10: 34596 | BB10: 36201 | BC10: 37864 | BD10: =AY10*(1+'Assumptions + Estimates'!J13) -> 49126.331 | BE10: =SUM(BA10:BD10) -> 157787.33 | BF10: =BA10*(1+'Assumptions + Estimates'!K13) -> 38055.6 | BG10: =BB10*(1+'Assumptions + Estimates'!L13) -> 39821.1 | BH10: =BC10*(1+'Assumptions + Estimates'!M13) -> 41650.4 | BI10: =BD10*(1+'Assumptions + Estimates'!N13) -> 54038.964 | BJ10: =SUM(BF10:BI10) -> 173566.06 | BK10: =BJ10*(1+'Assumptions + Estimates'!P13) -> 190922.67 | BL10: =BK10*(1+'Assumptions + Estimates'!Q13) -> 210014.94 | BM10: =BL10*(1+'Assumptions + Estimates'!R13) -> 231016.43
A11: Subscription Services | K11: 2762 | L11: 4467 | M11: 1300 | N11: 1431 | O11: 1532 | P11: 2130 | Q11: =SUM(M11:P11) -> 6393 | R11: 1939 | S11: 2165 | T11: 2441 | U11: 3177 | V11: =SUM(R11:U11) -> 9722 | W11: 3102 | X11: 3408 | Y11: 3698 | Z11: 3959 | AA11: =SUM(W11:Z11) -> 14167 | AB11: 4342 | AC11: 4676 | AD11: 4957 | AE11: 5235 | AF11: =SUM(AB11:AE11) -> 19210 | AG11: 5556 | AH11: 6018 | AI11: 6572 | AJ11: 7061 | AK11: =SUM(AG11:AJ11) -> 25207 | AL11: 7580 | AM11: 7917 | AN11: 8148 | AO11: 8123 | AP11: =SUM(AL11:AO11) -> 31768 | AQ11: 8410 | AR11: 8716 | AS11: 8903 | AT11: 9189 | AU11: =SUM(AQ11:AT11) -> 35218 | AV11: 9657 | AW11: 9894 | AX11: 10170 | AY11: 10488 | AZ11: =SUM(AV11:AY11) -> 40209 | BA11: 10722 | BB11: 10866 | BC11: 11278 | BD11: =AY11*(1+'Assumptions + Estimates'!J14) -> 11697.622 | BE11: =SUM(BA11:BD11) -> 44563.622 | BF11: =BA11*(1+'Assumptions + Estimates'!K14) -> 11794.2 | BG11: =BB11*(1+'Assumptions + Estimates'!L14) -> 11952.6 | BH11: =BC11*(1+'Assumptions + Estimates'!M14) -> 12405.8 | BI11: =BD11*(1+'Assumptions + Estimates'!N14) -> 12867.384 | BJ11: =SUM(BF11:BI11) -> 49019.984 | BK11: =BJ11*(1+'Assumptions + Estimates'!P14) -> 53921.982 | BL11: =BK11*(1+'Assumptions + Estimates'!Q14) -> 59314.181 | BM11: =BL11*(1+'Assumptions + Estimates'!R14) -> 65245.599
A12: Advertising Services | Q12: =SUM(M12:P12) -> 0 | V12: =SUM(R12:U12) -> 0 | AA12: =SUM(W12:Z12) -> 0 | AF12: =SUM(AB12:AE12) -> 0 | AI12: 4982 | AJ12: 7350 | AK12: =SUM(AG12:AJ12) -> 12332 | AL12: 6381 | AM12: 7451 | AN12: 7612 | AO12: 9716 | AP12: =SUM(AL12:AO12) -> 31160 | AQ12: 7877 | AR12: 8757 | AS12: 9548 | AT12: 11557 | AU12: =SUM(AQ12:AT12) -> 37739 | AV12: 9509 | AW12: 10683 | AX12: 12060 | AY12: 14654 | AZ12: =SUM(AV12:AY12) -> 46906 | BA12: 11824 | BB12: 12771 | BC12: 14331 | BD12: =AY12*(1+'Assumptions + Estimates'!J15) -> 17458.636 | BE12: =SUM(BA12:BD12) -> 56384.636 | BF12: =BA12*(1+'Assumptions + Estimates'!K15) -> 13952.32 | BG12: =BB12*(1+'Assumptions + Estimates'!L15) -> 15069.78 | BH12: =BC12*(1+'Assumptions + Estimates'!M15) -> 16910.58 | BI12: =BD12*(1+'Assumptions + Estimates'!N15) -> 20601.19 | BJ12: =SUM(BF12:BI12) -> 66533.87 | BK12: =BJ12*(1+'Assumptions + Estimates'!P15) -> 76513.95 | BL12: =BK12*(1+'Assumptions + Estimates'!Q15) -> 87991.043 | BM12: =BL12*(1+'Assumptions + Estimates'!R15) -> 101189.7
A13: AWS | K13: 4644 | L13: 7880 | M13: 2566 | N13: 2886 | O13: 3231 | P13: 3536 | Q13: =SUM(M13:P13) -> 12219 | R13: 3661 | S13: 4100 | T13: 4584 | U13: 5113 | V13: =SUM(R13:U13) -> 17458 | W13: 5442 | X13: 6105 | Y13: 6679 | Z13: 7430 | AA13: =SUM(W13:Z13) -> 25656 | AB13: 7696 | AC13: 8381 | AD13: 8995 | AE13: 9954 | AF13: =SUM(AB13:AE13) -> 35026 | AG13: 10219 | AH13: 10808 | AI13: 11601 | AJ13: 12742 | AK13: =SUM(AG13:AJ13) -> 45370 | AL13: 13503 | AM13: 14809 | AN13: 16110 | AO13: 17780 | AP13: =SUM(AL13:AO13) -> 62202 | AQ13: 18441 | AR13: 19739 | AS13: 20538 | AT13: 21378 | AU13: =SUM(AQ13:AT13) -> 80096 | AV13: 21354 | AW13: 22140 | AX13: 23059 | AY13: 24204 | AZ13: =SUM(AV13:AY13) -> 90757 | BA13: 25037 | BB13: 26281 | BC13: 27452 | BD13: =AY13*(1+'Assumptions + Estimates'!J16) -> 28641.964 | BE13: =SUM(BA13:BD13) -> 107411.96 | BF13: =BA13*(1+'Assumptions + Estimates'!K16) -> 29543.66 | BG13: =BB13*(1+'Assumptions + Estimates'!L16) -> 31011.58 | BH13: =BC13*(1+'Assumptions + Estimates'!M16) -> 32393.36 | BI13: =BD13*(1+'Assumptions + Estimates'!N16) -> 33797.518 | BJ13: =SUM(BF13:BI13) -> 126746.12 | BK13: =BJ13*(1+'Assumptions + Estimates'!P16) -> 145758.04 | BL13: =BK13*(1+'Assumptions + Estimates'!Q16) -> 167621.74 | BM13: =BL13*(1+'Assumptions + Estimates'!R16) -> 192765
A14: Other | K14: 1322 | L14: 1710 | M14: 545 | N14: 626 | O14: 709 | P14: 1071 | Q14: =SUM(M14:P14) -> 2951 | R14: 850 | S14: 945 | T14: 1123 | U14: 1735 | V14: =SUM(R14:U14) -> 4653 | W14: 2031 | X14: 2194 | Y14: 2495 | Z14: 3388 | AA14: =SUM(W14:Z14) -> 10108 | AB14: 2716 | AC14: 3002 | AD14: 3586 | AE14: 4782 | AF14: =SUM(AB14:AE14) -> 14086 | AG14: 3906 | AH14: 4221 | AI14: 416 | AJ14: 602 | AK14: =SUM(AG14:AJ14) -> 9145 | AL14: 524 | AM14: 463 | AN14: 479 | AO14: 710 | AP14: =SUM(AL14:AO14) -> 2176 | AQ14: 661 | AR14: 1070 | AS14: 1263 | AT14: 1253 | AU14: =SUM(AQ14:AT14) -> 4247 | AV14: 1027 | AW14: 1344 | AX14: 1226 | AY14: 1361 | AZ14: =SUM(AV14:AY14) -> 4958 | BA14: 1262 | BB14: 1260 | BC14: 1313 | BD14: =AY14*(1+'Assumptions + Estimates'!J17) -> 1429.05 | BE14: =SUM(BA14:BD14) -> 5264.05 | BF14: =BA14*(1+'Assumptions + Estimates'!K17) -> 1325.1 | BG14: =BB14*(1+'Assumptions + Estimates'!L17) -> 1323 | BH14: =BC14*(1+'Assumptions + Estimates'!M17) -> 1378.65 | BI14: =BD14*(1+'Assumptions + Estimates'!N17) -> 1500.5025 | BJ14: =SUM(BF14:BI14) -> 5527.2525 | BK14: =BJ14*(1+'Assumptions + Estimates'!P17) -> 5803.6151 | BL14: =BK14*(1+'Assumptions + Estimates'!Q17) -> 6093.7959 | BM14: =BL14*(1+'Assumptions + Estimates'!R17) -> 6398.4857
A15: Total Revenue | E15: 19166 | F15: 24509 | G15: 34204 | H15: 48077 | I15: 61093 | J15: 74452 | K15: =SUM(K8:K14) -> 88988 | L15: =SUM(L8:L14) -> 107006 | M15: =SUM(M8:M14) -> 29128 | N15: =SUM(N8:N14) -> 30404 | O15: =SUM(O8:O14) -> 32714 | P15: =SUM(P8:P14) -> 43741 | Q15: =SUM(Q8:Q14) -> 135987 | R15: =SUM(R8:R14) -> 35714 | ... BM15: =SUM(BM8:BM14) -> 920707.8
A16: Total Cost of Goods Sold | E16: 14896 | F16: 18978 | G16: 26561 | H16: 37288 | I16: 45971 | J16: 54181 | K16: 62752 | L16: 71651 | M16: 18866 | N16: 19180 | O16: 21260 | P16: 28958 | Q16: 88264 | R16: 22440 | S16: 23451 | T16: 27549 | U16: 38494 | V16: 111934 | W16: 30735 | X16: 30632 | Y16: 33003 | Z16: 44786 | AA16: 139156 | AB16: 33920 | AC16: 36337 | AD16: 41302 | AE16: 53977 | AF16: 165536 | AG16: 44257 | AH16: 52660 | AI16: 57106 | AJ16: 79284 | AK16: 233307 | AL16: 62403 | AM16: 64176 | AN16: 62930 | AO16: 82835 | AP16: 272344 | AQ16: 66499 | AR16: 66424 | AS16: 70268 | AT16: 85640 | AU16: 288831 | AV16: 67791 | AW16: 69373 | AX16: 75022 | AY16: 92553 | AZ16: 304739 | BA16: 72633 | BB16: 73785 | BC16: 80977 | BD16: =BD$15*'Assumptions + Estimates'!J23 -> 99574.475 | BE16: =SUM(BA16:BD16) -> 326969.48 | BF16: =BF$15*'Assumptions + Estimates'!$O23 -> 81918.97 | BG16: =BG$15*'Assumptions + Estimates'!$O23 -> 84659.099 | BH16: =BH$15*'Assumptions + Estimates'!$O23 -> 90849.065 | BI16: =BI$15*'Assumptions + Estimates'!$O23 -> 107278.32 | BJ16: =SUM(BF16:BI16) -> 364705.45 | BK16: =BK$15*'Assumptions + Estimates'!P23 -> 391109.71 | BL16: =BL$15*'Assumptions + Estimates'!Q23 -> 419847.65 | BM16: =BM$15*'Assumptions + Estimates'!R23 -> 451146.82
A17: Gross Profit (GAAP) | E17: =E15-E16 -> 4270 | F17: =F15-F16 -> 5531 | G17: =G15-G16 -> 7643 | H17: =H15-H16 -> 10789 | I17: =I15-I16 -> 15122 | J17: =J15-J16 -> 20271 | K17: =K15-K16 -> 26236 | L17: =L15-L16 -> 35355 | ... BM17: =BM15-BM16 -> 469560.98
A18: Fulfillment | E18: 1658 | F18: 2052 | G18: 2898 | H18: 4576 | I18: 6419 | J18: 8585 | K18: 10766 | L18: 13410 | M18: 3687 | N18: 3878 | O18: 4335 | P18: 5719 | Q18: 17619 | R18: 4697 | S18: 5158 | T18: 6420 | U18: 8974 | V18: 25249 | W18: 7792 | X18: 7932 | Y18: 8275 | Z18: 10028 | AA18: 34027 | AB18: 8601 | AC18: 9271 | AD18: 10167 | AE18: 12192 | AF18: 40231 | AG18: 11531 | AH18: 13806 | AI18: 14705 | AJ18: 18474 | AK18: 58516 | AL18: 16530 | AM18: 17638 | AN18: 18498 | AO18: 22445 | AP18: 75111 | AQ18: 20271 | AR18: 20342 | AS18: 20583 | AT18: 23103 | AU18: 84299 | AV18: 20905 | AW18: 21305 | AX18: 22314 | AY18: 26095 | AZ18: 90619 | BA18: 22317 | BB18: 23566 | BC18: 24660 | BD18: =BD$15*'Assumptions + Estimates'!J25 -> 28932.961 | BE18: =SUM(BA18:BD18) -> 99475.961 | BF18: =BF$15*'Assumptions + Estimates'!$O25 -> 24260.618 | BG18: =BG$15*'Assumptions + Estimates'!$O25 -> 25072.118 | BH18: =BH$15*'Assumptions + Estimates'!$O25 -> 26905.3 | BI18: =BI$15*'Assumptions + Estimates'!$O25 -> 31770.887 | BJ18: =SUM(BF18:BI18) -> 108008.92 | BK18: =BK$15*'Assumptions + Estimates'!P25 -> 115032.27 | BL18: =BL$15*'Assumptions + Estimates'!Q25 -> 125954.29 | BM18: =BM$15*'Assumptions + Estimates'!R25 -> 138106.17
A19: Technology and Content | E19: 482 | F19: 680 | G19: 1029 | H19: 1630 | I19: 2408 | J19: 3133 | K19: 4332 | L19: 5254 | M19: 1436 | N19: 1546 | O19: 1738 | P19: 2513 | Q19: 7233 | R19: 1920 | S19: 2229 | T19: 2479 | U19: 3440 | V19: 10068 | W19: 2699 | X19: 2901 | Y19: 3303 | Z19: 7669 | AA19: 16572 | AB19: 7927 | AC19: 9065 | AD19: 9200 | AE19: 9740 | AF19: 35932 | AG19: 9325 | AH19: 10388 | AI19: 10976 | AJ19: 12049 | AK19: 42738 | AL19: 12488 | AM19: 13871 | AN19: 14380 | AO19: 15313 | AP19: 56052 | AQ19: 14842 | AR19: 18072 | AS19: 19485 | AT19: 20814 | AU19: 73213 | AV19: 20450 | AW19: 21931 | AX19: 21203 | AY19: 22038 | AZ19: 85622 | BA19: 20424 | BB19: 22304 | BC19: 22245 | BD19: =BD$15*'Assumptions + Estimates'!J26 -> 24423.928 | BE19: =SUM(BA19:BD19) -> 89396.928 | BF19: =BF$15*'Assumptions + Estimates'!$O26 -> 20479.742 | BG19: =BG$15*'Assumptions + Estimates'!$O26 -> 21164.775 | BH19: =BH$15*'Assumptions + Estimates'!$O26 -> 22712.266 | BI19: =BI$15*'Assumptions + Estimates'!$O26 -> 26819.58 | BJ19: =SUM(BF19:BI19) -> 91176.364 | BK19: =BK$15*'Assumptions + Estimates'!P26 -> 99694.631 | BL19: =BL$15*'Assumptions + Estimates'!Q26 -> 117557.34 | BM19: =BM$15*'Assumptions + Estimates'!R26 -> 138106.17
A20: Marketing | E20: 1033 | F20: 1240 | G20: 1734 | H20: 2909 | I20: 4564 | J20: 6565 | K20: 9275 | L20: 12540 | M20: 3526 | N20: 3880 | O20: 4135 | P20: 4545 | Q20: 16086 | R20: 4813 | S20: 5549 | T20: 5944 | U20: 6314 | V20: 22620 | W20: 6759 | X20: 7247 | Y20: 7162 | Z20: 4911 | AA20: 26079 | AB20: 3664 | AC20: 4291 | AD20: 4752 | AE20: 6172 | AF20: 18879 | AG20: 4828 | AH20: 4345 | AI20: 5434 | AJ20: 7403 | AK20: 22010 | AL20: 6207 | AM20: 7524 | AN20: 8010 | AO20: 10810 | AP20: 32551 | AQ20: 8320 | AR20: 10086 | AS20: 11014 | AT20: 12818 | AU20: 42238 | AV20: 10172 | AW20: 10745 | AX20: 10551 | AY20: 12902 | AZ20: 44370 | BA20: 9662 | BB20: 10512 | BC20: 10609 | BD20: =BD$15*'Assumptions + Estimates'!J27 -> 13151.346 | BE20: =SUM(BA20:BD20) -> 43934.346 | BF20: =BF$15*'Assumptions + Estimates'!$O27 -> 11027.554 | BG20: =BG$15*'Assumptions + Estimates'!$O27 -> 11396.417 | BH20: =BH$15*'Assumptions + Estimates'!$O27 -> 12229.682 | BI20: =BI$15*'Assumptions + Estimates'!$O27 -> 14441.312 | BJ20: =SUM(BF20:BI20) -> 49094.965 | BK20: =BK$15*'Assumptions + Estimates'!P27 -> 61350.542 | BL20: =BL$15*'Assumptions + Estimates'!Q27 -> 67175.624 | BM20: =BM$15*'Assumptions + Estimates'!R27 -> 73656.624
A21: General & Administrative | E21: 279 | F21: 328 | G21: 470 | H21: 658 | I21: 896 | J21: 1129 | K21: 1552 | L21: 1747 | M21: 497 | N21: 580 | O21: 639 | P21: 717 | Q21: 2433 | R21: 795 | S21: 874 | T21: 960 | U21: 1044 | V21: 3673 | W21: 1067 | X21: 1111 | Y21: 1041 | Z21: 1117 | AA21: 4336 | AB21: 1173 | AC21: 1270 | AD21: 1348 | AE21: 1412 | AF21: 5203 | AG21: 1452 | AH21: 1580 | AI21: 1668 | AJ21: 1968 | AK21: 6668 | AL21: 1987 | AM21: 2158 | AN21: 2153 | AO21: 2525 | AP21: 8823 | AQ21: 2594 | AR21: 2903 | AS21: 3061 | AT21: 3333 | AU21: 11891 | AV21: 3043 | AW21: 3202 | AX21: 2561 | AY21: 3010 | AZ21: 11816 | BA21: 2742 | BB21: 3041 | BC21: 2713 | BD21: =BD$15*'Assumptions + Estimates'!J28 -> 3757.5274 | BE21: =SUM(BA21:BD21) -> 12253.527 | BF21: =BF$15*'Assumptions + Estimates'!$O28 -> 3150.7296 | BG21: =BG$15*'Assumptions + Estimates'!$O28 -> 3256.1192 | BH21: =BH$15*'Assumptions + Estimates'!$O28 -> 3494.1948 | BI21: =BI$15*'Assumptions + Estimates'!$O28 -> 4126.0893 | BJ21: =SUM(BF21:BI21) -> 14027.133 | BK21: =BK$15*'Assumptions + Estimates'!P28 -> 19172.044 | BL21: =BL$15*'Assumptions + Estimates'!Q28 -> 25190.859 | BM21: =BM$15*'Assumptions + Estimates'!R28 -> 27621.234
A22: Other Operating Expenses (Income) | E22: -24 | F22: 102 | G22: 106 | H22: 154 | I22: 159 | J22: 114 | K22: 133 | L22: 171 | M22: 45 | N22: 55 | O22: 32 | P22: 34 | Q22: 166 | R22: 44 | S22: 66 | T22: 45 | U22: 60 | V22: 215 | W22: 63 | X22: 80 | Y22: 68 | Z22: 86 | AA22: 297 | AB22: -5 | AC22: 86 | AD22: 55 | AE22: 65 | AF22: 201 | AG22: 70 | AH22: 290 | AI22: 62 | AJ22: -496 | AK22: -74 | AL22: 38 | AM22: 11 | AN22: -11 | AO22: 24 | AP22: 62 | AQ22: 249 | AR22: 90 | AS22: 165 | AT22: 759 | AU22: 1263 | AV22: 223 | AW22: 146 | AX22: 244 | AY22: 154 | AZ22: 767 | BA22: 228 | BB22: 97 | BC22: 262 | BD22: =BD$15*'Assumptions + Estimates'!J29 -> 187.87637 | BE22: =SUM(BA22:BD22) -> 774.87637 | BF22: =BF$15*'Assumptions + Estimates'!$O29 -> 157.53648 | BG22: =BG$15*'Assumptions + Estimates'!$O29 -> 162.80596 | BH22: =BH$15*'Assumptions + Estimates'!$O29 -> 174.70974 | BI22: =BI$15*'Assumptions + Estimates'!$O29 -> 206.30446 | BJ22: =SUM(BF22:BI22) -> 701.35664 | BK22: =BK$15*'Assumptions + Estimates'!P29 -> 766.88178 | BL22: =BL$15*'Assumptions + Estimates'!Q29 -> 839.6953 | BM22: =BM$15*'Assumptions + Estimates'!R29 -> 920.7078
A23: Total Operating Expenses | E23: =SUM(E18:E22) -> 3428 | F23: =SUM(F18:F22) -> 4402 | G23: =SUM(G18:G22) -> 6237 | H23: =SUM(H18:H22) -> 9927 | I23: =SUM(I18:I22) -> 14446 | J23: =SUM(J18:J22) -> 19526 | K23: =SUM(K18:K22) -> 26058 | L23: =SUM(L18:L22) -> 33122 | ... BM23: =SUM(BM18:BM22) -> 378410.9
A24: Operating Profit (GAAP) | E24: =E17-E23 -> 842 | F24: =F17-F23 -> 1129 | G24: =G17-G23 -> 1406 | H24: =H17-H23 -> 862 | I24: =I17-I23 -> 676 | J24: =J17-J23 -> 745 | K24: =K17-K23 -> 178 | L24: =L17-L23 -> 2233 | ... BM24: =BM17-BM23 -> 91150.072
A25: Interest Income | E25: 83 | F25: 37 | G25: 51 | H25: 61 | I25: 40 | J25: 38 | K25: 39 | L25: 50 | M25: 21 | N25: 24 | O25: 26 | P25: 30 | Q25: 101 | R25: 39 | S25: 44 | T25: 54 | U25: 66 | V25: 203 | W25: 80 | X25: 94 | Y25: 117 | Z25: 150 | AA25: 441 | AB25: 183 | AC25: 215 | AD25: 224 | AE25: 211 | AF25: 833 | AG25: 202 | AH25: 135 | AI25: 118 | AJ25: 100 | AK25: 555 | AL25: 105 | AM25: 106 | AN25: 119 | AO25: 118 | AP25: 448 | AQ25: 108 | AR25: 159 | AS25: 277 | AT25: 445 | AU25: 989 | AV25: 611 | AW25: 661 | AX25: 776 | AY25: 901 | AZ25: 2949 | BA25: 993 | BB25: 1180 | BC25: 1256 | BD25: =BD$15*'Assumptions + Estimates'!J32 -> 939.38184 | BE25: =SUM(BA25:BD25) -> 4368.3818 | BF25: =BF$15*'Assumptions + Estimates'!$O32 -> 787.6824 | BG25: =BG$15*'Assumptions + Estimates'!$O32 -> 814.0298 | BH25: =BH$15*'Assumptions + Estimates'!$O32 -> 873.5487 | BI25: =BI$15*'Assumptions + Estimates'!$O32 -> 1031.5223 | BJ25: =SUM(BF25:BI25) -> 3506.7832 | BK25: =BK$15*'Assumptions + Estimates'!P32 -> 3834.4089 | BL25: =BL$15*'Assumptions + Estimates'!Q32 -> 4198.4765 | BM25: =BM$15*'Assumptions + Estimates'!R32 -> 4603.539
A26: Interest Expense | E26: -71 | F26: -34 | G26: -39 | H26: -65 | I26: -92 | J26: -141 | K26: -210 | L26: -459 | M26: -117 | N26: -116 | O26: -118 | P26: -133 | Q26: -484 | R26: -139 | S26: -143 | T26: -228 | U26: -339 | V26: -849 | W26: -330 | X26: -343 | Y26: -358 | Z26: -387 | AA26: -1418 | AB26: -366 | AC26: -383 | AD26: -396 | AE26: -455 | AF26: -1600 | AG26: -402 | AH26: -403 | AI26: -428 | AJ26: -414 | AK26: -1647 | AL26: -399 | AM26: -435 | AN26: -493 | AO26: -482 | AP26: -1809 | AQ26: -472 | AR26: -584 | AS26: -617 | AT26: -694 | AU26: -2367 | AV26: -823 | AW26: -840 | AX26: -806 | AY26: -713 | AZ26: -3182 | BA26: -644 | BB26: -589 | BC26: -603 | BD26: =BD$15*'Assumptions + Estimates'!J33 -> -1878.7637 | BE26: =SUM(BA26:BD26) -> -3714.7637 | BF26: =BF$15*'Assumptions + Estimates'!$O33 -> -1575.3648 | BG26: =BG$15*'Assumptions + Estimates'!$O33 -> -1628.0596 | BH26: =BH$15*'Assumptions + Estimates'!$O33 -> -1747.0974 | BI26: =BI$15*'Assumptions + Estimates'!$O33 -> -2063.0446 | BJ26: =SUM(BF26:BI26) -> -7013.5664 | BK26: =BK$15*'Assumptions + Estimates'!P33 -> -7668.8178 | BL26: =BL$15*'Assumptions + Estimates'!Q33 -> -8396.953 | BM26: =BM$15*'Assumptions + Estimates'!R33 -> -9207.078
A27: Other Income, Net | E27: 47 | F27: 29 | G27: 79 | H27: 76 | I27: -80 | J27: -136 | K27: -118 | L27: -256 | M27: 81 | N27: -14 | O27: 8 | P27: 14 | Q27: 89 | R27: 48 | S27: 137 | T27: 143 | U27: 18 | V27: 346 | W27: 239 | X27: -129 | Y27: -93 | Z27: -199 | AA27: -182 | AB27: 164 | AC27: -27 | AD27: -353 | AE27: 418 | AF27: 202 | AG27: -406 | AH27: 646 | AI27: 925 | AJ27: 1206 | AK27: 2371 | AL27: 1697 | AM27: 1261 | AN27: -163 | AO27: 11838 | AP27: 14633 | AQ27: -8570 | AR27: -5545 | AS27: 759 | AT27: -3450 | AU27: -16806 | AV27: -443 | AW27: 61 | AX27: 1031 | AY27: 289 | AZ27: 938 | BA27: -2673 | BB27: -18 | BC27: -27 | BD27: =BD$15*'Assumptions + Estimates'!J34 -> 375.75274 | BE27: =SUM(BA27:BD27) -> -2342.2473 | BF27: =BF$15*'Assumptions + Estimates'!$O34 -> 315.07296 | BG27: =BG$15*'Assumptions + Estimates'!$O34 -> 325.61192 | BH27: =BH$15*'Assumptions + Estimates'!$O34 -> 349.41948 | BI27: =BI$15*'Assumptions + Estimates'!$O34 -> 412.60893 | BJ27: =SUM(BF27:BI27) -> 1402.7133 | BK27: =BK$15*'Assumptions + Estimates'!P34 -> 1533.7636 | BL27: =BL$15*'Assumptions + Estimates'!Q34 -> 1679.3906 | BM27: =BM$15*'Assumptions + Estimates'!R34 -> 1841.4156
A28: Pre Tax Income | E28: =E24+E25+E26+E27 -> 901 | F28: =F24+F25+F26+F27 -> 1161 | G28: =G24+G25+G26+G27 -> 1497 | H28: =H24+H25+H26+H27 -> 934 | I28: =I24+I25+I26+I27 -> 544 | J28: =J24+J25+J26+J27 -> 506 | K28: =K24+K25+K26+K27 -> -111 | L28: =L24+L25+L26+L27 -> 1568 | ... BM28: =BM24+BM25+BM26+BM27 -> 88387.948
A29: Income Tax (Provision)/Benefit | E29: -247 | F29: -253 | G29: -352 | H29: -291 | I29: -428 | J29: -161 | K29: -167 | L29: -950 | M29: -475 | N29: -307 | O29: -229 | P29: -414 | Q29: -1425 | R29: -229 | S29: -467 | T29: -58 | U29: -16 | V29: -770 | W29: -287 | X29: -74 | Y29: -508 | Z29: -327 | AA29: -1196 | AB29: -836 | AC29: -257 | AD29: -494 | AE29: -786 | AF29: -2373 | AG29: -744 | AH29: -984 | AI29: -569 | AJ29: -566 | AK29: -2863 | AL29: -2156 | AM29: -868 | AN29: -1155 | AO29: -612 | AP29: -4791 | AQ29: 1422 | AR29: 637 | AS29: -69 | AT29: 1227 | AU29: =SUM(AQ29:AT29) -> 3217 | AV29: -948 | AW29: -804 | AX29: -2306 | AY29: -3062 | AZ29: =SUM(AV29:AY29) -> -7120 | BA29: -2467 | BB29: -1767 | BC29: -2706 | BD29: =IF(BD28>0,BD28*-'Assumptions + Estimates'!J39) -> -3629.7714 | BE29: =SUM(BA29:BD29) -> -10569.771 | BF29: =IF(BF28>0,BF28*-'Assumptions + Estimates'!$O39,0) -> -3374.4314 | BG29: =IF(BG28>0,BG28*-'Assumptions + Estimates'!$O39,0) -> -3487.3037 | BH29: =IF(BH28>0,BH28*-'Assumptions + Estimates'!$O39,0) -> -3742.2826 | BI29: =IF(BI28>0,BI28*-'Assumptions + Estimates'!$O39,0) -> -4419.0416 | BJ29: =SUM(BF29:BI29) -> -15023.059 | BK29: =IF(BK28>0,BK28*-'Assumptions + Estimates'!P39,0) -> -16265.562 | BL29: =IF(BL28>0,BL28*-'Assumptions + Estimates'!Q39,0) -> -16928.257 | BM29: =IF(BM28>0,BM28*-'Assumptions + Estimates'!R39,0) -> -18561.469
A30: Equity Income (Net of Tax) | E30: -9 | F30: -6 | G30: 7 | H30: -12 | I30: -155 | J30: -71 | K30: 37 | L30: -22 | M30: -68 | N30: -15 | O30: -10 | P30: -3 | Q30: -96 | R30: 0 | S30: -2 | T30: -2 | U30: 0 | V30: -4 | W30: 0 | X30: 3 | Y30: 1 | Z30: 4 | AA30: 8 | AB30: -4 | AC30: -7 | AD30: -4 | AE30: 1 | AF30: -14 | AG30: -104 | AH30: 6 | AI30: 91 | AJ30: 23 | AK30: 16 | AL30: -5 | AM30: 12 | AN30: -4 | AO30: 1 | AP30: 4 | AQ30: -1 | AR30: -12 | AS30: -3 | AT30: 13 | AU30: =SUM(AQ30:AT30) -> -3 | AV30: 1 | AW30: -9 | AX30: -4 | AY30: 0 | AZ30: =SUM(AV30:AY30) -> -12 | BA30: -85 | BB30: 7 | BC30: -3 | BD30: 0 | BE30: =SUM(BA30:BD30) -> -81 | BF30: 0 | BG30: 0 | BH30: 0 | BI30: 0 | BJ30: =SUM(BF30:BI30) -> 0 | BK30: 0 | BL30: 0 | BM30: 0
A31: Net Income | E31: =E28+E29+E30 -> 645 | F31: =F28+F29+F30 -> 902 | G31: =G28+G29+G30 -> 1152 | H31: =H28+H29+H30 -> 631 | I31: =I28+I29+I30 -> -39 | J31: =J28+J29+J30 -> 274 | K31: =K28+K29+K30 -> -241 | L31: =L28+L29+L30 -> 596 | ... BM31: =BM28+BM29+BM30 -> 69826.479
A32: EPS Basic | E32: =ROUND(E31/E35,2) -> 0.08 | F32: =ROUND(F31/F35,2) -> 0.1 | G32: =ROUND(G31/G35,2) -> 0.13 | H32: =ROUND(H31/H35,2) -> 0.07 | I32: =ROUND(I31/I35,2) -> 0 | J32: =ROUND(J31/J35,2) -> 0.03 | K32: =ROUND(K31/K35,2) -> -0.03 | L32: =ROUND(L31/L35,2) -> 0.06 | Q32: =ROUND(Q31/Q35,2) -> 0.25 | V32: =ROUND(V31/V35,2) -> 0.32 | AA32: =ROUND(AA31/AA35,2) -> 1.03 | AF32: =ROUND(AF31/AF35,2) -> 1.17 | AK32: =ROUND(AK31/AK35,2) -> 2.13 | AP32: =ROUND(AP31/AP35,2) -> 3.3 | AU32: =ROUND(AU31/AU35,2) -> -0.27 | AZ32: =ROUND(AZ31/AZ35,2) -> 2.95 | BE32: =ROUND(BE31/BE35,2) -> 5.02 | BJ32: =ROUND(BJ31/BJ35,2) -> 5.31 | BK32: =ROUND(BK31/BK35,2) -> 5.68 | BL32: =ROUND(BL31/BL35,2) -> 5.85 | BM32: =ROUND(BM31/BM35,2) -> 6.34
A33: EPS (GAAP) | E33: =ROUND(E31/E36,2) -> 0.07 | F33: =ROUND(F31/F36,2) -> 0.1 | G33: =ROUND(G31/G36,2) -> 0.13 | H33: =ROUND(H31/H36,2) -> 0.07 | I33: =ROUND(I31/I36,2) -> 0 | J33: =ROUND(J31/J36,2) -> 0.03 | K33: =ROUND(K31/K36,2) -> -0.03 | L33: =ROUND(L31/L36,2) -> 0.06 | ... BM33: =ROUND(BM31/BM36,2) -> 6.24
A34: Weighted-average shares used:
A35: Basic Share Count | E35: 8460 | F35: 8660 | G35: 8940 | H35: 9060 | I35: 9060 | J35: 9140 | K35: 9240 | L35: 9340 | Q35: 9480 | V35: 9600 | AA35: 9740 | AF35: 9880 | AK35: 10005 | AP35: 10117 | AU35: 10189 | AX35: 10322 | AZ35: 10304 | BC35: 10501 | BE35: =BE36-(AZ36-AZ35) -> 10530.25 | BJ35: =BJ36-(BE36-BE35) -> 10647 | BK35: =BK36-(BJ36-BJ35) -> 10767 | BL35: =BL36-(BK36-BK35) -> 10887 | BM35: =BM36-(BL36-BL35) -> 11007
A36: Diluted Share Count | E36: 8640 | F36: 8840 | G36: 9120 | H36: 9220 | I36: 9060 | J36: 9300 | K36: 9240 | L36: 9540 | M36: 9620 | N36: 9656 | O36: 9700 | P36: 9720 | Q36: 9680 | R36: 9800 | S36: 9840 | T36: 9880 | U36: 9910 | V36: 9860 | W36: 9960 | X36: 10000 | Y36: 10020 | Z36: 10020 | AA36: 10002 | AB36: 10040 | AC36: 10060 | AD36: 10080 | AE36: 10100 | AF36: 10074 | AG36: 10120 | AH36: 10180 | AI36: 10240 | AJ36: 10264 | AK36: 10200 | AL36: 10266 | AM36: 10286 | AN36: 10306 | AO36: 10324 | AP36: 10296 | AQ36: 10180 | AR36: 10175 | AS36: 10331 | AT36: 10308 | AU36: 10189 | AV36: 10347 | AW36: 10449 | AX36: 10558 | AY36: 10610 | AZ36: 10492 | BA36: 10670 | BB36: 10708 | BC36: 10735 | BD36: =BC36+25 -> 10760 | BE36: =AVERAGE(BA36:BD36) -> 10718.25 | BF36: =BD36+30 -> 10790 | BG36: =BF36+30 -> 10820 | BH36: =BG36+30 -> 10850 | BI36: =BH36+30 -> 10880 | BJ36: =AVERAGE(BF36:BI36) -> 10835 | BK36: =BJ36+120 -> 10955 | BL36: =BK36+120 -> 11075 | BM36: =BL36+120 -> 11195
A38: Growth
A39: Online Stores (yr/yr Growth) | Q39: =Q8/L8-1 -> 0.18954503 | R39: =R8/M8-1 -> 0.14611368 | S39: =S8/N8-1 -> 0.16566886 | T39: =T8/O8-1 -> 0.22241779 | U39: =U8/P8-1 -> 0.19747529 | V39: =V8/Q8-1 -> 0.18508837 | W39: =W8/R8-1 -> 0.18018926 | X39: =X8/S8-1 -> 0.14359687 | ... BJ39: =BJ8/BE8-1 -> 0.05 | BK39: =BK8/BJ8-1 -> 0.05 | BL39: =BL8/BK8-1 -> 0.05 | BM39: =BM8/BL8-1 -> 0.05
A40: Physical Stores (yr/yr Growth) | Y40: =Y9/T9-1 -> 2.3291536 | Z40: =Z9/U9-1 -> -0.026758072 | AA40: =AA9/V9-1 -> 1.9706795 | AB40: =AB9/W9-1 -> 0.01032137 | AC40: =AC9/X9-1 -> 0.004174397 | AD40: =AD9/Y9-1 -> -0.013182674 | AE40: =AE9/Z9-1 -> -0.0086344013 | AF40: =AF9/AA9-1 -> -0.0018578727 | ... BJ40: =BJ9/BE9-1 -> 0.05 | BK40: =BK9/BJ9-1 -> 0.05 | BL40: =BL9/BK9-1 -> 0.05 | BM40: =BM9/BL9-1 -> 0.05
A41: Third-Party Seller Services (yr/yr Growth) | Q41: =Q10/L10-1 -> 0.42931742 | R41: =R10/M10-1 -> 0.34097063 | S41: =S10/N10-1 -> 0.37536888 | T41: =T10/O10-1 -> 0.40268931 | U41: =U10/P10-1 -> 0.41134657 | V41: =V10/Q10-1 -> 0.38656924 | W41: =W10/R10-1 -> 0.43911153 | X41: =X10/S10-1 -> 0.38778429 | ... BJ41: =BJ10/BE10-1 -> 0.1 | BK41: =BK10/BJ10-1 -> 0.1 | BL41: =BL10/BK10-1 -> 0.1 | BM41: =BM10/BL10-1 -> 0.1
A42: Subscription Services (yr/yr Growth) | Q42: =Q11/L11-1 -> 0.43116185 | R42: =R11/M11-1 -> 0.49153846 | S42: =S11/N11-1 -> 0.51292802 | T42: =T11/O11-1 -> 0.59334204 | U42: =U11/P11-1 -> 0.4915493 | V42: =V11/Q11-1 -> 0.52072579 | W42: =W11/R11-1 -> 0.59979371 | X42: =X11/S11-1 -> 0.57413395 | ... BJ42: =BJ11/BE11-1 -> 0.1 | BK42: =BK11/BJ11-1 -> 0.1 | BL42: =BL11/BK11-1 -> 0.1 | BM42: =BM11/BL11-1 -> 0.1
A43: Advertising Services (yr/yr Growth) | AN43: =AN12/AI12-1 -> 0.52790044 | AO43: =AO12/AJ12-1 -> 0.32190476 | AP43: =AP12/AK12-1 -> 1.5267596 | AQ43: =AQ12/AL12-1 -> 0.23444601 | AR43: =AR12/AM12-1 -> 0.17527849 | AS43: =AS12/AN12-1 -> 0.25433526 | AT43: =AT12/AO12-1 -> 0.18948127 | AU43: =AU12/AP12-1 -> 0.21113607 | ... BJ43: =BJ12/BE12-1 -> 0.18 | BK43: =BK12/BJ12-1 -> 0.15 | BL43: =BL12/BK12-1 -> 0.15 | BM43: =BM12/BL12-1 -> 0.15
A44: AWS (yr/yr Growth) | Q44: =Q13/L13-1 -> 0.55063452 | R44: =R13/M13-1 -> 0.42673422 | S44: =S13/N13-1 -> 0.42065142 | T44: =T13/O13-1 -> 0.4187558 | U44: =U13/P13-1 -> 0.44598416 | V44: =V13/Q13-1 -> 0.42875849 | W44: =W13/R13-1 -> 0.4864791 | X44: =X13/S13-1 -> 0.48902439 | ... BJ44: =BJ13/BE13-1 -> 0.18 | BK44: =BK13/BJ13-1 -> 0.15 | BL44: =BL13/BK13-1 -> 0.15 | BM44: =BM13/BL13-1 -> 0.15
A45: Other (yr/yr Growth) | Q45: =Q14/L14-1 -> 0.72573099 | R45: =R14/M14-1 -> 0.55963303 | S45: =S14/N14-1 -> 0.50958466 | T45: =T14/O14-1 -> 0.58392102 | U45: =U14/P14-1 -> 0.61998133 | V45: =V14/Q14-1 -> 0.57675364 | W45: =W14/R14-1 -> 1.3894118 | X45: =X14/S14-1 -> 1.3216931 | ... BJ45: =BJ14/BE14-1 -> 0.05 | BK45: =BK14/BJ14-1 -> 0.05 | BL45: =BL14/BK14-1 -> 0.05 | BM45: =BM14/BL14-1 -> 0.05
A46: Total Revenue | Q46: =Q15/L15-1 -> 0.27083528 | R46: =R15/M15-1 -> 0.22610547 | S46: =S15/N15-1 -> 0.24835548 | T46: =T15/O15-1 -> 0.33716452 | U46: =U15/P15-1 -> 0.38206717 | V46: =V15/Q15-1 -> 0.30796326 | W46: =W15/R15-1 -> 0.42918743 | X46: =X15/S15-1 -> 0.39338691 | ... BJ46: =BJ15/BE15-1 -> 0.099230361 | BK46: =BK15/BJ15-1 -> 0.093426267 | BL46: =BL15/BK15-1 -> 0.094947516 | BM46: =BM15/BL15-1 -> 0.096478448
A47: Total Cost of Goods Sold | Q47: =Q16/L16-1 -> 0.23185999 | R47: =R16/M16-1 -> 0.18944132 | S47: =S16/N16-1 -> 0.22267987 | T47: =T16/O16-1 -> 0.29581373 | U47: =U16/P16-1 -> 0.32930451 | V47: =V16/Q16-1 -> 0.26817275 | W47: =W16/R16-1 -> 0.36965241 | X47: =X16/S16-1 -> 0.30621295 | ... BJ47: =BJ16/BE16-1 -> 0.11541132 | BK47: =BK16/BJ16-1 -> 0.072398839 | BL47: =BL16/BK16-1 -> 0.073477957 | BM47: =BM16/BL16-1 -> 0.074548879
A48: Gross Profit (GAAP) | Q48: =Q17/L17-1 -> 0.34982322 | R48: =R17/M17-1 -> 0.29351004 | S48: =S17/N17-1 -> 0.29223093 | T48: =T17/O17-1 -> 0.41391654 | U48: =U17/P17-1 -> 0.48542244 | V48: =V17/Q17-1 -> 0.38155606 | W48: =W17/R17-1 -> 0.52983276 | X48: =X17/S17-1 -> 0.53433536 | ... BJ48: =BJ17/BE17-1 -> 0.082222571 | BK48: =BK17/BJ17-1 -> 0.11620598 | BL48: =BL17/BK17-1 -> 0.11729338 | BM48: =BM17/BL17-1 -> 0.11840802
A49: Fulfillment | Q49: =Q18/L18-1 -> 0.31387025 | R49: =R18/M18-1 -> 0.27393545 | S49: =S18/N18-1 -> 0.33006704 | T49: =T18/O18-1 -> 0.48096886 | U49: =U18/P18-1 -> 0.56915545 | V49: =V18/Q18-1 -> 0.43305522 | W49: =W18/R18-1 -> 0.65893123 | X49: =X18/S18-1 -> 0.53780535 | ... BJ49: =BJ18/BE18-1 -> 0.085779138 | BK49: =BK18/BJ18-1 -> 0.065025585 | BL49: =BL18/BK18-1 -> 0.094947516 | BM49: =BM18/BL18-1 -> 0.096478448
A50: Technology and Content | Q50: =Q19/L19-1 -> 0.3766654 | R50: =R19/M19-1 -> 0.33704735 | S50: =S19/N19-1 -> 0.44178525 | T50: =T19/O19-1 -> 0.42635213 | U50: =U19/P19-1 -> 0.36888181 | V50: =V19/Q19-1 -> 0.39195355 | W50: =W19/R19-1 -> 0.40572917 | X50: =X19/S19-1 -> 0.30148048 | ... BJ50: =BJ19/BE19-1 -> 0.019904886 | BK50: =BK19/BJ19-1 -> 0.093426267 | BL50: =BL19/BK19-1 -> 0.17917425 | BM50: =BM19/BL19-1 -> 0.17479834
A51: Marketing | Q51: =Q20/L20-1 -> 0.28277512 | R51: =R20/M20-1 -> 0.36500284 | S51: =S20/N20-1 -> 0.43015464 | T51: =T20/O20-1 -> 0.43748489 | U51: =U20/P20-1 -> 0.38921892 | V51: =V20/Q20-1 -> 0.40619172 | W51: =W20/R20-1 -> 0.40432163 | X51: =X20/S20-1 -> 0.30600108 | ... BJ51: =BJ20/BE20-1 -> 0.11746207 | BK51: =BK20/BJ20-1 -> 0.24963002 | BL51: =BL20/BK20-1 -> 0.094947516 | BM51: =BM20/BL20-1 -> 0.096478448
A52: General & Administrative | Q52: =Q21/L21-1 -> 0.39267315 | R52: =R21/M21-1 -> 0.59959759 | S52: =S21/N21-1 -> 0.50689655 | T52: =T21/O21-1 -> 0.50234742 | U52: =U21/P21-1 -> 0.45606695 | V52: =V21/Q21-1 -> 0.50965886 | W52: =W21/R21-1 -> 0.34213836 | X52: =X21/S21-1 -> 0.27116705 | ... BJ52: =BJ21/BE21-1 -> 0.14474244 | BK52: =BK21/BJ21-1 -> 0.36678283 | BL52: =BL21/BK21-1 -> 0.31393702 | BM52: =BM21/BL21-1 -> 0.096478448
A53: Other Operating Expenses (Income) | Q53: =Q22/L22-1 -> -0.029239766 | R53: =R22/M22-1 -> -0.022222222 | S53: =S22/N22-1 -> 0.2 | T53: =T22/O22-1 -> 0.40625 | U53: =U22/P22-1 -> 0.76470588 | V53: =V22/Q22-1 -> 0.29518072 | W53: =W22/R22-1 -> 0.43181818 | X53: =X22/S22-1 -> 0.21212121 | ... BJ53: =BJ22/BE22-1 -> -0.094879298 | BK53: =BK22/BJ22-1 -> 0.093426267 | BL53: =BL22/BK22-1 -> 0.094947516 | BM53: =BM22/BL22-1 -> 0.096478448
A54: Total Operating Expenses | Q54: =Q23/L23-1 -> 0.31444357 | R54: =R23/M23-1 -> 0.33489283 | S54: =S23/N23-1 -> 0.39611631 | T54: =T23/O23-1 -> 0.45675154 | U54: =U23/P23-1 -> 0.46599645 | V54: =V23/Q23-1 -> 0.4200565 | W54: =W23/R23-1 -> 0.4980846 | X54: =X23/S23-1 -> 0.38880081 | ... BJ54: =BJ23/BE23-1 -> 0.069856034 | BK54: =BK23/BJ23-1 -> 0.1255001 | BL54: =BL23/BK23-1 -> 0.13749729 | BM54: =BM23/BL23-1 -> 0.12382205
A55: Operating Profit (GAAP) | Q55: =Q24/L24-1 -> 0.87460815 | R55: =R24/M24-1 -> -0.06162465 | S55: =S24/N24-1 -> -0.51128405 | T55: =T24/O24-1 -> -0.39652174 | U55: =U24/P24-1 -> 0.69482072 | V55: =V24/Q24-1 -> -0.018872432 | W55: =W24/R24-1 -> 0.91741294 | X55: =X24/S24-1 -> 3.75 | ... BJ55: =BJ24/BE24-1 -> 0.12882307 | BK55: =BK24/BJ24-1 -> 0.083012684 | BL55: =BL24/BK24-1 -> 0.042305809 | BM55: =BM24/BL24-1 -> 0.096478448
... A61: Equity Income (Net of Tax) | Q61: =Q30/L30-1 -> 3.3636364 | R61: =R30/M30-1 -> -1 | S61: =S30/N30-1 -> -0.86666667 | T61: =T30/O30-1 -> -0.8 | U61: =U30/P30-1 -> -1 | V61: =V30/Q30-1 -> -0.95833333 | W61: =W30/R30-1 -> #DIV/0! | X61: =X30/S30-1 -> -2.5 | ... BJ61: =BJ30/BE30-1 -> -1 | BK61: =BK30/BJ30-1 -> #DIV/0! | BL61: =BL30/BK30-1 -> #DIV/0! | BM61: =BM30/BL30-1 -> #DIV/0!
A62: Net Income | Q62: =Q31/L31-1 -> 2.9781879 | R62: =R31/M31-1 -> 0.41130604 | S62: =S31/N31-1 -> -0.77012835 | T62: =T31/O31-1 -> 0.015873016 | U62: =U31/P31-1 -> 1.4779706 | V62: =V31/Q31-1 -> 0.27920709 | W62: =W31/R31-1 -> 1.25 | X62: =X31/S31-1 -> 11.862944 | ... AY62: =AY31/AT31-1 -> 37.215827 | AZ62: =-(AZ31/AU31-1) -> 12.177443 | BA62: =BA31/AV31-1 -> 2.2884615 | BB62: =BB31/AW31-1 -> 0.99777778 | BC62: =BC31/AX31-1 -> 0.55157405 | BD62: =BD31/AY31-1 -> 0.28528374 | BE62: =-(BE31/AZ31-1) -> -0.73866407 | BF62: =BF31/BA31-1 -> 0.21697724 | BG62: =BG31/BB31-1 -> -0.027148368 | BH62: =BH31/BC31-1 -> -0.081542873 | BI62: =BI31/BD31-1 -> 0.21744348 | BJ62: =-(BJ31/BE31-1) -> -0.068365635 | BK62: =BK31/BJ31-1 -> 0.082706402 | BL62: =BL31/BK31-1 -> 0.040742194 | BM62: =BM31/BL31-1 -> 0.096478448
A63: EPS (GAAP) | Q63: =Q33/L33-1 -> 3 | R63: =R33/M33-1 -> 0.4 | S63: =S33/N33-1 -> -0.77777778 | T63: =T33/O33-1 -> 0 | U63: =U33/P33-1 -> 1.375 | V63: =V33/Q33-1 -> 0.29166667 | W63: =W33/R33-1 -> 1.2857143 | X63: =X33/S33-1 -> 11.5 | ... AY63: =AY33/AT33-1 -> 32.333333 | AZ63: =-(AZ33/AU33-1) -> 11.740741 | BA63: =BA33/AV33-1 -> 2.1612903 | BB63: =BB33/AW33-1 -> 0.93846154 | BC63: =BC33/AX33-1 -> 0.5212766 | BD63: =BD33/AY33-1 -> 0.27 | BE63: =-(BE33/AZ33-1) -> -0.70344828 | BF63: =BF33/BA33-1 -> 0.20408163 | BG63: =BG33/BB33-1 -> -0.03968254 | BH63: =BH33/BC33-1 -> -0.090909091 | BI63: =BI33/BD33-1 -> 0.20472441 | BJ63: =-(BJ33/BE33-1) -> -0.056680162 | BK63: =BK32/BJ32-1 -> 0.069679849 | BL63: =BL32/BK32-1 -> 0.029929577 | BM63: =BM32/BL32-1 -> 0.083760684
A65: % of Revenue
A66: Online Stores | K66: =K8/K$15 -> 0.7699128 | L66: =L8/L$15 -> 0.71830552 | M66: =M8/M$15 -> 0.68374073 | N66: =N8/N$15 -> 0.67024076 | O66: =O8/O$15 -> 0.6599621 | P66: =P8/P$15 -> 0.67552182 | Q66: =Q8/Q$15 -> 0.67235839 | R66: =R8/R$15 -> 0.63913311 | ... BC66: =BC8/BC$15 -> 0.38653172
A67: Physical Stores | K67: =K9/K$15 -> 0 | L67: =L9/L$15 -> 0 | M67: =M9/M$15 -> 0 | N67: =N9/N$15 -> 0 | O67: =O9/O$15 -> 0 | P67: =P9/P$15 -> 0 | Q67: =Q9/Q$15 -> 0 | R67: =R9/R$15 -> 0 | ... BC67: =BC9/BC$15 -> 0.032905959
A68: Third-Party Seller Services | K68: =K10/K$15 -> 0.13200656 | L68: =L10/L$15 -> 0.15032802 | M68: =M10/M$15 -> 0.16482422 | N68: =N10/N$15 -> 0.16718195 | O68: =O10/O$15 -> 0.17277007 | P68: =P10/P$15 -> 0.17045792 | Q68: =Q10/Q$15 -> 0.16907499 | R68: =R10/R$15 -> 0.18026544 | ... BC68: =BC10/BC$15 -> 0.23832273
A69: Subscription Services | K69: =K11/K$15 -> 0.031037893 | L69: =L11/L$15 -> 0.041745323 | M69: =M11/M$15 -> 0.044630596 | N69: =N11/N$15 -> 0.047066176 | O69: =O11/O$15 -> 0.046830103 | P69: =P11/P$15 -> 0.048695732 | Q69: =Q11/Q$15 -> 0.047011847 | R69: =R11/R$15 -> 0.054292434 | ... BC69: =BC11/BC$15 -> 0.070985731
A70: Advertising Services | K70: =K12/K$15 -> 0 | L70: =L12/L$15 -> 0 | M70: =M12/M$15 -> 0 | N70: =N12/N$15 -> 0 | O70: =O12/O$15 -> 0 | P70: =P12/P$15 -> 0 | Q70: =Q12/Q$15 -> 0 | R70: =R12/R$15 -> 0 | ... BC70: =BC12/BC$15 -> 0.090201854
A71: AWS | K71: =K13/K$15 -> 0.052186812 | L71: =L13/L$15 -> 0.07364073 | M71: =M13/M$15 -> 0.08809393 | N71: =N13/N$15 -> 0.094921721 | O71: =O13/O$15 -> 0.098765055 | P71: =P13/P$15 -> 0.080839487 | Q71: =Q13/Q$15 -> 0.089854177 | R71: =R13/R$15 -> 0.10250882 | ... BC71: =BC13/BC$15 -> 0.17278775
A72: Other | K72: =K14/K$15 -> 0.014855936 | L72: =L14/L$15 -> 0.015980412 | M72: =M14/M$15 -> 0.018710519 | N72: =N14/N$15 -> 0.020589396 | O72: =O14/O$15 -> 0.021672678 | P72: =P14/P$15 -> 0.024485037 | Q72: =Q14/Q$15 -> 0.021700604 | R72: =R14/R$15 -> 0.02380019 | ... BC72: =BC14/BC$15 -> 0.0082642547
A73: Total Revenue | E73: =E15/E$15 -> 1 | F73: =F15/F$15 -> 1 | G73: =G15/G$15 -> 1 | H73: =H15/H$15 -> 1 | I73: =I15/I$15 -> 1 | J73: =J15/J$15 -> 1 | K73: =K15/K$15 -> 1 | L73: =L15/L$15 -> 1 | ... BC73: =BC15/BC$15 -> 1
A74: Total Cost of Goods Sold | E74: =E16/E$15 -> 0.77720964 | F74: =F16/F$15 -> 0.7743278 | G74: =G16/G$15 -> 0.7765466 | H74: =H16/H$15 -> 0.77558916 | I74: =I16/I$15 -> 0.75247573 | J74: =J16/J$15 -> 0.72773062 | K74: =K16/K$15 -> 0.70517373 | L74: =L16/L$15 -> 0.66959797 | ... BC74: =BC16/BC$15 -> 0.50968359
A75: Gross Profit (GAAP) (%) | E75: =E17/E$15 -> 0.22279036 | F75: =F17/F$15 -> 0.2256722 | G75: =G17/G$15 -> 0.2234534 | H75: =H17/H$15 -> 0.22441084 | I75: =I17/I$15 -> 0.24752427 | J75: =J17/J$15 -> 0.27226938 | K75: =K17/K$15 -> 0.29482627 | L75: =L17/L$15 -> 0.33040203 | ... BC75: =BC17/BC$15 -> 0.49031641
A76: Fulfillment (%) | E76: =E18/E$15 -> 0.086507357 | F76: =F18/F$15 -> 0.083724346 | G76: =G18/G$15 -> 0.084726933 | H76: =H18/H$15 -> 0.095180648 | I76: =I18/I$15 -> 0.10506932 | J76: =J18/J$15 -> 0.11530919 | K76: =K18/K$15 -> 0.1209826 | L76: =L18/L$15 -> 0.12532008 | ... BC76: =BC18/BC$15 -> 0.15521441
A77: Technology and Content (%) | E77: =E19/E$15 -> 0.025148701 | F77: =F19/F$15 -> 0.02774491 | G77: =G19/G$15 -> 0.030084201 | H77: =H19/H$15 -> 0.033903946 | I77: =I19/I$15 -> 0.039415318 | J77: =J19/J$15 -> 0.042080804 | K77: =K19/K$15 -> 0.048680721 | L77: =L19/L$15 -> 0.04910005 | ... BC77: =BC19/BC$15 -> 0.14001397
A78: Marketing (%) | E78: =E20/E$15 -> 0.053897527 | F78: =F20/F$15 -> 0.050593659 | G78: =G20/G$15 -> 0.050695825 | H78: =H20/H$15 -> 0.060507103 | I78: =I20/I$15 -> 0.074705776 | J78: =J20/J$15 -> 0.088177618 | K78: =K20/K$15 -> 0.10422754 | L78: =L20/L$15 -> 0.11718969 | ... BC78: =BC20/BC$15 -> 0.066774927
A79: General & Administrative (%) | E79: =E21/E$15 -> 0.014557028 | F79: =F21/F$15 -> 0.013382839 | G79: =G21/G$15 -> 0.013741083 | H79: =H21/H$15 -> 0.013686378 | I79: =I21/I$15 -> 0.014666165 | J79: =J21/J$15 -> 0.015164133 | K79: =K21/K$15 -> 0.017440554 | L79: =L21/L$15 -> 0.016326187 | ... BC79: =BC21/BC$15 -> 0.017076103
A80: Other Operating Expenses (Income) (%) | E80: =E22/E$15 -> -0.0012522175 | F80: =F22/F$15 -> 0.0041617365 | G80: =G22/G$15 -> 0.0030990527 | H80: =H22/H$15 -> 0.0032031949 | I80: =I22/I$15 -> 0.0026025895 | J80: =J22/J$15 -> 0.0015311879 | K80: =K22/K$15 -> 0.0014945835 | L80: =L22/L$15 -> 0.0015980412 | ... BC80: =BC22/BC$15 -> 0.0016490744
A81: Total Operating Expenses | E81: =E23/E$15 -> 0.1788584 | F81: =F23/F$15 -> 0.17960749 | G81: =G23/G$15 -> 0.18234709 | H81: =H23/H$15 -> 0.20648127 | I81: =I23/I$15 -> 0.23645917 | J81: =J23/J$15 -> 0.26226293 | K81: =K23/K$15 -> 0.292826 | L81: =L23/L$15 -> 0.30953404 | ... BC81: =BC23/BC$15 -> 0.38072849
A82: Operating Profit (GAAP) | E82: =E24/E$15 -> 0.043931963 | F82: =F24/F$15 -> 0.046064711 | G82: =G24/G$15 -> 0.041106303 | H82: =H24/H$15 -> 0.017929571 | I82: =I24/I$15 -> 0.011065097 | J82: =J24/J$15 -> 0.010006447 | K82: =K24/K$15 -> 0.0020002697 | L82: =L24/L$15 -> 0.020867989 | ... BC82: =BC24/BC$15 -> 0.10958792
A83: Interest Income (%) | E83: =E25/E$15 -> 0.0043305854 | F83: =F25/F$15 -> 0.0015096495 | G83: =G25/G$15 -> 0.0014910537 | H83: =H25/H$15 -> 0.001268798 | I83: =I25/I$15 -> 0.0006547395 | J83: =J25/J$15 -> 0.00051039596 | K83: =K25/K$15 -> 0.00043826134 | L83: =L25/L$15 -> 0.00046726352 | ... BC83: =BC25/BC$15 -> 0.0079054866
A84: Interest Expense (%) | E84: =E26/E$15 -> -0.0037044767 | F84: =F26/F$15 -> -0.0013872455 | G84: =G26/G$15 -> -0.0011402175 | H84: =H26/H$15 -> -0.0013519978 | I84: =I26/I$15 -> -0.0015059008 | J84: =J26/J$15 -> -0.0018938376 | K84: =K26/K$15 -> -0.0023598687 | L84: =L26/L$15 -> -0.0042894791 | ... BC84: =BC26/BC$15 -> -0.0037953889
... A89: Net Income | E89: =E31/E$15 -> 0.033653344 | F89: =F31/F$15 -> 0.036802807 | G89: =G31/G$15 -> 0.033680271 | H89: =H31/H$15 -> 0.013124779 | I89: =I31/I$15 -> -0.00063837101 | J89: =J31/J$15 -> 0.0036802235 | K89: =K31/K$15 -> -0.0027082303 | L89: =L31/L$15 -> 0.0055697811 | ... BC89: =BC31/BC$15 -> 0.096477149
A90: Effective Tax Rate (GAAP) | E90: =E29/-E28 -> 0.27413984 | F90: =F29/-F28 -> 0.21791559 | G90: =G29/-G28 -> 0.23513694 | H90: =H29/-H28 -> 0.31156317 | I90: =I29/-I28 -> 0.78676471 | J90: =J29/-J28 -> 0.31818182 | K90: =K29/-K28 -> -1.5045045 | L90: =L29/-L28 -> 0.60586735 | ... BC90: =BC29/-BC28 -> 0.15002495
A93: Depreciation | E93: =CF!E9+CF!E11 -> 263 | F93: =CF!F9+CF!F11 -> 481 | G93: =CF!G9+CF!G11 -> 674 | H93: =CF!H9+CF!H11 -> 1237 | I93: =CF!I9+CF!I11 -> 2313 | J93: =CF!J9+CF!J11 -> 3367 | K93: =CF!K9+CF!K11 -> 4875 | L93: =CF!L9+CF!L11 -> 6436 | ... AU93: =CF!AU9+CF!AU11 -> 41921 | AV93: =CF!AV9 -> 11123 | AW93: =CF!AW9 -> 11589 | AX93: =CF!AX9 -> 12131 | AY93: =CF!AY9 -> 13820 | AZ93: =CF!AZ9 -> 48663 | BA93: =CF!BA9 -> 11684 | BB93: =CF!BB9 -> 12038 | BC93: =CF!BC9 -> 13442 | ... BM93: =CF!BM9 -> 101277.86
A94: EBITDA | E94: =E95+E93 -> 1152 | F94: =F95+F93 -> 1639 | G94: =G95+G93 -> 2159 | H94: =H95+H93 -> 2175 | I94: =I95+I93 -> 2909 | J94: =J95+J93 -> 3976 | K94: =K95+K93 -> 4935 | L94: =L95+L93 -> 8413 | ... BM94: =BM95+BM93 -> 194269.34
A95: EBIT | E95: =E28+(-E26-E25) -> 889 | F95: =F28+(-F26-F25) -> 1158 | G95: =G28+(-G26-G25) -> 1485 | H95: =H28+(-H26-H25) -> 938 | I95: =I28+(-I26-I25) -> 596 | J95: =J28+(-J26-J25) -> 609 | K95: =K28+(-K26-K25) -> 60 | L95: =L28+(-L26-L25) -> 1977 | ... BM95: =BM28+(-BM26-BM25) -> 92991.487
A96: EBIT t-1 | Q96: =SUM(M95:O95,K95) -> 3066 | V96: =SUM(R95:T95,P95) -> 3577 | AA96: =SUM(W95:Y95,U95) -> 10796 | AF96: =SUM(AB95:AD95,Z95) -> 14032 | AK96: =SUM(AG95:AI95,AE95) -> 21488 | AP96: =SUM(AL95:AN95,AJ95) -> 32293 | AU96: =SUM(AQ95:AS95,AO95) -> 11453 | AZ96: =SUM(AV95:AX95,AT95) -> 23579 | BE96: =SUM(BA95:BC95,AY95) -> 58170 | BJ96: =SUM(BF95:BH95,BD95) -> 71194.591 | BK96: =BJ95 -> 75045.161 | BL96: =BK95 -> 81289.468 | BM96: =BL95 -> 84809.225
A97: Revenue t-1 | Q97: =SUM(M15:O15,K15) -> 181234 | V97: =SUM(R15:T15,P15) -> 161154 | AA97: =SUM(W15:Y15,U15) -> 220957 | AF97: =SUM(AB15:AD15,Z15) -> 265468 | AK97: =SUM(AG15:AI15,AE15) -> 347946 | AP97: =SUM(AL15:AN15,AJ15) -> 457965 | AU97: =SUM(AQ15:AS15,AO15) -> 502191 | AZ97: =SUM(AV15:AX15,AT15) -> 554028 | BE97: =SUM(BA15:BC15,AY15) -> 620128 | BJ97: =SUM(BF15:BH15,BD15) -> 682928.55 | BK97: =BJ15 -> 701356.64 | BL97: =BK15 -> 766881.78 | BM97: =BL15 -> 839695.3
A98: Net Income t-1 | Q98: =SUM(M31:O31,K31) -> 1381 | V98: =SUM(R31:T31,P31) -> 1926 | AA98: =SUM(W31:Y31,U31) -> 8902 | AF98: =SUM(AB31:AD31,Z31) -> 11347 | AK98: =SUM(AG31:AI31,AE31) -> 17377 | AP98: =SUM(AL31:AN31,AJ31) -> 26263 | AU98: =SUM(AQ31:AS31,AO31) -> 11323 | AZ98: =SUM(AV31:AX31,AT31) -> 20079 | BE98: =SUM(BA31:BC31,AY31) -> 49868 | BJ98: =SUM(BF31:BH31,BD31) -> 53546.159 | BK98: =BJ31 -> 56515.318 | BL98: =BK31 -> 61189.497 | BM98: =BL31 -> 63682.491
A101: Estimates | BA101: 45382 | BB101: 45473 | BC101: 45565 | BD101: 45657 | BE101: 2024 | BF101: 45747 | BG101: 45838 | BH101: 45930 | BI101: 46022 | BJ101: 2025 | BK101: 2026 | BL101: 2027 | BM101: 2028
A102: Online Stores | BA102: =AV8*(1+'Assumptions + Estimates'!F11) -> 52117.92 | BB102: =AW8*(1+'Assumptions + Estimates'!G11) -> 54025.32 | BC102: =AX8*(1+'Assumptions + Estimates'!H11) -> 61275.69 | BD102: =AY8*(1+'Assumptions + Estimates'!I11) -> 76186.44 | BE102: =SUM(BA102:BD102) -> 243605.37 | BF102: =BF8 -> 57403.5 | BG102: =BG8 -> 58161.6 | BH102: =BH8 -> 64481.55 | BI102: =BI8 -> 77818.306 | BJ102: =SUM(BF102:BI102) -> 257864.96 | BK102: =BK8 -> 270758.2 | BL102: =BL8 -> 284296.11 | BM102: =BM8 -> 298510.92
A103: Physical Stores | BA103: =AV9*(1+'Assumptions + Estimates'!F12) -> 5090.8 | BB103: =AW9*(1+'Assumptions + Estimates'!G12) -> 5224.96 | BC103: =AX9*(1+'Assumptions + Estimates'!H12) -> 5256.54 | BD103: =AY9*(1+'Assumptions + Estimates'!I12) -> 5461.12 | BE103: =SUM(BA103:BD103) -> 21033.42 | BF103: =BF9 -> 5462.1 | BG103: =BG9 -> 5466.3 | BH103: =BH9 -> 5489.4 | BI103: =BI9 -> 5680.5985 | BJ103: =SUM(BF103:BI103) -> 22098.399 | BK103: =BK9 -> 23203.318 | BL103: =BL9 -> 24363.484 | BM103: =BM9 -> 25581.659
A104: Third-Party Seller Services | BA104: =AV10*(1+'Assumptions + Estimates'!F13) -> 32802 | BB104: =AW10*(1+'Assumptions + Estimates'!G13) -> 35565.2 | BC104: =AX10*(1+'Assumptions + Estimates'!H13) -> 39493.3 | BD104: =AY10*(1+'Assumptions + Estimates'!I13) -> 50092.85 | BE104: =SUM(BA104:BD104) -> 157953.35 | BF104: =BF10 -> 38055.6 | BG104: =BG10 -> 39821.1 | BH104: =BH10 -> 41650.4 | BI104: =BI10 -> 54038.964 | BJ104: =SUM(BF104:BI104) -> 173566.06 | BK104: =BK10 -> 190922.67 | BL104: =BL10 -> 210014.94 | BM104: =BM10 -> 231016.43
A105: Subscription Services | BA105: =AV11*(1+'Assumptions + Estimates'!F14) -> 10622.7 | BB105: =AW11*(1+'Assumptions + Estimates'!G14) -> 10883.4 | BC105: =AX11*(1+'Assumptions + Estimates'!H14) -> 11593.8 | BD105: =AY11*(1+'Assumptions + Estimates'!I14) -> 11746.56 | BE105: =SUM(BA105:BD105) -> 44846.46 | BF105: =BF11 -> 11794.2 | BG105: =BG11 -> 11952.6 | BH105: =BH11 -> 12405.8 | BI105: =BI11 -> 12867.384 | BJ105: =SUM(BF105:BI105) -> 49019.984 | BK105: =BK11 -> 53921.982 | BL105: =BL11 -> 59314.181 | BM105: =BM11 -> 65245.599
A106: Advertising Services | BA106: =AV12*(1+'Assumptions + Estimates'!F15) -> 11220.62 | BB106: =AW12*(1+'Assumptions + Estimates'!G15) -> 12605.94 | BC106: =AX12*(1+'Assumptions + Estimates'!H15) -> 14472 | BD106: =AY12*(1+'Assumptions + Estimates'!I15) -> 17584.8 | BE106: =SUM(BA106:BD106) -> 55883.36 | BF106: =BF12 -> 13952.32 | BG106: =BG12 -> 15069.78 | BH106: =BH12 -> 16910.58 | BI106: =BI12 -> 20601.19 | BJ106: =SUM(BF106:BI106) -> 66533.87 | BK106: =BK12 -> 76513.95 | BL106: =BL12 -> 87991.043 | BM106: =BM12 -> 101189.7
A107: AWS | BA107: =AV13*(1+'Assumptions + Estimates'!F16) -> 24557.1 | BB107: =AW13*(1+'Assumptions + Estimates'!G16) -> 26125.2 | BC107: =AX13*(1+'Assumptions + Estimates'!H16) -> 27670.8 | BD107: =AY13*(1+'Assumptions + Estimates'!I16) -> 29044.8 | BE107: =SUM(BA107:BD107) -> 107397.9 | BF107: =BF13 -> 29543.66 | BG107: =BG13 -> 31011.58 | BH107: =BH13 -> 32393.36 | BI107: =BI13 -> 33797.518 | BJ107: =SUM(BF107:BI107) -> 126746.12 | BK107: =BK13 -> 145758.04 | BL107: =BL13 -> 167621.74 | BM107: =BM13 -> 192765
A108: Other | BA108: =AV14*(1+'Assumptions + Estimates'!F17) -> 1078.35 | BB108: =AW14*(1+'Assumptions + Estimates'!G17) -> 1411.2 | BC108: =AX14*(1+'Assumptions + Estimates'!H17) -> 1287.3 | BD108: =AY14*(1+'Assumptions + Estimates'!I17) -> 1429.05 | BE108: =SUM(BA108:BD108) -> 5205.9 | BF108: =BF14 -> 1325.1 | BG108: =BG14 -> 1323 | BH108: =BH14 -> 1378.65 | BI108: =BI14 -> 1500.5025 | BJ108: =SUM(BF108:BI108) -> 5527.2525 | BK108: =BK14 -> 5803.6151 | BL108: =BL14 -> 6093.7959 | BM108: =BM14 -> 6398.4857
A109: Total Revenue | BA109: =SUM(BA102:BA108) -> 137489.49 | BB109: =SUM(BB102:BB108) -> 145841.22 | BC109: =SUM(BC102:BC108) -> 161049.43 | BD109: =SUM(BD102:BD108) -> 191545.62 | BE109: =SUM(BE102:BE108) -> 635925.76 | BF109: =SUM(BF102:BF108) -> 157536.48 | BG109: =SUM(BG102:BG108) -> 162805.96 | BH109: =SUM(BH102:BH108) -> 174709.74 | ... BM109: =SUM(BM102:BM108) -> 920707.8
A110: Net Income | BA110: =BA109*'Assumptions + Estimates'!F20 -> 6874.4745 | BB110: =BB109*'Assumptions + Estimates'!G20 -> 10208.885 | BC110: =BC109*'Assumptions + Estimates'!H20 -> 14494.449 | BD110: =BD109*'Assumptions + Estimates'!I20 -> 15323.65 | BE110: =SUM(BA110:BD110) -> 46901.458 | BF110: =BF109*'Assumptions + Estimates'!K20 -> 12602.918 | BG110: =BG109*'Assumptions + Estimates'!L20 -> 13024.477 | BH110: =BH109*'Assumptions + Estimates'!M20 -> 13976.779 | BI110: =BI109*'Assumptions + Estimates'!N20 -> 16504.357 | BJ110: =SUM(BF110:BI110) -> 56108.531 | BK110: =BK109*'Assumptions + Estimates'!P20 -> 61350.542 | BL110: =BL109*'Assumptions + Estimates'!Q20 -> 63816.843 | BM110: =BM109*'Assumptions + Estimates'!R20 -> 69973.792
A112: Realized x Budget
A113: Total Revenue | BA113: =BA15-BA109 -> 5823.51 | BB113: =BB15-BB109 -> 2135.78 | BC113: =BC15-BC109 -> -2172.43
A114: Net Income | BA114: =BA31-BA110 -> 3556.5255 | BB114: =BB31-BB110 -> 3276.1146 | BC114: =BC31-BC110 -> 833.5513
A116: Total Revenue % | BA116: =BA113/BA109 -> 0.042356038 | BB116: =BB113/BB109 -> 0.014644557 | BC116: =BC113/BC109 -> -0.013489213
A117: Net Income % | BA117: =BA114/BA110 -> 0.51735234 | BB117: =BB114/BB110 -> 0.32090816 | BC117: =BC114/BC110 -> 0.057508314

Sheet BS
A1: Amazon.com Inc. (AMZN)
A2: Balance Sheet
A3: In millions except per share data
BD5: Estimates | BE5: Estimates | BF5: Estimates | BG5: Estimates | BH5: Estimates | BI5: Estimates | BJ5: Estimates | BK5: Estimates | BL5: Estimates | BM5: Estimates
E6: 2008 | F6: 2009 | G6: 2010 | H6: 2011 | I6: 2012 | J6: 2013 | K6: 2014 | L6: 2015 | M6: 42460 | N6: 42551 | O6: 42643 | P6: 42735 | Q6: 2016 | R6: 42825 | S6: 42916 | T6: 43008 | U6: 43100 | V6: 2017 | W6: 43190 | X6: 43281 | Y6: 43373 | Z6: 43465 | AA6: 2018 | AB6: 43555 | AC6: 43646 | AD6: 43738 | AE6: 43830 | AF6: 2019 | AG6: 43921 | AH6: 44012 | AI6: 44104 | AJ6: 44196 | AK6: 2020 | AL6: 44286 | AM6: 44377 | AN6: 44469 | AO6: 44561 | AP6: 2021 | AQ6: 44651 | AR6: 44742 | AS6: 44834 | AT6: 44926 | AU6: 2022 | AV6: 45016 | AW6: 45107 | AX6: 45199 | AY6: 45291 | AZ6: 2023 | BA6: 45382 | BB6: 45473 | BC6: 45565 | BD6: 45657 | BE6: 2024 | BF6: 45747 | BG6: 45838 | BH6: 45930 | BI6: 46022 | BJ6: 2025 | BK6: 2026 | BL6: 2027 | BM6: 2028
A8: Cash & Equivalents | E8: 2769 | F8: 3444 | G8: 3777 | H8: 5269 | I8: 8084 | J8: 8658 | K8: 14557 | L8: 15890 | M8: 12470 | N8: 12521 | O8: 13656 | P8: 19334 | Q8: 19334 | R8: 15440 | S8: 13203 | T8: 12767 | U8: 20522 | V8: 20522 | W8: 16676 | X8: 19823 | Y8: 20425 | Z8: 31750 | AA8: 31750 | AB8: 23115 | AC8: 22616 | AD8: 23255 | AE8: 36092 | AF8: 36092 | AG8: 27201 | AH8: 36092 | AI8: 29930 | AJ8: 42122 | AK8: 42122 | AL8: 33834 | AM8: 40380 | AN8: 29944 | AO8: 36220 | AP8: 36220 | AQ8: 36393 | AR8: 37478 | AS8: 34947 | AT8: 53888 | AU8: 53888 | AV8: 49343 | AW8: 49529 | AX8: 49605 | AY8: 73387 | AZ8: 73387 | BA8: 72852 | BB8: 71178 | BC8: 75091 | BD8: =BD32+BD40-BD18-BD9-BD10-BD11 -> 85676.718 | BE8: =BD8 -> 85676.718 | BF8: =BF32+BF40-BF18-BF9-BF10-BF11 -> 88244.539 | BG8: =BG32+BG40-BG18-BG9-BG10-BG11 -> 96981.304 | BH8: =BH32+BH40-BH18-BH9-BH10-BH11 -> 110678.75 | BI8: =BI32+BI40-BI18-BI9-BI10-BI11 -> 119328.85 | BJ8: =BI8 -> 119328.85 | BK8: =BK32+BK40-BK18-BK9-BK10-BK11 -> 162927.4 | BL8: =BL32+BL40-BL18-BL9-BL10-BL11 -> 208523.5 | BM8: =BM32+BM40-BM18-BM9-BM10-BM11 -> 260421.22
A9: Marketable Securities | E9: 958 | F9: 2922 | G9: 4985 | H9: 4307 | I9: 3364 | J9: 3789 | K9: 2859 | L9: 3918 | M9: 3389 | N9: 4019 | O9: 4691 | P9: 6647 | Q9: 6647 | R9: 6091 | S9: 8248 | T9: 11543 | U9: 10464 | V9: 10464 | W9: 8287 | X9: 7227 | Y9: 9340 | Z9: 9500 | AA9: 9500 | AB9: 13905 | AC9: 18847 | AD9: 20146 | AE9: 18929 | AF9: 18929 | AG9: 22091 | AH9: 18929 | AI9: 38472 | AJ9: 42274 | AK9: 42274 | AL9: 39436 | AM9: 49514 | AN9: 49044 | AO9: 59829 | AP9: 59829 | AQ9: 29992 | AR9: 23232 | AS9: 23715 | AT9: 16138 | AU9: 16138 | AV9: 15062 | AW9: 14441 | AX9: 14564 | AY9: 13393 | AZ9: 13393 | BA9: 12222 | BB9: 17914 | BC9: 12960 | BD9: =BC9*(1+'Assumptions + Estimates'!$J$8) -> 13530.24 | BE9: =BD9 -> 13530.24 | BF9: =BE9*(1+'Assumptions + Estimates'!$O$8) -> 13990.268 | BG9: =BF9*(1+'Assumptions + Estimates'!$O$8) -> 14465.937 | BH9: =BG9*(1+'Assumptions + Estimates'!$O$8) -> 14957.779 | BI9: =BH9*(1+'Assumptions + Estimates'!$O$8) -> 15466.344 | BJ9: =BI9 -> 15466.344 | BK9: =BJ9*(1+'Assumptions + Estimates'!$O$8) -> 15992.199 | BL9: =BK9*(1+'Assumptions + Estimates'!$O$8) -> 16535.934 | BM9: =BL9*(1+'Assumptions + Estimates'!$O$8) -> 17098.156
A10: Inventories | E10: 1399 | F10: 2171 | G10: 3202 | H10: 4992 | I10: 6031 | J10: 7411 | K10: 8299 | L10: 10243 | M10: 9582 | N10: 9588 | O10: 10696 | P10: 11461 | Q10: 11461 | R10: 10600 | S10: 11510 | T10: 13711 | U10: 16047 | V10: 16047 | W10: 13840 | X10: 14824 | Y10: 15862 | Z10: 17174 | AA10: 17174 | AB10: 16432 | AC10: 18580 | AD10: 18766 | AE10: 20497 | AF10: 20497 | AG10: 18857 | AH10: 20497 | AI10: 23735 | AJ10: 23795 | AK10: 23795 | AL10: 23849 | AM10: 24119 | AN10: 30933 | AO10: 32640 | AP10: 32640 | AQ10: 34987 | AR10: 38153 | AS10: 36647 | AT10: 34405 | AU10: 34405 | AV10: 34170 | AW10: 36587 | AX10: 35406 | AY10: 33318 | AZ10: 33318 | BA10: 31147 | BB10: 34109 | BC10: 36103 | BD10: =BC10*(1+'Assumptions + Estimates'!$J$7) -> 37041.678 | BE10: =BD10 -> 37041.678 | BF10: =BE10*(1+'Assumptions + Estimates'!$O$7) -> 37819.553 | BG10: =BF10*(1+'Assumptions + Estimates'!$O$7) -> 38613.764 | BH10: =BG10*(1+'Assumptions + Estimates'!$O$7) -> 39424.653 | BI10: =BH10*(1+'Assumptions + Estimates'!$O$7) -> 40252.571 | BJ10: =BI10 -> 40252.571 | BK10: =BJ10*(1+'Assumptions + Estimates'!P7) -> 41057.622 | BL10: =BK10*(1+'Assumptions + Estimates'!Q7) -> 41878.774 | BM10: =BL10*(1+'Assumptions + Estimates'!R7) -> 42716.35
A11: Accounts Receivable, Net, & Other | E11: 827 | F11: 988 | G11: 1587 | H11: 2571 | I11: 3817 | J11: 4767 | K11: 5612 | L11: 5654 | M11: 5072 | N11: 6092 | O11: 6566 | P11: 8339 | Q11: 8339 | R11: 7329 | S11: 8046 | T11: 10557 | U11: 13164 | V11: 13164 | W11: 12026 | X11: 12607 | Y11: 14258 | Z11: 16677 | AA11: 16677 | AB11: 15979 | AC11: 16747 | AD11: 16887 | AE11: 20816 | AF11: 20816 | AG11: 17836 | AH11: 20816 | AI11: 20832 | AJ11: 24542 | AK11: 24542 | AL11: 24289 | AM11: 26835 | AN11: 28610 | AO11: 32891 | AP11: 32891 | AQ11: 32504 | AR11: 34804 | AS11: 36154 | AT11: 42360 | AU11: 42360 | AV11: 37646 | AW11: 39925 | AX11: 43420 | AY11: 52253 | AZ11: 52253 | BA11: 47768 | BB11: 50106 | BC11: 51638 | BD11: =BC11*(AY11/AX11) -> 62142.801 | BE11: =BD11 -> 62142.801 | BF11: =BE11*(BA11/AZ11) -> 56808.936 | BG11: =BF11*(BB11/BA11) -> 59589.443 | BH11: =BG11*(BC11/BB11) -> 61411.401 | BI11: =BH11*(BD11/BC11) -> 73904.421 | BJ11: =BI11 -> 73904.421 | BK11: =BJ11*(BJ11/BE11) -> 87892.135 | BL11: =BK11*(BK11/BJ11) -> 104527.27 | BM11: =BL11*(BL11/BK11) -> 124310.9
A12: Total Current Assets | E12: =SUM(E8:E11) -> 5953 | F12: =SUM(F8:F11) -> 9525 | G12: =SUM(G8:G11) -> 13551 | H12: =SUM(H8:H11) -> 17139 | I12: =SUM(I8:I11) -> 21296 | J12: =SUM(J8:J11) -> 24625 | K12: =SUM(K8:K11) -> 31327 | L12: =SUM(L8:L11) -> 35705 | ... BM12: =SUM(BM8:BM11) -> 444546.62
A14: PP&E | E14: 854 | F14: 1290 | G14: 2414 | H14: 4417 | I14: 7060 | J14: 10949 | K14: 16967 | L14: 21838 | M14: 23308 | N14: 25190 | O14: 27177 | P14: 29114 | Q14: 29114 | R14: 32632 | S14: 37083 | T14: 45335 | U14: 48866 | V14: 48866 | W14: 52331 | X14: 54768 | Y14: 58019 | Z14: 61797 | AA14: 61797 | AB14: 61048 | AC14: 64723 | AD14: 67662 | AE14: 72705 | AF14: 72705 | AG14: 77779 | AH14: 72705 | AI14: 99981 | AJ14: 113114 | AK14: 113114 | AL14: 121461 | AM14: 133502 | AN14: 147152 | AO14: 160281 | AP14: 160281 | AQ14: 168468 | AR14: 173706 | AS14: 177195 | AT14: 186715 | AU14: 186715 | AV14: 190754 | AW14: 193784 | AX14: 196468 | AY14: 204177 | AZ14: 204177 | BA14: 209950 | BB14: 220717 | BC14: 237917 | BD14: =BC14+(-CF!BD22-CF!BD23)-CF!BD9 -> 239987.74 | BE14: =BD14 -> 239987.74 | BF14: =BE14+(-CF!BF22-CF!BF23)-CF!BF9 -> 244856.43 | BG14: =BF14+(-CF!BG22-CF!BG23)-CF!BG9 -> 249704.5 | BH14: =BG14+(-CF!BH22-CF!BH23)-CF!BH9 -> 254298.78 | BI14: =BH14+(-CF!BI22-CF!BI23)-CF!BI9 -> 260543.15 | BJ14: =BI14 -> 260543.15 | BK14: =BJ14+(-CF!BK22-CF!BK23)-CF!BK9 -> 269876.33 | BL14: =BK14+(-CF!BL22-CF!BL23)-CF!BL9 -> 275866.86 | BM14: =BL14+(-CF!BM22-CF!BM23)-CF!BM9 -> 277808.54
A15: Operating Leases | E15: 0 | F15: 0 | G15: 0 | H15: 0 | I15: 0 | J15: 0 | K15: 0 | L15: 0 | M15: 0 | N15: 0 | O15: 0 | P15: 0 | Q15: 0 | R15: 0 | S15: 0 | T15: 0 | U15: 0 | V15: 0 | W15: 0 | X15: 0 | Y15: 0 | Z15: 0 | AA15: 0 | AB15: 20132 | AC15: 21649 | AD15: 23114 | AE15: 25141 | AF15: 25141 | AG15: 26279 | AH15: 25141 | AI15: 34119 | AJ15: 37553 | AK15: 37553 | AL15: 39328 | AM15: 43346 | AN15: 52151 | AO15: 56082 | AP15: 56082 | AQ15: 56161 | AR15: 58430 | AS15: 62033 | AT15: 66123 | AU15: 66123 | AV15: 68262 | AW15: 70332 | AX15: 70758 | AY15: 72513 | AZ15: 72513 | BA15: 73313 | BB15: 74575 | BC15: 76527 | BD15: =BC15*(AY15/AX15) -> 78425.088 | BE15: =BD15 -> 78425.088 | BF15: =BE15*(BA15/AZ15) -> 79290.313 | BG15: =BF15*(BB15/BA15) -> 80655.205 | BH15: =BG15*(BC15/BB15) -> 82766.355 | BI15: =BH15*(BD15/BC15) -> 84819.196 | BJ15: =BI15 -> 84819.196 | BK15: =BJ15*(BJ15/BE15) -> 91734.625 | BL15: =BK15*(BK15/BJ15) -> 99213.879 | BM15: =BL15*(BL15/BK15) -> 107302.93
A16: Goodwill | E16: 438 | F16: 1234 | G16: 1349 | H16: 1955 | I16: 2552 | J16: 2655 | K16: 3319 | L16: 3759 | M16: 3785 | N16: 3774 | O16: 3815 | P16: 3784 | Q16: 3784 | R16: 3823 | S16: 4254 | T16: 13271 | U16: 13350 | V16: 13350 | W16: 13388 | X16: 13944 | Y16: 14553 | Z16: 14548 | AA16: 14548 | AB16: 14708 | AC16: 14727 | AD16: 14734 | AE16: 14754 | AF16: 14754 | AG16: 14739 | AH16: 14754 | AI16: 14960 | AJ16: 15017 | AK16: 15017 | AL16: 15220 | AM16: 15350 | AN16: 15345 | AO16: 15371 | AP16: 15371 | AQ16: 20229 | AR16: 20195 | AS16: 20168 | AT16: 20288 | AU16: 20288 | AV16: 22749 | AW16: 22785 | AX16: 22749 | AY16: 22789 | AZ16: 22789 | BA16: 22770 | BB16: 22879 | BC16: 23081 | BD16: =AVERAGE(BA16:BC16) -> 22910 | BE16: =BD16 -> 22910 | BF16: =AVERAGE(BC16:BE16) -> 22967 | BG16: =AVERAGE(BD16:BF16) -> 22929 | BH16: =AVERAGE(BE16:BG16) -> 22935.333 | BI16: =AVERAGE(BF16:BH16) -> 22943.778 | BJ16: =BI16 -> 22943.778 | BK16: =AVERAGE(BH16:BJ16) -> 22940.963 | BL16: =AVERAGE(BI16:BK16) -> 22942.84 | BM16: =AVERAGE(BJ16:BL16) -> 22942.527
A17: Other Assets, Non-Current | E17: 865 | F17: 1492 | G17: 1287 | H17: 1416 | I17: 1647 | J17: 1930 | K17: 2892 | L17: 3445 | M17: 3522 | N17: 3892 | O17: 4296 | P17: 4723 | Q17: 4723 | R17: 5054 | S17: 5437 | T17: 8083 | U17: 8897 | V17: 8897 | W17: 9814 | X17: 10907 | Y17: 11238 | Z17: 11202 | AA17: 11202 | AB17: 12783 | AC17: 13462 | AD17: 14535 | AE17: 16314 | AF17: 16314 | AG17: 16456 | AH17: 16314 | AI17: 20150 | AJ17: 22778 | AK17: 22778 | AL17: 25660 | AM17: 27273 | AN17: 29227 | AO17: 27235 | AP17: 27235 | AQ17: 32033 | AR17: 33730 | AS17: 37503 | AT17: 42758 | AU17: 42758 | AV17: 46392 | AW17: 50224 | AX17: 53913 | AY17: 56024 | AZ17: 56024 | BA17: 60947 | BB17: 63340 | BC17: 71309 | BD17: =BC17*(AY17/AX17) -> 74101.152 | BE17: =BD17 -> 74101.152 | BF17: =BE17 -> 74101.152 | BG17: =BF17*(BB17/BA17) -> 77010.632 | BH17: =BG17 -> 77010.632 | BI17: =BH17*(BD17/BC17) -> 80026.035 | BJ17: =BI17 -> 80026.035 | BK17: =BJ17*(BJ17/BE17) -> 86424.652 | BL17: =BK17*(BK17/BJ17) -> 93334.882 | BM17: =BL17*(BL17/BK17) -> 100797.63
A18: Total Non-Current Assets | E18: =SUM(E14:E17) -> 2157 | F18: =SUM(F14:F17) -> 4016 | G18: =SUM(G14:G17) -> 5050 | H18: =SUM(H14:H17) -> 7788 | I18: =SUM(I14:I17) -> 11259 | J18: =SUM(J14:J17) -> 15534 | K18: =SUM(K14:K17) -> 23178 | L18: =SUM(L14:L17) -> 29042 | ... BM18: =SUM(BM14:BM17) -> 508851.63
A20: Total Assets | E20: =E18+E12 -> 8110 | F20: =F18+F12 -> 13541 | G20: =G18+G12 -> 18601 | H20: =H18+H12 -> 24927 | I20: =I18+I12 -> 32555 | J20: =J18+J12 -> 40159 | K20: =K18+K12 -> 54505 | L20: =L18+L12 -> 64747 | ... BM20: =BM18+BM12 -> 953398.25
A22: Accounts Payable | E22: 3594 | F22: 5605 | G22: 8051 | H22: 11145 | I22: 13318 | J22: 15133 | K22: 16459 | L22: 20397 | M22: 14990 | N22: 16123 | O22: 18801 | P22: 25309 | Q22: 25309 | R22: 18891 | S22: 21439 | T22: 26075 | U22: 34616 | V22: 34616 | W22: 25172 | X22: 27657 | Y22: 30904 | Z22: 38192 | AA22: 38192 | AB22: 31809 | AC22: 36063 | AD22: 35794 | AE22: 47183 | AF22: 47183 | AG22: 40056 | AH22: 47183 | AI22: 58334 | AJ22: 72539 | AK22: 72539 | AL22: 63926 | AM22: 66090 | AN22: 71474 | AO22: 78664 | AP22: 78664 | AQ22: 68547 | AR22: 71219 | AS22: 67760 | AT22: 79600 | AU22: 79600 | AV22: 66907 | AW22: 69481 | AX22: 72004 | AY22: 84981 | AZ22: 84981 | BA22: 73068 | BB22: 81817 | BC22: 84570 | BD22: =BC22*(BC22/BB22) -> 87415.634 | BE22: =BD22 -> 87415.634 | BF22: =BE22+(BA22-AZ22) -> 75502.634 | BG22: =BF22+(BB22-BA22) -> 84251.634 | BH22: =BG22+(BC22-BB22) -> 87004.634 | BI22: =BH22+(BD22-BC22) -> 89850.267 | BJ22: =BI22 -> 89850.267 | BK22: =BJ22+(BJ22-BE22) -> 92284.901 | BL22: =BK22+(BK22-BJ22) -> 94719.535 | BM22: =BL22+(BL22-BK22) -> 97154.168
A23: Accrued Expenses & Other | E23: 1152 | F23: 1759 | G23: 2321 | H23: 3751 | I23: 4892 | J23: 6688 | K23: 9807 | L23: 10372 | M23: 9431 | N23: 9613 | O23: 10497 | P23: 13739 | Q23: 13739 | R23: 13054 | S23: 14016 | T23: 15844 | U23: 18170 | V23: 18170 | W23: 16691 | X23: 17140 | Y23: 18420 | Z23: 23663 | AA23: 23663 | AB23: 24588 | AC23: 26140 | AD23: 28961 | AE23: 32439 | AF23: 32439 | AG23: 30791 | AH23: 32439 | AI23: 34327 | AJ23: 44138 | AK23: 44138 | AL23: 40939 | AM23: 41007 | AN23: 41546 | AO23: 51775 | AP23: 51775 | AQ23: 58141 | AR23: 56254 | AS23: 59974 | AT23: 62566 | AU23: 62566 | AV23: 66382 | AW23: 64235 | AX23: 58812 | AY23: 64709 | AZ23: 64709 | BA23: 63970 | BB23: 60351 | BC23: 60602 | BD23: =BC23+(AY23-AX23) -> 66499 | BE23: =BD23 -> 66499 | BF23: =BE23+(BA23-AZ23) -> 65760 | BG23: =BF23+(BB23-BA23) -> 62141 | BH23: =BG23+(BC23-BB23) -> 62392 | BI23: =BH23+(BD23-BC23) -> 68289 | BJ23: =BI23 -> 68289 | BK23: =BJ23+(BJ23-BE23) -> 70079 | BL23: =BK23+(BK23-BJ23) -> 71869 | BM23: =BL23+(BL23-BK23) -> 73659
A24: Unearned Revenue | E24: 0 | F24: 0 | G24: 0 | H24: 0 | I24: 792 | J24: 1159 | K24: 1823 | L24: 3118 | M24: 3766 | N24: 3851 | O24: 4200 | P24: 4768 | Q24: 4768 | R24: 5454 | S24: 5065 | T24: 5153 | U24: 5097 | V24: 5097 | W24: 6182 | X24: 6004 | Y24: 6000 | Z24: 6536 | AA24: 6536 | AB24: 7298 | AC24: 7475 | AD24: 7381 | AE24: 8190 | AF24: 8190 | AG24: 8864 | AH24: 8190 | AI24: 9251 | AJ24: 9708 | AK24: 9708 | AL24: 10539 | AM24: 10695 | AN24: 10974 | AO24: 11827 | AP24: 11827 | AQ24: 12820 | AR24: 12818 | AS24: 12629 | AT24: 13227 | AU24: 13227 | AV24: 14281 | AW24: 14522 | AX24: 14398 | AY24: 15227 | AZ24: 15227 | BA24: 15927 | BB24: 16004 | BC24: 16305 | BD24: =BC24+(AY24-AX24) -> 17134 | BE24: =BD24 -> 17134 | BF24: =BE24+(BA24-AZ24) -> 17834 | BG24: =BF24+(BB24-BA24) -> 17911 | BH24: =BG24+(BC24-BB24) -> 18212 | BI24: =BH24+(BD24-BC24) -> 19041 | BJ24: =BI24 -> 19041 | BK24: =BJ24+(BJ24-BE24) -> 20948 | BL24: =BK24+(BK24-BJ24) -> 22855 | BM24: =BL24+(BL24-BK24) -> 24762
A25: Total Current Liabilities | E25: =SUM(E22:E24) -> 4746 | F25: =SUM(F22:F24) -> 7364 | G25: =SUM(G22:G24) -> 10372 | H25: =SUM(H22:H24) -> 14896 | I25: =SUM(I22:I24) -> 19002 | J25: =SUM(J22:J24) -> 22980 | K25: =SUM(K22:K24) -> 28089 | L25: =SUM(L22:L24) -> 33887 | ... BM25: =SUM(BM22:BM24) -> 195575.17
A27: Long-Term Lease Liabilities | E27: 0 | F27: 0 | G27: 0 | H27: 0 | I27: 0 | J27: 0 | K27: 0 | L27: 0 | M27: 0 | N27: 0 | O27: 0 | P27: 0 | Q27: 0 | R27: 0 | S27: 0 | T27: 0 | U27: 0 | V27: 0 | W27: 0 | X27: 0 | Y27: 0 | Z27: 9650 | AA27: 9650 | AB27: 33275 | AC27: 35134 | AD27: 37058 | AE27: 39791 | AF27: 39791 | AG27: 40300 | AH27: 39791 | AI27: 48589 | AJ27: 52573 | AK27: 52573 | AL27: 53067 | AM27: 56297 | AN27: 63848 | AO27: 67651 | AP27: 67651 | AQ27: 65731 | AR27: 66524 | AS27: 69332 | AT27: 72968 | AU27: 72968 | AV27: 74267 | AW27: 75822 | AX27: 75891 | AY27: 77297 | AZ27: 77297 | BA27: 77052 | BB27: 78084 | BC27: 79802 | BD27: =BC27+(AY27-AX27) -> 81208 | BE27: =BD27 -> 81208 | BF27: =BE27+(BA27-AZ27) -> 80963 | BG27: =BF27+(BB27-BA27) -> 81995 | BH27: =BG27+(BC27-BB27) -> 83713 | BI27: =BH27+(BD27-BC27) -> 85119 | BJ27: =BI27 -> 85119 | BK27: =BJ27+(BJ27-BE27) -> 89030 | BL27: =BK27+(BK27-BJ27) -> 92941 | BM27: =BL27+(BL27-BK27) -> 96852
A28: Long-Term Debt | E28: 409 | F28: 109 | G28: 0 | H28: 255 | I28: 3084 | J28: 3191 | K28: 8265 | L28: 8227 | M28: 8219 | N28: 8212 | O28: 8205 | P28: 7694 | Q28: 7694 | R28: 7691 | S28: 7683 | T28: 24710 | U28: 24743 | V28: 24743 | W28: 24640 | X28: 24638 | Y28: 24684 | Z28: 23495 | AA28: 23495 | AB28: 23322 | AC28: 23329 | AD28: 22472 | AE28: 23414 | AF28: 23414 | AG28: 23437 | AH28: 23414 | AI28: 32929 | AJ28: 31816 | AK28: 31816 | AL28: 31868 | AM28: 50279 | AN28: 50055 | AO28: 48744 | AP28: 48744 | AQ28: 47556 | AR28: 58053 | AS28: 58919 | AT28: 67150 | AU28: 67150 | AV28: 67084 | AW28: 63092 | AX28: 61098 | AY28: 58314 | AZ28: 58314 | BA28: 57634 | BB28: 54889 | BC28: 54890 | BD28: =BC28*(1+Valuation!$P$17) -> 56954.6 | BE28: =BD28 -> 56954.6 | BF28: =BE28*(1+Valuation!$P$17) -> 59096.857 | BG28: =BF28*(1+Valuation!$P$17) -> 61319.691 | BH28: =BG28*(1+Valuation!$P$17) -> 63626.134 | BI28: =BH28*(1+Valuation!$P$17) -> 66019.33 | BJ28: =BI28 -> 66019.33 | BK28: =BJ28*(1+Valuation!$P$17) -> 68502.542 | BL28: =BK28*(1+Valuation!$P$17) -> 71079.157 | BM28: =BL28*(1+Valuation!$P$17) -> 73752.686
A29: Other Long-Term Liabilities | E29: 487 | F29: 1083 | G29: 1561 | H29: 2370 | I29: 2277 | J29: 4242 | K29: 7410 | L29: 9249 | M29: 9966 | N29: 10739 | O29: 11412 | P29: 12607 | Q29: 12607 | R29: 14205 | S29: 16364 | T29: 18827 | U29: 20975 | V29: 20975 | W29: 22214 | X29: 23666 | Y29: 24562 | Z29: 17563 | AA29: 17563 | AB29: 9400 | AC29: 10149 | AD29: 10925 | AE29: 12171 | AF29: 12171 | AG29: 12518 | AH29: 12171 | AI29: 15974 | AJ29: 17017 | AK29: 17017 | AL29: 19418 | AM29: 21148 | AN29: 23945 | AO29: 23643 | AP29: 23643 | AQ29: 23971 | AR29: 23458 | AS29: 22259 | AT29: 21121 | AU29: 21121 | AV29: 20931 | AW29: 21853 | AX29: 21707 | AY29: 25451 | AZ29: 25451 | BA29: 26657 | BB29: 27226 | BC29: 29306 | BD29: =BC29+(AY29-AX29) -> 33050 | BE29: =BD29 -> 33050 | BF29: =BE29+(BA29-AZ29) -> 34256 | BG29: =BF29+(BB29-BA29) -> 34825 | BH29: =BG29+(BC29-BB29) -> 36905 | BI29: =BH29+(BD29-BC29) -> 40649 | BJ29: =BI29 -> 40649 | BK29: =BJ29+(BJ29-BE29) -> 48248 | BL29: =BK29+(BK29-BJ29) -> 55847 | BM29: =BL29+(BL29-BK29) -> 63446
A30: Total Non-Current Liabilities | E30: =SUM(E27:E29) -> 896 | F30: =SUM(F27:F29) -> 1192 | G30: =SUM(G27:G29) -> 1561 | H30: =SUM(H27:H29) -> 2625 | I30: =SUM(I27:I29) -> 5361 | J30: =SUM(J27:J29) -> 7433 | K30: =SUM(K27:K29) -> 15675 | L30: =SUM(L27:L29) -> 17476 | ... BM30: =SUM(BM27:BM29) -> 234050.69
A32: Total Liabilities | E32: =E30+E25 -> 5642 | F32: =F30+F25 -> 8556 | G32: =G30+G25 -> 11933 | H32: =H30+H25 -> 17521 | I32: =I30+I25 -> 24363 | J32: =J30+J25 -> 30413 | K32: =K30+K25 -> 43764 | L32: =L30+L25 -> 51363 | ... BM32: =BM30+BM25 -> 429625.85
A34: Preferred Stock | E34: 0 | F34: 0 | G34: 0 | H34: 0 | I34: 0 | J34: 0 | K34: 0 | L34: 0 | M34: 0 | N34: 0 | O34: 0 | P34: 0 | Q34: 0 | R34: 0 | S34: 0 | T34: 0 | U34: 0 | V34: 0 | W34: 0 | X34: 0 | Y34: 0 | Z34: 0 | AA34: 0 | AB34: 0 | AC34: 0 | AD34: 0 | AE34: 0 | AF34: 0 | AG34: 0 | AH34: 0 | AI34: 0 | AJ34: 0 | AK34: 0 | AL34: 0 | AM34: 0 | AN34: 0 | AO34: 0 | AP34: 0 | AQ34: 0 | AR34: 0 | AS34: 0 | AT34: 0 | AU34: 0 | AV34: 0 | AW34: 0 | AX34: 0 | AY34: 0 | AZ34: 0 | BA34: 0 | BB34: 0 | BC34: 0 | BD34: 0 | BE34: =BD34 -> 0 | BF34: 0 | BG34: 0 | BH34: 0 | BI34: 0 | BJ34: =BI34 -> 0 | BK34: =BJ34 -> 0 | BL34: =BK34 -> 0 | BM34: =BL34 -> 0
A35: Common Stock | E35: 4 | F35: 5 | G35: 5 | H35: 5 | I35: 5 | J35: 5 | K35: 5 | L35: 5 | M35: 5 | N35: 5 | O35: 5 | P35: 5 | Q35: 5 | R35: 5 | S35: 5 | T35: 5 | U35: 5 | V35: 5 | W35: 5 | X35: 5 | Y35: 5 | Z35: 5 | AA35: 5 | AB35: 5 | AC35: 5 | AD35: 5 | AE35: 5 | AF35: 5 | AG35: 5 | AH35: 5 | AI35: 5 | AJ35: 5 | AK35: 5 | AL35: 5 | AM35: 5 | AN35: 5 | AO35: 5 | AP35: 5 | AQ35: 5 | AR35: 107 | AS35: 107 | AT35: 108 | AU35: 108 | AV35: 108 | AW35: 108 | AX35: 108 | AY35: 109 | AZ35: 109 | BA35: 109 | BB35: 110 | BC35: 110 | BD35: =BC35 -> 110 | BE35: =BD35 -> 110 | BF35: =BE35 -> 110 | BG35: =BF35 -> 110 | BH35: =BG35 -> 110 | BI35: =BH35 -> 110 | BJ35: =BI35 -> 110 | BK35: =BJ35 -> 110 | ... BM35: =BL35 -> 110
A36: Treasury Stock | E36: -600 | F36: -600 | G36: -600 | H36: -877 | I36: -1837 | J36: -1837 | K36: -1837 | L36: -1837 | M36: -1837 | N36: -1837 | O36: -1837 | P36: -1837 | Q36: -1837 | R36: -1837 | S36: -1837 | T36: -1837 | U36: -1837 | V36: -1837 | W36: -1837 | X36: -1837 | Y36: -1837 | Z36: -1837 | AA36: -1837 | AB36: -1837 | AC36: -1837 | AD36: -1837 | AE36: -1837 | AF36: -1837 | AG36: -1837 | AH36: -1837 | AI36: -1837 | AJ36: -1837 | AK36: -1837 | AL36: -1837 | AM36: -1837 | AN36: -1837 | AO36: -1837 | AP36: -1837 | AQ36: -4503 | AR36: -7837 | AS36: -7837 | AT36: -7837 | AU36: -7837 | AV36: -7837 | AW36: -7837 | AX36: -7837 | AY36: -7837 | AZ36: -7837 | BA36: -7837 | BB36: -7837 | BC36: -7837 | BD36: =BC36 -> -7837 | BE36: =BD36 -> -7837 | BF36: =BE36 -> -7837 | BG36: =BF36 -> -7837 | BH36: =BG36 -> -7837 | BI36: =BH36 -> -7837 | BJ36: =BI36 -> -7837 | BK36: =BJ36 -> -7837 | ... BM36: =BL36 -> -7837
A37: Additional Paid-In Capital | E37: 4121 | F37: 5736 | G37: 6325 | H37: 6990 | I37: 8347 | J37: 9573 | K37: 11135 | L37: 13394 | M37: 14144 | N37: 15026 | O37: 15968 | P37: 17186 | Q37: 17186 | R37: 17976 | S37: 19129 | T37: 20212 | U37: 21389 | V37: 21389 | W37: 22563 | X37: 24028 | Y37: 25375 | Z37: 26791 | AA37: 26791 | AB37: 28059 | AC37: 30035 | AD37: 31817 | AE37: 33658 | AF37: 33658 | AG37: 35412 | AH37: 33658 | AI37: 40307 | AJ37: 42865 | AK37: 42865 | AL37: 45160 | AM37: 48724 | AN37: 51879 | AO37: 55538 | AP37: 55538 | AQ37: 58793 | AR37: 63871 | AS37: 69419 | AT37: 75066 | AU37: 75066 | AV37: 79863 | AW37: 86896 | AX37: 92711 | AY37: 99025 | AZ37: 99025 | BA37: 103938 | BB37: 110633 | BC37: 115934 | BD37: =BC37 -> 115934 | BE37: =BD37 -> 115934 | BF37: =BE37 -> 115934 | BG37: =BF37 -> 115934 | BH37: =BG37 -> 115934 | BI37: =BH37 -> 115934 | BJ37: =BI37 -> 115934 | BK37: =BJ37 -> 115934 | ... BM37: =BL37 -> 115934
A38: Accumulated Other Comprehensive Income (Loss) | E38: -123 | F38: -56 | G38: -190 | H38: -316 | I38: -239 | J38: -185 | K38: -511 | L38: -723 | M38: -614 | N38: -571 | O38: -521 | P38: -985 | Q38: -985 | R38: -797 | S38: -607 | T38: -501 | U38: -484 | V38: -484 | W38: -467 | X38: -934 | Y38: -1034 | Z38: -1035 | AA38: -1035 | AB38: -1010 | AC38: -960 | AD38: -1429 | AE38: -986 | AF38: -986 | AG38: -2063 | AH38: -986 | AI38: -1029 | AJ38: -180 | AK38: -180 | AL38: -666 | AM38: -525 | AN38: -1075 | AO38: -1376 | AP38: -1376 | AQ38: -2365 | AR38: -4782 | AS38: -7115 | AT38: -4487 | AU38: -4487 | AV38: -3973 | AW38: -3680 | AX38: -5003 | AY38: -3040 | AZ38: -3040 | BA38: -3598 | BB38: -3993 | BC38: -1918 | BD38: =AVERAGE(BA38:BC38) -> -3169.6667 | BE38: =BD38 -> -3169.6667 | BF38: =AVERAGE(BC38:BE38) -> -2752.4444 | BG38: =AVERAGE(BD38:BF38) -> -3030.5926 | BH38: =AVERAGE(BE38:BG38) -> -2984.2346 | BI38: =AVERAGE(BF38:BH38) -> -2922.4239 | BJ38: =BI38 -> -2922.4239 | BK38: =BJ38+(BJ38-BE38) -> -2675.1811 | BL38: =BK38+(BK38-BF38) -> -2597.9177 | BM38: =BL38+(BL38-BG38) -> -2165.2428
A39: Retained Earnings | E39: -730 | F39: 172 | G39: 1324 | H39: 1955 | I39: 1916 | J39: 2190 | K39: 1949 | L39: 2545 | M39: 3058 | N39: 3915 | O39: 4167 | P39: 4916 | Q39: 4916 | R39: 6327 | S39: 6524 | T39: 6779 | U39: 8636 | V39: 8636 | W39: 11199 | X39: 13733 | Y39: 16616 | Z39: 19625 | AA39: 19625 | AB39: 23193 | AC39: 25818 | AD39: 27952 | AE39: 31220 | AF39: 31220 | AG39: 33755 | AH39: 31220 | AI39: 45329 | AJ39: 52551 | AK39: 52551 | AL39: 60658 | AM39: 68436 | AN39: 71592 | AO39: 85915 | AP39: 85915 | AQ39: 82071 | AR39: 80043 | AS39: 82915 | AT39: 83193 | AU39: 83193 | AV39: 86365 | AW39: 93115 | AX39: 102994 | AY39: 113618 | AZ39: 113618 | BA39: 124049 | BB39: 137534 | BC39: 152862 | BD39: =BC39+IS!BD31 -> 166516.85 | BE39: =BD39 -> 166516.85 | BF39: =BE39+IS!BF31 -> 179211.14 | BG39: =BF39+IS!BG31 -> 192330.05 | BH39: =BG39+IS!BH31 -> 206408.16 | BI39: =BH39+IS!BI31 -> 223032.17 | BJ39: =BI39 -> 223032.17 | BK39: =BJ39+IS!BK31 -> 284221.67 | BL39: =BK39+IS!BL31 -> 347904.16 | BM39: =BL39+IS!BM31 -> 417730.64
A40: Total Stockholders' Equity | E40: =SUM(E34:E39) -> 2672 | F40: =SUM(F34:F39) -> 5257 | G40: =SUM(G34:G39) -> 6864 | H40: =SUM(H34:H39) -> 7757 | I40: =SUM(I34:I39) -> 8192 | J40: =SUM(J34:J39) -> 9746 | K40: =SUM(K34:K39) -> 10741 | L40: =SUM(L34:L39) -> 13384 | ... BM40: =SUM(BM34:BM39) -> 523772.4
A42: Total Liabilities & Stockholders' Equity | E42: =E40+E32 -> 8314 | F42: =F40+F32 -> 13813 | G42: =G40+G32 -> 18797 | H42: =H40+H32 -> 25278 | I42: =I40+I32 -> 32555 | J42: =J40+J32 -> 40159 | K42: =K40+K32 -> 54505 | L42: =L40+L32 -> 64747 | ... BM42: =BM40+BM32 -> 953398.25
A43: CHECK | E43: =E20-E42 -> -204 | F43: =F20-F42 -> -272 | G43: =G20-G42 -> -196 | H43: =H20-H42 -> -351 | I43: =I20-I42 -> 0 | J43: =J20-J42 -> 0 | K43: =K20-K42 -> 0 | L43: =L20-L42 -> 0 | ... BM43: =BM20-BM42 -> 0
A45: Key Metrics
A46: Cash | E46: =E8+E9 -> 3727 | F46: =F8+F9 -> 6366 | G46: =G8+G9 -> 8762 | H46: =H8+H9 -> 9576 | I46: =I8+I9 -> 11448 | J46: =J8+J9 -> 12447 | K46: =K8+K9 -> 17416 | L46: =L8+L9 -> 19808 | ... BM46: =BM8+BM9 -> 277519.38
A47: Debt | E47: =E28+E27 -> 409 | F47: =F28+F27 -> 109 | G47: =G28+G27 -> 0 | H47: =H28+H27 -> 255 | I47: =I28+I27 -> 3084 | J47: =J28+J27 -> 3191 | K47: =K28+K27 -> 8265 | L47: =L28+L27 -> 8227 | ... BM47: =BM28+BM27 -> 170604.69
A48: Net Cash / (Debt) | E48: =E46-E47 -> 3318 | F48: =F46-F47 -> 6257 | G48: =G46-G47 -> 8762 | H48: =H46-H47 -> 9321 | I48: =I46-I47 -> 8364 | J48: =J46-J47 -> 9256 | K48: =K46-K47 -> 9151 | L48: =L46-L47 -> 11581 | ... BM48: =BM46-BM47 -> 106914.69
A49: Invested Capital | E49: =E40+E27+E28 -> 3081 | F49: =F40+F27+F28 -> 5366 | G49: =G40+G27+G28 -> 6864 | H49: =H40+H27+H28 -> 8012 | I49: =I40+I27+I28 -> 11276 | J49: =J40+J27+J28 -> 12937 | K49: =K40+K27+K28 -> 19006 | L49: =L40+L27+L28 -> 21611 | ... BM49: =BM40+BM27+BM28 -> 694377.08
A50: Net PP&E | E50: =E14+E15 -> 854 | F50: =F14+F15 -> 1290 | G50: =G14+G15 -> 2414 | H50: =H14+H15 -> 4417 | I50: =I14+I15 -> 7060 | J50: =J14+J15 -> 10949 | K50: =K14+K15 -> 16967 | L50: =L14+L15 -> 21838 | ... BM50: =BM14+BM15 -> 385111.47
A51: Working Capital | E51: =(E12)-(E25) -> 1207 | F51: =(F12)-(F25) -> 2161 | G51: =(G12)-(G25) -> 3179 | H51: =(H12)-(H25) -> 2243 | I51: =(I12)-(I25) -> 2294 | J51: =(J12)-(J25) -> 1645 | K51: =(K12)-(K25) -> 3238 | L51: =(L12)-(L25) -> 1818 | ... BM51: =(BM12)-(BM25) -> 248971.46
A52: Working Capital Change | AK52: =AK51-AF51 -> -2174 | AP52: =AP51-AK51 -> 12966 | AU52: =AU51-AP51 -> -27916 | AZ52: =AZ51-AU51 -> 16036 | BE52: =BE51-AZ51 -> 19908.803 | BJ52: =BJ51-BE51 -> 44429.112 | BK52: =BK51-BF51 -> 86790.796 | BL52: =BL51-BG51 -> 136675.13 | BM52: =BM51-BH51 -> 190107.5

Sheet PB_CACHE_JS
A1: {"Ratios":{"F|^NASDAQ:AMZNRevenue % GrowthFY12/31/2021USDt":{"r":[[0.21695366571345676]],"c":null,"a":["Ratios!H2"]},"F|^NASDAQ:AMZN0.216953665713457FY12/31/2022USDt":{"id":4,"description":null,"headerValues":[],"financialValues":[],"customValues":[],"error":"PBXLP_FIELD"},"F|^NASDAQ:AMZN#FIELDNOTFOUNDFY12/31/2023USDt":{"id":5,"description":null,"headerValues":[],"financialValues":[],"customValues":[],"error":"PBXLP_FIELD"},"F|^NASDAQ:AMZNRevenue % GrowthFY12/31/2023USDt":{"r":[[0.1182957412988368]],"c":null,"a":["Ratios!J2"]},"F|^NASDAQ:AMZNRevenue % GrowthFY12/31/2022USDt":{"r":[[0.09399517263985091]],"c":null,"a":["Ratios!I2"]},"F|^NASDAQ:AMZNDebt to EquityFY12/31/2023USDt":{"r":[[0.6717572755417957]],"c":null,"a":["Ratios!J7"]},"F|^NASDAQ:AMZNNet Income from Continuing Operations % GrowthFY12/31/2023USDt":{"id":34,"description":null,"headerValues":[],"financialValues":[],"customValues":[],"error":null},"F|^NASDAQ:AMZNAssets TurnoverFY12/31/2023USDt":{"r":[[1.1878682994151022]],"c":null,"a":["Ratios!J8"]},"F|^NASDAQ:AMZNBook Value to Net IncomeFY12/31/2023USDt":{"r":[[5.613929334428923]],"c":null,"a":["Ratios!J5"]},"F|^NASDAQ:AMZNNet Income Available to Common Stockholders % GrowthFY12/31/2023USDt":{"id":31,"description":null,"headerValues":[],"financialValues":[],"customValues":[],"error":null},"F|^NASDAQ:AMZNQuick RatioFY12/31/2023USDt":{"r":[[0.8430483212767634]],"c":null,"a":["Ratios!J6"]},"F|^NASDAQ:AMZNDebt to EquityFY12/31/2022USDt":{"r":[[0.9594297569893798]],"c":null,"a":["Ratios!I7"]},"F|^NASDAQ:AMZNNet Income from Continuing Operations % GrowthFY12/31/2022USDt":{"id":35,"description":null,"headerValues":[],"financialValues":[],"customValues":[],"error":null},"F|^NASDAQ:AMZNAssets TurnoverFY12/31/2022USDt":{"r":[[1.1997282082236853]],"c":null,"a":["Ratios!I8"]},"F|^NASDAQ:AMZNBook Value to Net IncomeFY12/31/2022USDt":{"id":29,"description":null,"headerValues":[],"financialValues":[],"customValues":[],"error":null},"F|^NASDAQ:AMZNNet Income Available to Common Stockholders % GrowthFY12/31/2022USDt":{"id":32,"description":null,"headerValues":[],"financialValues":[],"customValues":[],"error":null},"F|^NASDAQ:AMZNQuick RatioFY12/31/2022USDt":{"r":[[0.7232372114574016]],"c":null,"a":["Ratios!I6"]},"F|^NASDAQ:AMZNDebt to EquityFY12/31/2021USDt":{"r":[[0.8419472675322797]],"c":null,"a":["Ratios!H7"]},"F|^NASDAQ:AMZNNet Income from Continuing Operations % GrowthFY12/31/2021USDt":{"id":36,"description":null,"headerValues":[],"financialValues":[],"customValues":[],"error":null},"F|^NASDAQ:AMZNAssets TurnoverFY12/31/2021USDt":{"r":[[1.2996128452609228]],"c":null,"a":["Ratios!H8"]},"F|^NASDAQ:AMZNBook Value to Net IncomeFY12/31/2021USDt":{"r":[[3.418870639012109]],"c":null,"a":["Ratios!H5"]},"F|^NASDAQ:AMZNNet Income Available to Common Stockholders % GrowthFY12/31/2021USDt":{"r":[[0.5641085743753222]],"c":null,"a":["Ratios!H4"]},"F|^NASDAQ:AMZNQuick RatioFY12/31/2021USDt":{"r":[[0.9063303951752352]],"c":null,"a":["Ratios!H6"]},"F|^NASDAQ:AMZNNormalized Return on Invested Capital (ROIC)FY12/31/2023USDt":{"id":10,"description":null,"headerValues":[],"financialValues":[],"customValues":[],"error":"PBXLP_FIELD"},"F|^NASDAQ:AMZNNormalized Return on Invested Capital (ROIC)FY12/31/2022USDt":{"id":11,"description":null,"headerValues":[],"financialValues":[],"customValues":[],"error":"PBXLP_FIELD"},"F|^NASDAQ:AMZNNormalized Return on Invested Capital (ROIC)FY12/31/2021USDt":{"id":12,"description":null,"headerValues":[],"financialValues":[],"customValues":[],"error":"PBXLP_FIELD"},"F|^NASDAQ:AMZNNormalized Return on Assets (ROA)FY12/31/2023USDt":{"id":13,"description":null,"headerValues":[],"financialValues":[],"customValues":[],"error":"PBXLP_FIELD"},"F|^NASDAQ:AMZNNormalized Return on Assets (ROA)FY12/31/2022USDt":{"id":14,"description":null,"headerValues":[],"financialValues":[],"customValues":[],"error":"PBXLP_FIELD"},"F|^NASDAQ:AMZNNormalized Return on Assets (ROA)FY12/31/2021USDt":{"id":15,"description":null,"headerValues":[],"financialValues":[],"customValues":[],"error":"PBXLP_FIELD"},"F|^NASDAQ:AMZNNormalized Return on Equity (ROE)FY12/31/2023USDt":{"id":16,"description":null,"headerValues":[],"financialValues":[],"customValues":[],"error":"PBXLP_FIELD"},"F|^NASDAQ:AMZNNormalized Return on Equity (ROE)FY12/31/2022USDt":{"id":17,"description":null,"headerValues":[],"financialValues":[],"customValues":[],"error":"PBXLP_FIELD"},"F|^NASDAQ:AMZNNormalized Return on Equity (ROE)FY12/31/2021USDt":{"id":18,"description":null,"headerValues":[],"financialValues":[],"customValues":[],"error":"PBXLP_FIELD"},"F|^NASDAQ:AMZNStock PriceFY12/31/2021USDt":{"r":[[166.717]],"c":null,"a":["Ratios!H12"]},"F|^NASDAQ:AMZNEV to EBITDAFY12/31/2022USDt":{"r":[[18.519077187823548]],"c":null,"a":["Ratios!I17"]},"F|^NASDAQ:AMZNPrice to Tangible Book ValueFY12/31/2022USDt":{"r":[[7.301608407701946]],"c":null,"a":["Ratios!I22"]},"F|^NASDAQ:AMZNPrice to BookFY12/31/2022USDt":{"r":[[6.2305493530391525]],"c":null,"a":["Ratios!I20"]},"F|^NASDAQ:AMZNPrice to Cash FlowFY12/31/2022USDt":{"r":[[14.000799269239554]],"c":null,"a":["Ratios!I21"]},"F|^NASDAQ:AMZNPrice to EarningsFY12/31/2022USDt":{"r":[[76.39836289222374]],"c":null,"a":["Ratios!I18"]},"F|^NASDAQ:AMZNEnterprise Value (EV)FY12/31/2022USDt":{"r":[[926527950784]],"c":null,"a":["Ratios!I14"]},"F|^NASDAQ:AMZNEV to RevenueFY12/31/2022USDt":{"r":[[1.8449712376048157]],"c":null,"a":["Ratios!I15"]},"F|^NASDAQ:AMZNForward PE RatioFY12/31/2022USDt":{"r":[[47.19101123595505]],"c":null,"a":["Ratios!I19"]},"F|^NASDAQ:AMZNStock PriceFY12/31/2022USDt":{"r":[[84]],"c":null,"a":["Ratios!I12"]},"F|^NASDAQ:AMZNEV to EBIT FY12/31/2022USDt":{"r":[[80.89827562944207]],"c":null,"a":["Ratios!I16"]},"F|^NASDAQ:AMZNMarket CapFY12/31/2022USDt":{"r":[[856938950784]],"c":null,"a":["Ratios!I13"]},"F|^NASDAQ:AMZNEV to EBITDAFY12/31/2023USDt":{"r":[[22.957125591920857]],"c":null,"a":["Ratios!J17"]},"F|^NASDAQ:AMZNPrice to Tangible Book ValueFY12/31/2023USDt":{"r":[[9.795911973237468]],"c":null,"a":["Ratios!J22"]},"F|^NASDAQ:AMZNPrice to BookFY12/31/2023USDt":{"r":[[8.57798800915982]],"c":null,"a":["Ratios!J20"]},"F|^NASDAQ:AMZNPrice to Cash FlowFY12/31/2023USDt":{"r":[[18.327341541532245]],"c":null,"a":["Ratios!J21"]},"F|^NASDAQ:AMZNPrice to EarningsFY12/31/2023USDt":{"r":[[79.54973821989529]],"c":null,"a":["Ratios!J18"]},"F|^NASDAQ:AMZNEnterprise Value (EV)FY12/31/2023USDt":{"r":[[1642972607237]],"c":null,"a":["Ratios!J14"]},"F|^NASDAQ:AMZNEV to RevenueFY12/31/2023USDt":{"r":[[2.965504644597385]],"c":null,"a":["Ratios!J15"]},"F|^NASDAQ:AMZNForward PE RatioFY12/31/2023USDt":{"r":[[42.016469770347385]],"c":null,"a":["Ratios!J19"]},"F|^NASDAQ:AMZNStock PriceFY12/31/2023USDt":{"r":[[151.94]],"c":null,"a":["Ratios!J12"]},"F|^NASDAQ:AMZNEV to EBIT FY12/31/2023USDt":{"r":[[69.67948629021588]],"c":null,"a":["Ratios!J16"]},"F|^NASDAQ:AMZNMarket CapFY12/31/2023USDt":{"r":[[1570152607237]],"c":null,"a":["Ratios!J13"]},"F|^NASDAQ:AMZNEV to EBITDAFY12/31/2021USDt":{"r":[[26.797882078580855]],"c":null,"a":["Ratios!H17"]},"F|^NASDAQ:AMZNPrice to Tangible Book ValueFY12/31/2021USDt":{"r":[[16.066588543894166]],"c":null,"a":["Ratios!H22"]},"F|^NASDAQ:AMZNPrice to BookFY12/31/2021USDt":{"r":[[14.021684582462429]],"c":null,"a":["Ratios!H20"]},"F|^NASDAQ:AMZNPrice to Cash FlowFY12/31/2021USDt":{"r":[[25.349865704772476]],"c":null,"a":["Ratios!H21"]},"F|^NASDAQ:AMZNPrice to EarningsFY12/31/2021USDt":{"r":[[65.21298650498728]],"c":null,"a":["Ratios!H18"]},"F|^NASDAQ:AMZNEnterprise Value (EV)FY12/31/2021USDt":{"r":[[1725917595271]],"c":null,"a":["Ratios!H14"]},"F|^NASDAQ:AMZNEV to RevenueFY12/31/2021USDt":{"r":[[3.7686670275479566]],"c":null,"a":["Ratios!H15"]},"F|^NASDAQ:AMZNForward PE RatioFY12/31/2021USDt":{"r":[[3.232829164242777]],"c":null,"a":["Ratios!H19"]},"F|^NASDAQ:AMZNEV to EBIT FY12/31/2021USDt":{"r":[[53.44556390768897]],"c":null,"a":["Ratios!H16"]},"F|^NASDAQ:AMZNMarket CapFY12/31/2021USDt":{"r":[[1691002595271]],"c":null,"a":["Ratios!H13"]},"F|^NASDAQ:AMZNDebt to EquityFY09/30/2024USDt":{"r":[[0.6717572755417957]],"c":null,"a":["Ratios!K5"]},"F|^NASDAQ:AMZNPrice to Tangible Book ValueFY09/30/2024USDt":{"r":[[9.795911973237468]],"c":null,"a":["Ratios!K22"]},"F|^NASDAQ:AMZNEnterprise Value (EV)FY09/30/2024USDt":{"r":[[1642972607237]],"c":null,"a":["Ratios!K14"]},"F|^NASDAQ:AMZNEV to RevenueFY09/30/2024USDt":{"r":[[2.965504644597385]],"c":null,"a":["Ratios!K15"]},"F|^NASDAQ:AMZNForward PE RatioFY09/30/2024USDt":{"r":[[42.016469770347385]],"c":null,"a":["Ratios!K19"]},"F|^NASDAQ:AMZNBook Value to Net IncomeFY09/30/2024USDt":{"r":[[5.613929334428923]],"c":null,"a":["Ratios!K3"]},"F|^NASDAQ:AMZNStock PriceFY09/30/2024USDt":{"r":[[151.94]],"c":null,"a":["Ratios!K12"]},"F|^NASDAQ:AMZNMarket CapFY09/30/2024USDt":{"r":[[1570152607237]],"c":null,"a":["Ratios!K13"]},"F|^NASDAQ:AMZNEV to EBITDAFY09/30/2024USDt":{"r":[[22.957125591920857]],"c":null,"a":["Ratios!K17"]},"F|^NASDAQ:AMZNPrice to Cash FlowFY09/30/2024USDt":{"r":[[18.327341541532245]],"c":null,"a":["Ratios!K21"]},"F|^NASDAQ:AMZNPrice to BookFY09/30/2024USDt":{"r":[[8.57798800915982]],"c":null,"a":["Ratios!K20"]},"F|^NASDAQ:AMZNPrice to EarningsFY09/30/2024USDt":{"r":[[79.54973821989529]],"c":null,"a":["Ratios!K18"]},"F|^NASDAQ:AMZNAssets TurnoverFY09/30/2024USDt":{"r":[[1.1878682994151022]],"c":null,"a":["Ratios!K6"]},"F|^NASDAQ:AMZNQuick RatioFY09/30/2024USDt":{"r":[[0.8430483212767634]],"c":null,"a":["Ratios!K4"]},"F|^NASDAQ:AMZNEV to EBIT FY09/30/2024USDt":{"r":[[69.67948629021588]],"c":null,"a":["Ratios!K16"]},"F|^NASDAQ:AMZNRevenue % GrowthFY09/30/2024USDt":{"r":[[0.1182957412988368]],"c":null,"a":["Ratios!K2"]},"F|^NASDAQ:AMZNNormalized Return on Invested Capital (ROIC)FY09/30/2024USDt":{"id":132,"description":null,"headerValues":[],"financialValues":[],"customValues":[],"error":"PBXLP_FIELD"},"F|^NASDAQ:AMZNNormalized Return on Assets (ROA)FY09/30/2024USDt":{"id":133,"description":null,"headerValues":[],"financialValues":[],"customValues":[],"error":"PBXLP_FIELD"},"F|^NASDAQ:AMZNNormalized Return on Equity (ROE)FY09/30/2024USDt":{"id":134,"description":null,"headerValues":[],"financialValues":[],"customValues":[],"error":"PBXLP_FIELD"},"F|^NASDAQ:AMZNRevenue % GrowthFY09/30/2024USD":{"r":[[0.1182957412988368]],"c":null,"a":["Ratios!K2"]},"F|^NASDAQ:AMZNRevenue % GrowthFY09/30/2024USDr":{"r":[[0.1182957412988368]],"c":null,"a":["Ratios!K2"]},"F|^NASDAQ:AMZNRevenue % GrowthFQ09/30/2024USDr":{"r":[[0.10115862869559389]],"c":null,"a":["Ratios!K2"]},"F|^NASDAQ:AMZNRevenue % GrowthFQ09/30/2024USDt":{"r":[[0.11038348371225104]],"c":null,"a":["Ratios!K2"]},"F|^NASDAQ:AMZNBook Value to Net IncomeFQ09/30/2024USDt":{"id":165,"description":null,"headerValues":[],"financialValues":[],"customValues":[],"error":null},"F|^NASDAQ:AMZNPrice to Tangible Book ValueFQ09/30/2024USDt":{"r":[[9.15212812780941]],"c":null,"a":["Ratios!K22"]},"F|^NASDAQ:AMZNForward PE RatioFQ09/30/2024USDt":{"r":[[31.688775510204085]],"c":null,"a":["Ratios!K19"]},"F|^NASDAQ:AMZNEV to RevenueFQ09/30/2024USDt":{"r":[[3.3086339291467963]],"c":null,"a":["Ratios!K15"]},"F|^NASDAQ:AMZNStock PriceFQ09/30/2024USDt":{"r":[[186.33]],"c":null,"a":["Ratios!K12"]},"F|^NASDAQ:AMZNEnterprise Value (EV)FQ09/30/2024USDt":{"r":[[1999519976937]],"c":null,"a":["Ratios!K14"]},"F|^NASDAQ:AMZNDebt to EquityFQ09/30/2024USDt":{"id":163,"description":null,"headerValues":[],"financialValues":[],"customValues":[],"error":null},"F|^NASDAQ:AMZNQuick RatioFQ09/30/2024USDt":{"id":164,"description":null,"headerValues":[],"financialValues":[],"customValues":[],"error":null},"F|^NASDAQ:AMZNEV to EBIT FQ09/30/2024USDt":{"r":[[37.723233222092254]],"c":null,"a":["Ratios!K16"]},"F|^NASDAQ:AMZNMarket CapFQ09/30/2024USDt":{"r":[[1955638976937]],"c":null,"a":["Ratios!K13"]},"F|^NASDAQ:AMZNAssets TurnoverFQ09/30/2024USDt":{"id":162,"description":null,"headerValues":[],"financialValues":[],"customValues":[],"error":null},"F|^NASDAQ:AMZNEV to EBITDAFQ09/30/2024USDt":{"r":[[19.4736942376848]],"c":null,"a":["Ratios!K17"]},"F|^NASDAQ:AMZNPrice to BookFQ09/30/2024USDt":{"r":[[8.266553181051146]],"c":null,"a":["Ratios!K20"]},"F|^NASDAQ:AMZNPrice to Cash FlowFQ09/30/2024USDt":{"r":[[17.258035481062254]],"c":null,"a":["Ratios!K21"]},"F|^NASDAQ:AMZNPrice to EarningsFQ09/30/2024USDt":{"r":[[44.47016706443914]],"c":null,"a":["Ratios!K18"]},"F|^NASDAQ:AMZNMultiplesFQ09/30/2024USDt":{"id":158,"description":null,"headerValues":[],"financialValues":[],"customValues":[],"error":"PBXLP_FIELD"},"F|^NASDAQ:AMZNNormalized Return on Invested Capital (ROIC)FQ09/30/2024USDt":{"id":159,"description":null,"headerValues":[],"financialValues":[],"customValues":[],"error":"PBXLP_FIELD"},"F|^NASDAQ:AMZNNormalized Return on Assets (ROA)FQ09/30/2024USDt":{"id":160,"description":null,"headerValues":[],"financialValues":[],"customValues":[],"error":"PBXLP_FIELD"},"F|^NASDAQ:AMZNNormalized Return on Equity (ROE)FQ09/30/2024USDt":{"id":161,"description":null,"headerValues":[],"financialValues":[],"customValues":[],"error":"PBXLP_FIELD"},"F|^NASDAQ:AMZNNormalizedROEFY12/31/2021USDt":{"r":[[0.27754587530972336]],"c":null,"a":["Ratios!H7"]},"F|^NASDAQ:AMZNNormalizedROEFY12/31/2023USDt":{"r":[[0.2871295190796761]],"c":null,"a":["Ratios!J7"]},"F|^NASDAQ:AMZNNormalizedROEFY12/31/2022USDt":{"r":[[0.18452319625134608]],"c":null,"a":["Ratios!I7"]},"F|^NASDAQ:AMZNNormalizedROEFQ09/30/2024USDt":{"id":167,"description":null,"headerValues":[],"financialValues":[],"customValues":[],"error":null},"F|^NASDAQ:AMZNNormalizedROAFY12/31/2021USDt":{"r":[[0.08757420521560523]],"c":null,"a":["Ratios!H8"]},"F|^NASDAQ:AMZNNormalizedROAFY12/31/2022USDt":{"r":[[0.05919507712360084]],"c":null,"a":["Ratios!I8"]},"F|^NASDAQ:AMZNNormalizedROAFY12/31/2023USDt":{"r":[[0.10135338051378334]],"c":null,"a":["Ratios!J8"]},"F|^NASDAQ:AMZNNormalizedROAFQ09/30/2024USDt":{"id":171,"description":null,"headerValues":[],"financialValues":[],"customValues":[],"error":null},"F|^NASDAQ:AMZNNormalizedROICFY12/31/2023USDt":{"r":[[0.15911951361010523]],"c":null,"a":["Ratios!J9"]},"F|^NASDAQ:AMZNNormalizedROICFY12/31/2022USDt":{"r":[[0.10096422529103502]],"c":null,"a":["Ratios!I9"]},"F|^NASDAQ:AMZNNormalizedROICFY12/31/2021USDt":{"r":[[0.15256817982603557]],"c":null,"a":["Ratios!H9"]},"F|^NASDAQ:AMZNNormalizedROICFQ09/30/2024USDt":{"id":179,"description":null,"headerValues":[],"financialValues":[],"customValues":[],"error":null},"F|^NASDAQ:AMZNInterest and Dividend IncomeFY12/31/2022USDt":{"r":[[989000000]],"c":null,"a":["Ratios!I35"]},"F|^NASDAQ:AMZNCommon Equity Book ValueFY12/31/2022USDt":{"r":[[146043000000]],"c":null,"a":["Ratios!I28"]},"F|^NASDAQ:AMZNTotal Unusual ItemsFY12/31/2022USDt":{"r":[[35547000000]],"c":null,"a":["Ratios!I42"]},"F|^NASDAQ:AMZNNormalized Basic EPSFY12/31/2022USDt":{"r":[[2.4861222887427616]],"c":null,"a":["Ratios!I36"]},"F|^NASDAQ:AMZNNormalized IncomeFY12/31/2022USDt":{"r":[[25360130000]],"c":null,"a":["Ratios!I40"]},"F|^NASDAQ:AMZNNet Tangible AssetsFY12/31/2022USDt":{"r":[[436290000000]],"c":null,"a":["Ratios!I29"]},"F|^NASDAQ:AMZNInvested CapitalFY12/31/2022USDt":{"r":[[286161000000]],"c":null,"a":["Ratios!I31"]},"F|^NASDAQ:AMZNTangible Book ValueFY12/31/2022USDt":{"r":[[119658000000]],"c":null,"a":["Ratios!I30"]},"F|^NASDAQ:AMZNTax Effect of Unusual ItemsFY12/31/2022USDt":{"r":[[7464870000]],"c":null,"a":["Ratios!I41"]},"F|^NASDAQ:AMZNRepayment of DebtFY12/31/2022USDt":{"r":[[-47001000000]],"c":null,"a":["Ratios!I48"]},"F|^NASDAQ:AMZNTotal Unusual Items Excluding GoodwillFY12/31/2022USDt":{"r":[[35547000000]],"c":null,"a":["Ratios!I43"]},"F|^NASDAQ:AMZNFree Cash FlowFY12/31/2022USDt":{"r":[[3993000000]],"c":null,"a":["Ratios!I46"]},"F|^NASDAQ:AMZNRecommended Normalized Basic EPSFY12/31/2022USDt":{"r":[[2.4861222887427616]],"c":null,"a":["Ratios!I37"]},"F|^NASDAQ:AMZNEnterprise ValueFY12/31/2022USDt":{"r":[[926527950784]],"c":null,"a":["Ratios!I32"]},"F|^NASDAQ:AMZNTotal DebtFY12/31/2022USDt":{"r":[[140118000000]],"c":null,"a":["Ratios!I25"]},"F|^NASDAQ:AMZNCapital Lease ObligationsFY12/31/2022USDt":{"id":744,"description":null,"headerValues":[],"financialValues":[],"customValues":[],"error":null},"F|^NASDAQ:AMZNIssuance of DebtFY12/31/2022USDt":{"r":[[62719000000]],"c":null,"a":["Ratios!I47"]},"F|^NASDAQ:AMZNNet DebtFY12/31/2022USDt":{"r":[[70092000000]],"c":null,"a":["Ratios!I26"]},"F|^NASDAQ:AMZNRecommended Normalized Diluted EPSFY12/31/2022USDt":{"r":[[2.4861222887427616]],"c":null,"a":["Ratios!I39"]},"F|^NASDAQ:AMZNNormalized Diluted EPSFY12/31/2022USDt":{"r":[[2.4861222887427616]],"c":null,"a":["Ratios!I38"]},"F|^NASDAQ:AMZNInterest and Dividend IncomeFY12/31/2023USDt":{"r":[[2949000000]],"c":null,"a":["Ratios!J35"]},"F|^NASDAQ:AMZNCommon Equity Book ValueFY12/31/2023USDt":{"r":[[201875000000]],"c":null,"a":["Ratios!J28"]},"F|^NASDAQ:AMZNTotal Unusual ItemsFY12/31/2023USDt":{"r":[[22973000000]],"c":null,"a":["Ratios!J42"]},"F|^NASDAQ:AMZNNormalized Basic EPSFY12/31/2023USDt":{"r":[[4.756852964963235]],"c":null,"a":["Ratios!J36"]},"F|^NASDAQ:AMZNNormalized IncomeFY12/31/2023USDt":{"r":[[49042812950.98118]],"c":null,"a":["Ratios!J40"]},"F|^NASDAQ:AMZNNet Tangible AssetsFY12/31/2023USDt":{"r":[[497378000000]],"c":null,"a":["Ratios!J29"]},"F|^NASDAQ:AMZNInvested CapitalFY12/31/2023USDt":{"r":[[337486000000]],"c":null,"a":["Ratios!J31"]},"F|^NASDAQ:AMZNTangible Book ValueFY12/31/2023USDt":{"r":[[171399000000]],"c":null,"a":["Ratios!J30"]},"F|^NASDAQ:AMZNTax Effect of Unusual ItemsFY12/31/2023USDt":{"r":[[4355187049.018825]],"c":null,"a":["Ratios!J41"]},"F|^NASDAQ:AMZNRepayment of DebtFY12/31/2023USDt":{"r":[[-34008000000]],"c":null,"a":["Ratios!J48"]},"F|^NASDAQ:AMZNTotal Unusual Items Excluding GoodwillFY12/31/2023USDt":{"r":[[22973000000]],"c":null,"a":["Ratios!J43"]},"F|^NASDAQ:AMZNFree Cash FlowFY12/31/2023USDt":{"r":[[43758000000]],"c":null,"a":["Ratios!J46"]},"F|^NASDAQ:AMZNRecommended Normalized Basic EPSFY12/31/2023USDt":{"r":[[4.756852964963235]],"c":null,"a":["Ratios!J37"]},"F|^NASDAQ:AMZNEnterprise ValueFY12/31/2023USDt":{"r":[[1642972607237]],"c":null,"a":["Ratios!J32"]},"F|^NASDAQ:AMZNTotal DebtFY12/31/2023USDt":{"r":[[135611000000]],"c":null,"a":["Ratios!J25"]},"F|^NASDAQ:AMZNCapital Lease ObligationsFY12/31/2023USDt":{"id":743,"description":null,"headerValues":[],"financialValues":[],"customValues":[],"error":null},"F|^NASDAQ:AMZNIssuance of DebtFY12/31/2023USDt":{"r":[[18129000000]],"c":null,"a":["Ratios!J47"]},"F|^NASDAQ:AMZNNet DebtFY12/31/2023USDt":{"r":[[48831000000]],"c":null,"a":["Ratios!J26"]},"F|^NASDAQ:AMZNRecommended Normalized Diluted EPSFY12/31/2023USDt":{"r":[[4.674477025446166]],"c":null,"a":["Ratios!J39"]},"F|^NASDAQ:AMZNNormalized Diluted EPSFY12/31/2023USDt":{"r":[[4.674477025446166]],"c":null,"a":["Ratios!J38"]},"F|^NASDAQ:AMZNInterest and Dividend IncomeFY12/31/2021USDt":{"r":[[448000000]],"c":null,"a":["Ratios!H35"]},"F|^NASDAQ:AMZNCommon Equity Book ValueFY12/31/2021USDt":{"r":[[138245000000]],"c":null,"a":["Ratios!H28"]},"F|^NASDAQ:AMZNTotal Unusual ItemsFY12/31/2021USDt":{"r":[[-1950000000]],"c":null,"a":["Ratios!H42"]},"F|^NASDAQ:AMZNNormalized Basic EPSFY12/31/2021USDt":{"r":[[3.131460004757267]],"c":null,"a":["Ratios!H36"]},"F|^NASDAQ:AMZNNormalized IncomeFY12/31/2021USDt":{"r":[[31658880868.129276]],"c":null,"a":["Ratios!H40"]},"F|^NASDAQ:AMZNNet Tangible AssetsFY12/31/2021USDt":{"r":[[400071000000]],"c":null,"a":["Ratios!H29"]},"F|^NASDAQ:AMZNInvested CapitalFY12/31/2021USDt":{"r":[[254640000000]],"c":null,"a":["Ratios!H31"]},"F|^NASDAQ:AMZNTangible Book ValueFY12/31/2021USDt":{"r":[[117767000000]],"c":null,"a":["Ratios!H30"]},"F|^NASDAQ:AMZNTax Effect of Unusual ItemsFY12/31/2021USDt":{"r":[[-244880868.12927577]],"c":null,"a":["Ratios!H41"]},"F|^NASDAQ:AMZNRepayment of DebtFY12/31/2021USDt":{"r":[[-20668000000]],"c":null,"a":["Ratios!H48"]},"F|^NASDAQ:AMZNTotal Unusual Items Excluding GoodwillFY12/31/2021USDt":{"r":[[-1950000000]],"c":null,"a":["Ratios!H43"]},"F|^NASDAQ:AMZNFree Cash FlowFY12/31/2021USDt":{"r":[[4885000000]],"c":null,"a":["Ratios!H46"]},"F|^NASDAQ:AMZNRecommended Normalized Basic EPSFY12/31/2021USDt":{"r":[[3.131460004757267]],"c":null,"a":["Ratios!H37"]},"F|^NASDAQ:AMZNEnterprise ValueFY12/31/2021USDt":{"r":[[1725917595271]],"c":null,"a":["Ratios!H32"]},"F|^NASDAQ:AMZNTotal DebtFY12/31/2021USDt":{"r":[[116395000000]],"c":null,"a":["Ratios!H25"]},"F|^NASDAQ:AMZNCapital Lease ObligationsFY12/31/2021USDt":{"id":745,"description":null,"headerValues":[],"financialValues":[],"customValues":[],"error":null},"F|^NASDAQ:AMZNIssuance of DebtFY12/31/2021USDt":{"r":[[26959000000]],"c":null,"a":["Ratios!H47"]},"F|^NASDAQ:AMZNNet DebtFY12/31/2021USDt":{"r":[[20346000000]],"c":null,"a":["Ratios!H26"]},"F|^NASDAQ:AMZNRecommended Normalized Diluted EPSFY12/31/2021USDt":{"r":[[3.074390138707195]],"c":null,"a":["Ratios!H39"]},"F|^NASDAQ:AMZNNormalized Diluted EPSFY12/31/2021USDt":{"r":[[3.074390138707195]],"c":null,"a":["Ratios!H38"]},"F|^NASDAQ:AMZNTotal Unusual ItemsFQ09/30/2024USDt":{"r":[[5368000000]],"c":null,"a":["Ratios!K42"]},"F|^NASDAQ:AMZNInterest and Dividend IncomeFQ09/30/2024USDt":{"r":[[1256000000]],"c":null,"a":["Ratios!K35"]},"F|^NASDAQ:AMZNCommon Equity Book ValueFQ09/30/2024USDt":{"id":738,"description":null,"headerValues":[],"financialValues":[],"customValues":[],"error":null},"F|^NASDAQ:AMZNTotal DebtFQ09/30/2024USDt":{"r":[[0]],"c":null,"a":["Ratios!K25"]},"F|^NASDAQ:AMZNNormalized IncomeFQ09/30/2024USDt":{"r":[[19890666075.28968]],"c":null,"a":["Ratios!K40"]},"F|^NASDAQ:AMZNNet Tangible AssetsFQ09/30/2024USDt":{"id":734,"description":null,"headerValues":[],"financialValues":[],"customValues":[],"error":null},"F|^NASDAQ:AMZNFree Cash FlowFQ09/30/2024USDt":{"r":[[10025000000]],"c":null,"a":["Ratios!K46"]},"F|^NASDAQ:AMZNRecommended Normalized Basic EPSFQ09/30/2024USDt":{"r":[[1.8944982454327857]],"c":null,"a":["Ratios!K37"]},"F|^NASDAQ:AMZNEnterprise ValueFQ09/30/2024USDt":{"r":[[1999519976937]],"c":null,"a":["Ratios!K32"]},"F|^NASDAQ:AMZNTotal Unusual Items Excluding GoodwillFQ09/30/2024USDt":{"r":[[5368000000]],"c":null,"a":["Ratios!K43"]},"F|^NASDAQ:AMZNNet DebtFQ09/30/2024USDt":{"r":[[0]],"c":null,"a":["Ratios!K26"]},"F|^NASDAQ:AMZNRecommended Normalized Diluted EPSFQ09/30/2024USDt":{"r":[[1.8550271146054664]],"c":null,"a":["Ratios!K39"]},"F|^NASDAQ:AMZNNormalized Diluted EPSFQ09/30/2024USDt":{"r":[[1.8550271146054664]],"c":null,"a":["Ratios!K38"]},"F|^NASDAQ:AMZNIssuance of DebtFQ09/30/2024USDt":{"r":[[1725000000]],"c":null,"a":["Ratios!K47"]},"F|^NASDAQ:AMZNCapital Lease ObligationsFQ09/30/2024USDt":{"id":742,"description":null,"headerValues":[],"financialValues":[],"customValues":[],"error":null},"F|^NASDAQ:AMZNRepayment of DebtFQ09/30/2024USDt":{"r":[[-4405000000]],"c":null,"a":["Ratios!K48"]},"F|^NASDAQ:AMZNNormalized Basic EPSFQ09/30/2024USDt":{"r":[[1.8944982454327857]],"c":null,"a":["Ratios!K36"]},"F|^NASDAQ:AMZNInvested CapitalFQ09/30/2024USDt":{"r":[[0]],"c":null,"a":["Ratios!K31"]},"F|^NASDAQ:AMZNTax Effect of Unusual ItemsFQ09/30/2024USDt":{"r":[[805333924.7103176]],"c":null,"a":["Ratios!K41"]},"F|^NASDAQ:AMZNTangible Book ValueFQ09/30/2024USDt":{"id":730,"description":null,"headerValues":[],"financialValues":[],"customValues":[],"error":null},"F|^NASDAQ:AMZNCash Flow MetricsFQ09/30/2024USDt":{"id":678,"description":null,"headerValues":[],"financialValues":[],"customValues":[],"error":"PBXLP_FIELD"},"F|^NASDAQ:AMZNCash Flow MetricsFY12/31/2023USDt":{"id":679,"description":null,"headerValues":[],"financialValues":[],"customValues":[],"error":"PBXLP_FIELD"},"F|^NASDAQ:AMZNCash Flow MetricsFY12/31/2022USDt":{"id":680,"description":null,"headerValues":[],"financialValues":[],"customValues":[],"error":"PBXLP_FIELD"},"F|^NASDAQ:AMZNCash Flow MetricsFY12/31/2021USDt":{"id":681,"description":null,"headerValues":[],"financialValues":[],"customValues":[],"error":"PBXLP_FIELD"},"F|^NASDAQ:AMZNProfitability MetricsFQ09/30/2024USDt":{"id":718,"description":null,"headerValues":[],"financialValues":[],"customValues":[],"error":"PBXLP_FIELD"},"F|^NASDAQ:AMZNProfitability MetricsFY12/31/2023USDt":{"id":719,"description":null,"headerValues":[],"financialValues":[],"customValues":[],"error":"PBXLP_FIELD"},"F|^NASDAQ:AMZNProfitability MetricsFY12/31/2022USDt":{"id":720,"description":null,"headerValues":[],"financialValues":[],"customValues":[],"error":"PBXLP_FIELD"},"F|^NASDAQ:AMZNProfitability MetricsFY12/31/2021USDt":{"id":721,"description":null,"headerValues":[],"financialValues":[],"customValues":[],"error":"PBXLP_FIELD"},"F|^NASDAQ:AMZNROEFY12/31/2022USDt":{"r":[[-0.019805582234640122]],"c":null,"a":["Ratios!H7"]},"F|^NASDAQ:AMZNROEFY12/31/2021USDt":{"r":[[0.2924942490040958]],"c":null,"a":["Ratios!G7"]},"F|^NASDAQ:AMZNROEFY12/31/2023USDt":{"r":[[0.17812835545813382]],"c":null,"a":["Ratios!I7"]},"F|^NASDAQ:AMZNROAFY12/31/2021USDt":{"r":[[0.09229087392520025]],"c":null,"a":["Ratios!G8"]},"F|^NASDAQ:AMZNROAFY12/31/2022USDt":{"r":[[-0.006353634619792622]],"c":null,"a":["Ratios!H8"]},"F|^NASDAQ:AMZNROAFY12/31/2023USDt":{"r":[[0.06287723759267289]],"c":null,"a":["Ratios!I8"]},"F|^NASDAQ:AMZNROICFY12/31/2023USDt":{"r":[[0.0989456646073852]],"c":null,"a":["Ratios!I9"]},"F|^NASDAQ:AMZNROICFY12/31/2022USDt":{"r":[[-0.006235188668873606]],"c":null,"a":["Ratios!H9"]},"F|^NASDAQ:AMZNROICFY12/31/2021USDt":{"r":[[0.16048766556392552]],"c":null,"a":["Ratios!G9"]},"F|^NASDAQ:AMZNROICFQ09/30/2024USDt":{"id":1505,"description":null,"headerValues":[],"financialValues":[],"customValues":[],"error":null},"F|^NASDAQ:AMZNROAFQ09/30/2024USDt":{"id":1506,"description":null,"headerValues":[],"financialValues":[],"customValues":[],"error":null},"F|^NASDAQ:AMZNROEFQ09/30/2024USDt":{"id":1507,"description":null,"headerValues":[],"financialValues":[],"customValues":[],"error":null}}}

Sheet CACHE_CHARTS_JS

Sheet CF
A1: Amazon.com Inc. (AMZN)
A2: Statement of Cash Flows
A3: In millions except per share data
BD5: Estimates | BE5: Estimates | BF5: Estimates | BG5: Estimates | BH5: Estimates | BI5: Estimates | BJ5: Estimates | BK5: Estimates | BL5: Estimates | BM5: Estimates
E6: 2008 | F6: 2009 | G6: 2010 | H6: 2011 | I6: 2012 | J6: 2013 | K6: 2014 | L6: 2015 | M6: 42460 | N6: 42551 | O6: 42643 | P6: 42735 | Q6: 2016 | R6: 42825 | S6: 42916 | T6: 43008 | U6: 43100 | V6: 2017 | W6: 43190 | X6: 43281 | Y6: 43373 | Z6: 43465 | AA6: 2018 | AB6: 43555 | AC6: 43646 | AD6: 43738 | AE6: 43830 | AF6: 2019 | AG6: 43921 | AH6: 44012 | AI6: 44104 | AJ6: 44196 | AK6: 2020 | AL6: 44286 | AM6: 44377 | AN6: 44469 | AO6: 44561 | AP6: 2021 | AQ6: 44651 | AR6: 44742 | AS6: 44834 | AT6: 44926 | AU6: 2022 | AV6: 45016 | AW6: 45107 | AX6: 45199 | AY6: 45291 | AZ6: 2023 | BA6: 45382 | BB6: 45473 | BC6: 45565 | BD6: 45657 | BE6: 2024 | BF6: 45747 | BG6: 45838 | BH6: 45930 | BI6: 46022 | BJ6: 2025 | BK6: 2026 | BL6: 2027 | BM6: 2028
A8: Net Income | E8: =IS!E31 -> 645 | F8: =IS!F31 -> 902 | G8: =IS!G31 -> 1152 | H8: =IS!H31 -> 631 | I8: =IS!I31 -> -39 | J8: =IS!J31 -> 274 | K8: =IS!K31 -> -241 | L8: =IS!L31 -> 596 | ... BM8: =IS!BM31 -> 69826.479
A9: Depreciation & Amortization | E9: 287 | F9: 378 | G9: 568 | H9: 1083 | I9: 2159 | J9: 3253 | K9: 4746 | L9: 6281 | M9: 1827 | N9: 1909 | O9: 2084 | P9: 2297 | Q9: 8117 | R9: 2435 | S9: 2633 | T9: 2912 | U9: 3498 | V9: 11478 | W9: 3671 | X9: 3630 | Y9: 3778 | Z9: 4262 | AA9: 15341 | AB9: 4854 | AC9: 5202 | AD9: 5563 | AE9: 6170 | AF9: 21789 | AG9: 5362 | AH9: 5748 | AI9: 6523 | AJ9: 7618 | AK9: 25251 | AL9: 7508 | AM9: 8038 | AN9: 8948 | AO9: 9802 | AP9: 34296 | AQ9: 8978 | AR9: 9594 | AS9: 10204 | AT9: 12685 | AU9: =SUM(AQ9:AT9) -> 41461 | AV9: 11123 | AW9: 11589 | AX9: 12131 | AY9: 13820 | AZ9: =SUM(AV9:AY9) -> 48663 | BA9: 11684 | BB9: 12038 | BC9: 13442 | BD9: =BC9*(AY9/AX9) -> 15313.531 | BE9: =SUM(BA9:BD9) -> 52477.531 | BF9: =BD9*(BA9/AY9) -> 12946.693 | BG9: =BF9*(BB9/BA9) -> 13338.949 | BH9: =BG9*(BC9/BB9) -> 14894.68 | BI9: =BH9*(BD9/BC9) -> 16968.467 | BJ9: =SUM(BF9:BI9) -> 58148.79 | BK9: ='Assumptions + Estimates'!P41*IS!BK15 -> 76688.178 | BL9: ='Assumptions + Estimates'!Q41*IS!BL15 -> 88168.006 | BM9: ='Assumptions + Estimates'!R41*IS!BM15 -> 101277.86
A10: Stock-Based Compensation | E10: 275 | F10: 341 | G10: 424 | H10: 557 | I10: 833 | J10: 1134 | K10: 1497 | L10: 2119 | M10: 544 | N10: 768 | O10: 776 | P10: 887 | Q10: 2975 | R10: 792 | S10: 1158 | T10: 1085 | U10: 1179 | V10: 4214 | W10: 1182 | X10: 1468 | Y10: 1350 | Z10: 1417 | AA10: 5417 | AB10: 1274 | AC10: 1971 | AD10: 1779 | AE10: 1840 | AF10: 6864 | AG10: 1757 | AH10: 2601 | AI10: 2288 | AJ10: 2562 | AK10: 9208 | AL10: 2306 | AM10: 3591 | AN10: 3180 | AO10: 3680 | AP10: 12757 | AQ10: 3250 | AR10: 5209 | AS10: 5556 | AT10: 5606 | AU10: =SUM(AQ10:AT10) -> 19621 | AV10: 4748 | AW10: 7127 | AX10: 5829 | AY10: 6319 | AZ10: =SUM(AV10:AY10) -> 24023 | BA10: 4961 | BB10: 6722 | BC10: 5333 | BD10: =BC10*(AY10/AX10) -> 5781.305 | BE10: =SUM(BA10:BD10) -> 22797.305 | BF10: =BD10*(BA10/AY10) -> 4538.8597 | BG10: =BF10*(BB10/BA10) -> 6150.013 | BH10: =BG10*(BC10/BB10) -> 4879.2055 | BI10: =BH10*(BD10/BC10) -> 5289.3635 | BJ10: =SUM(BF10:BI10) -> 20857.442 | BK10: =BJ10*(BJ10/BE10) -> 19082.645 | BL10: =BK10*(BK10/BJ10) -> 17458.869 | BM10: =BL10*(BL10/BK10) -> 15973.262
A11: Other Operating Expenses / (Income) | E11: -24 | F11: 103 | G11: 106 | H11: 154 | I11: 154 | J11: 114 | K11: 129 | L11: 155 | M11: 43 | N11: 53 | O11: 31 | P11: 31 | Q11: 158 | R11: 42 | S11: 60 | T11: 43 | U11: 56 | V11: 201 | W11: 56 | X11: 85 | Y11: 62 | Z11: 72 | AA11: 275 | AB11: -13 | AC11: 80 | AD11: 47 | AE11: 50 | AF11: 164 | AG11: 67 | AH11: 282 | AI11: 67 | AJ11: -487 | AK11: -71 | AL11: 30 | AM11: 18 | AN11: 24 | AO11: 65 | AP11: 137 | AQ11: 215 | AR11: 122 | AS11: 123 | AT11: 0 | AU11: =SUM(AQ11:AT11) -> 460 | AV11: 534 | AW11: 47 | AX11: -990 | AY11: 0 | AZ11: =SUM(AV11:AY11) -> -409 | BA11: 2734 | BB11: -95 | BC11: -141 | BD11: =BC11*(AY11/AX11) -> 0 | BE11: =SUM(BA11:BD11) -> 2498 | BF11: 0 | BG11: 0 | BH11: 0 | BI11: =BH11*(BD11/BC11) -> 0 | BJ11: =SUM(BF11:BI11) -> 0 | BK11: 0 | BL11: 0 | BM11: 0
A12: Other Expense / (Income) | E12: -195 | F12: -124 | G12: -340 | H12: -122 | I12: -185 | J12: 89 | K12: 53 | L12: 131 | M12: -50 | N12: 32 | O12: -23 | P12: 21 | Q12: -20 | R12: -40 | S12: -120 | T12: -128 | U12: -5 | V12: -293 | W12: -184 | X12: 110 | Y12: 96 | Z12: 197 | AA12: 219 | AB12: -135 | AC12: -7 | AD12: 388 | AE12: -494 | AF12: -248 | AG12: 565 | AH12: -769 | AI12: -1051 | AJ12: -1327 | AK12: -2582 | AL12: -1456 | AM12: -1258 | AN12: 340 | AO12: -11932 | AP12: -14306 | AQ12: 8689 | AR12: 6104 | AS12: -1272 | AT12: 3445 | AU12: =SUM(AQ12:AT12) -> 16966 | AV12: 0 | AW12: 0 | AX12: 0 | AY12: -339 | AZ12: =SUM(AV12:AY12) -> -339 | BA12: 0 | BB12: 0 | BC12: 0 | BD12: 0 | BE12: =SUM(BA12:BD12) -> 0 | BF12: 0 | BG12: 0 | BH12: 0 | BI12: 0 | BJ12: =SUM(BF12:BI12) -> 0 | BK12: 0 | BL12: 0 | BM12: 0
A13: Deferred Income Taxes | E13: -5 | F13: 81 | G13: 4 | H13: 136 | I13: -265 | J13: -156 | K13: -316 | L13: 81 | M13: 11 | N13: 106 | O13: -81 | P13: -282 | Q13: -246 | R13: -22 | S13: 376 | T13: -74 | U13: -308 | V13: -28 | W13: 141 | X13: -139 | Y13: 266 | Z13: 173 | AA13: 441 | AB13: 415 | AC13: 105 | AD13: 92 | AE13: 185 | AF13: 797 | AG13: 322 | AH13: 465 | AI13: 295 | AJ13: -1636 | AK13: -554 | AL13: 1703 | AM13: 701 | AN13: 909 | AO13: -3623 | AP13: -310 | AQ13: -2001 | AR13: -1955 | AS13: -825 | AT13: -3367 | AU13: =SUM(AQ13:AT13) -> -8148 | AV13: -472 | AW13: -2744 | AX13: -1196 | AY13: -1464 | AZ13: =SUM(AV13:AY13) -> -5876 | BA13: -938 | BB13: -785 | BC13: -1317 | BD13: =BC13*(AY13/AX13) -> -1612.1137 | BE13: =SUM(BA13:BD13) -> -4652.1137 | BF13: =BD13*(BA13/AY13) -> -1032.898 | BG13: =BF13*(BB13/BA13) -> -864.4189 | BH13: =BG13*(BC13/BB13) -> -1450.2416 | BI13: =BH13*(BD13/BC13) -> -1775.2122 | BJ13: =SUM(BF13:BI13) -> -5122.7707 | BK13: =BJ13*(BJ13/BE13) -> -5641.0443 | BL13: =BK13*(BK13/BJ13) -> -6211.752 | BM13: =BL13*(BL13/BK13) -> -6840.1985
A14: Changes in Operating Assets and Liabilities
A15: Inventories | E15: -232 | F15: -531 | G15: -1019 | H15: -1777 | I15: -999 | J15: -1410 | K15: -1193 | L15: -2187 | M15: 769 | N15: -57 | O15: -1095 | P15: -1043 | Q15: -1426 | R15: 947 | S15: -682 | T15: -1593 | U15: -2255 | V15: -3583 | W15: 2220 | X15: -1090 | Y15: -1094 | Z15: -1350 | AA15: -1314 | AB15: 719 | AC15: -2100 | AD15: -381 | AE15: -1516 | AF15: -3278 | AG15: 1392 | AH15: -672 | AI15: -3899 | AJ15: 329 | AK15: -2850 | AL15: -304 | AM15: -209 | AN15: -7059 | AO15: -1915 | AP15: -9487 | AQ15: -2614 | AR15: -3890 | AS15: 732 | AT15: 3180 | AU15: =SUM(AQ15:AT15) -> -2592 | AV15: 371 | AW15: -2373 | AX15: 808 | AY15: 2643 | AZ15: =SUM(AV15:AY15) -> 1449 | BA15: 1776 | BB15: -3085 | BC15: -1509 | BD15: =-(BS!BD10-BS!BC10) -> -938.678 | BE15: =SUM(BA15:BD15) -> -3756.678 | BF15: =-(BS!BF10-BS!BE10) -> -777.87524 | BG15: =-(BS!BG10-BS!BF10) -> -794.21062 | BH15: =-(BS!BH10-BS!BG10) -> -810.88904 | BI15: =-(BS!BI10-BS!BH10) -> -827.91771 | BJ15: =SUM(BF15:BI15) -> -3210.8926 | BK15: =-(BS!BK10-BS!BJ10) -> -805.05141 | BL15: =-(BS!BL10-BS!BK10) -> -821.15244 | BM15: =-(BS!BM10-BS!BL10) -> -837.57549
A16: Accounts Receivable | E16: -218 | F16: -481 | G16: -295 | H16: -866 | I16: -861 | J16: -846 | K16: -1039 | L16: -1755 | M16: 412 | N16: -1184 | O16: -671 | P16: -1924 | Q16: -3367 | R16: 965 | S16: -1221 | T16: -1760 | U16: -2764 | V16: -4780 | W16: 1029 | X16: -1364 | Y16: -2884 | Z16: -1395 | AA16: -4614 | AB16: -401 | AC16: -2193 | AD16: -1181 | AE16: -3906 | AF16: -7681 | AG16: 1262 | AH16: -2854 | AI16: -2016 | AJ16: -4560 | AK16: -8168 | AL16: -2255 | AM16: -4462 | AN16: -4890 | AO16: -6556 | AP16: -18163 | AQ16: -1516 | AR16: -6799 | AS16: -4794 | AT16: -8788 | AU16: =SUM(AQ16:AT16) -> -21897 | AV16: 1521 | AW16: -5167 | AX16: -6718 | AY16: -7447 | AZ16: =SUM(AV16:AY16) -> -17811 | BA16: 3684 | BB16: -2209 | BC16: -701 | BD16: =-(BS!BD11-BS!BC11) -> -10504.801 | BE16: =SUM(BA16:BD16) -> -9730.8009 | BF16: =-(BS!BF11-BS!BE11) -> 5333.8653 | BG16: =-(BS!BG11-BS!BF11) -> -2780.5077 | BH16: =-(BS!BH11-BS!BG11) -> -1821.958 | BI16: =-(BS!BI11-BS!BH11) -> -12493.02 | BJ16: =SUM(BF16:BI16) -> -11761.62 | BK16: =-(BS!BK11-BS!BJ11) -> -13987.714 | BL16: =-(BS!BL11-BS!BK11) -> -16635.135 | BM16: =-(BS!BM11-BS!BL11) -> -19783.627
A17: Accounts Payable | E17: 812 | F17: 1859 | G17: 2373 | H17: 2997 | I17: 2070 | J17: 1888 | K17: 1759 | L17: 4294 | M17: -5770 | N17: 977 | O17: 2540 | P17: 7283 | Q17: 5030 | R17: -6865 | S17: 2088 | T17: 2974 | U17: 8904 | V17: 7101 | W17: -10216 | X17: 2703 | Y17: 3894 | Z17: 6882 | AA17: 3263 | AB17: -6384 | AC17: 3668 | AD17: 226 | AE17: 10683 | AF17: 8193 | AG17: -8044 | AH17: 8616 | AI17: 3658 | AJ17: 13249 | AK17: 17479 | AL17: -8266 | AM17: 47 | AN17: 3832 | AO17: 7989 | AP17: 3602 | AQ17: -9380 | AR17: 3699 | AS17: -1226 | AT17: 9852 | AU17: =SUM(AQ17:AT17) -> 2945 | AV17: -11264 | AW17: 3029 | AX17: 2820 | AY17: 10888 | AZ17: =SUM(AV17:AY17) -> 5473 | BA17: -11282 | BB17: 6005 | BC17: -477 | BD17: =(BS!BD22-BS!BC22) -> 2845.6337 | BE17: =SUM(BA17:BD17) -> -2908.3663 | BF17: =(BS!BF22-BS!BE22) -> -11913 | BG17: =(BS!BG22-BS!BF22) -> 8749 | BH17: =(BS!BH22-BS!BG22) -> 2753 | BI17: =(BS!BI22-BS!BH22) -> 2845.6337 | BJ17: =SUM(BF17:BI17) -> 2434.6337 | BK17: =(BS!BK22-BS!BJ22) -> 2434.6337 | BL17: =(BS!BL22-BS!BK22) -> 2434.6337 | BM17: =(BS!BM22-BS!BL22) -> 2434.6337
A18: Accrued Expenses & Other Liabilities | E18: 247 | F18: 300 | G18: 740 | H18: 1067 | I18: 1038 | J18: 736 | K18: 706 | L18: 913 | M18: -956 | N18: -15 | O18: 441 | P18: 2254 | Q18: 1724 | R18: -1404 | S18: -252 | T18: -122 | U18: 2061 | V18: 283 | W18: -2225 | X18: -205 | Y18: 237 | Z18: 2665 | AA18: 472 | AB18: -2932 | AC18: -623 | AD18: -722 | AE18: 2894 | AF18: -1383 | AG18: -2761 | AH18: 1699 | AI18: -310 | AJ18: 7127 | AK18: 5755 | AL18: -4060 | AM18: -1685 | AN18: -1465 | AO18: 9333 | AP18: 2123 | AQ18: -5903 | AR18: -1412 | AS18: -20 | AT18: 5777 | AU18: =SUM(AQ18:AT18) -> -1558 | AV18: -5763 | AW18: -1938 | AX18: -1321 | AY18: 3792 | AZ18: =SUM(AV18:AY18) -> -5230 | BA18: -5629 | BB18: -7202 | BC18: -4408 | BD18: =(BS!BD23-BS!BC23) -> 5897 | BE18: =SUM(BA18:BD18) -> -11342 | BF18: =(BS!BF23-BS!BE23) -> -739 | BG18: =(BS!BG23-BS!BF23) -> -3619 | BH18: =(BS!BH23-BS!BG23) -> 251 | BI18: =(BS!BI23-BS!BH23) -> 5897 | BJ18: =SUM(BF18:BI18) -> 1790 | BK18: =(BS!BK23-BS!BJ23) -> 1790 | BL18: =(BS!BL23-BS!BK23) -> 1790 | BM18: =(BS!BM23-BS!BL23) -> 1790
A19: Unearned Revenue | E19: 105 | F19: 465 | G19: -218 | H19: 43 | I19: 275 | J19: 399 | K19: 741 | L19: 1292 | M19: 704 | N19: 132 | O19: 405 | P19: 714 | Q19: 1955 | R19: 807 | S19: -387 | T19: 184 | U19: 136 | V19: 740 | W19: 906 | X19: -283 | Y19: - | Z19: 528 | AA19: 1151 | AB19: 888 | AC19: 390 | AD19: -53 | AE19: 485 | AF19: 1710 | AG19: 607 | AH19: 247 | AI19: 78 | AJ19: 333 | AK19: 1265 | AL19: 900 | AM19: 156 | AN19: 338 | AO19: 920 | AP19: 2314 | AQ19: 1336 | AR19: 321 | AS19: 54 | AT19: 505 | AU19: =SUM(AQ19:AT19) -> 2216 | AV19: 818 | AW19: 156 | AX19: -25 | AY19: 3629 | AZ19: =SUM(AV19:AY19) -> 4578 | BA19: 1568 | BB19: 407 | BC19: 421 | BD19: =(BS!BD24-BS!BC24) -> 829 | BE19: =SUM(BA19:BD19) -> 3225 | BF19: =(BS!BF24-BS!BE24) -> 700 | BG19: =(BS!BG24-BS!BF24) -> 77 | BH19: =(BS!BH24-BS!BG24) -> 301 | BI19: =(BS!BI24-BS!BH24) -> 829 | BJ19: =SUM(BF19:BI19) -> 1907 | BK19: =(BS!BK24-BS!BJ24) -> 1907 | BL19: =(BS!BL24-BS!BK24) -> 1907 | BM19: =(BS!BM24-BS!BL24) -> 1907
A20: Cash Flow from Operations (CFO) | E20: =SUM(E8:E19) -> 1697 | F20: =SUM(F8:F19) -> 3293 | G20: =SUM(G8:G19) -> 3495 | H20: =SUM(H8:H19) -> 3903 | I20: =SUM(I8:I19) -> 4180 | J20: =SUM(J8:J19) -> 5475 | K20: =SUM(K8:K19) -> 6842 | L20: =SUM(L8:L19) -> 11920 | ... BM20: =SUM(BM8:BM19) -> 165747.83
A22: Purchases of PP&E | E22: -333 | F22: -373 | G22: -979 | H22: -1811 | I22: -3785 | J22: -3444 | K22: -4893 | L22: -4589 | M22: -1179 | N22: -1711 | O22: -1841 | P22: -2414 | Q22: -7145 | R22: -2148 | S22: -3113 | T22: -3074 | U22: -3619 | V22: -11954 | W22: -3098 | X22: -3243 | Y22: -3352 | Z22: -3733 | AA22: -13426 | AB22: -3290 | AC22: -3562 | AD22: -4697 | AE22: -5312 | AF22: -16861 | AG22: -6795 | AH22: -7459 | AI22: -11063 | AJ22: -14824 | AK22: -40141 | AL22: -12082 | AM22: -14288 | AN22: -15748 | AO22: -18935 | AP22: -61053 | AQ22: -14951 | AR22: -15724 | AS22: -16378 | AT22: -16592 | AU22: =SUM(AQ22:AT22) -> -63645 | AV22: -14207 | AW22: -11455 | AX22: -12479 | AY22: -14588 | AZ22: =SUM(AV22:AY22) -> -52729 | BA22: -14925 | BB22: -17620 | BC22: -22620 | BD22: ='Assumptions + Estimates'!J42*IS!BD15 -> -18787.637 | BE22: =SUM(BA22:BD22) -> -73952.637 | BF22: ='Assumptions + Estimates'!$O42*IS!BF15 -> -18904.378 | BG22: ='Assumptions + Estimates'!$O42*IS!BG15 -> -19536.715 | BH22: ='Assumptions + Estimates'!$O42*IS!BH15 -> -20965.169 | BI22: ='Assumptions + Estimates'!$O42*IS!BI15 -> -24756.536 | BJ22: =SUM(BF22:BI22) -> -84162.797 | BK22: ='Assumptions + Estimates'!P42*IS!BK15 -> -92025.813 | BL22: ='Assumptions + Estimates'!Q42*IS!BL15 -> -100763.44 | BM22: ='Assumptions + Estimates'!R42*IS!BM15 -> -110484.94
A23: Proceeds from PP&E Sales and Incentives | E23: - | F23: - | G23: - | H23: - | I23: - | J23: - | K23: - | L23: - | M23: - | N23: - | O23: - | P23: 409 | Q23: 409 | R23: 287 | S23: 612 | T23: 415 | U23: 583 | V23: 1897 | W23: 371 | X23: 294 | Y23: 825 | Z23: 614 | AA23: 2104 | AB23: 569 | AC23: 919 | AD23: 1312 | AE23: 1371 | AF23: 4171 | AG23: 1367 | AH23: 844 | AI23: 1255 | AJ23: 1629 | AK23: 5095 | AL23: 895 | AM23: 1300 | AN23: 997 | AO23: 2465 | AP23: 5657 | AQ23: 1209 | AR23: 1626 | AS23: 1337 | AT23: 1152 | AU23: =SUM(AQ23:AT23) -> 5324 | AV23: 1137 | AW23: 1043 | AX23: 1181 | AY23: 1235 | AZ23: =SUM(AV23:AY23) -> 4596 | BA23: 990 | BB23: 1227 | BC23: 1342 | BD23: =BC23*(AY23/AX23) -> 1403.3616 | BE23: =SUM(BA23:BD23) -> 4962.3616 | BF23: =(BA23/BE23)*(BE23*1.1) -> 1089 | BG23: =BF23*(BB23/BA23) -> 1349.7 | BH23: =BG23*(BC23/BB23) -> 1476.2 | BI23: =BH23*(BD23/BC23) -> 1543.6977 | BJ23: =SUM(BF23:BI23) -> 5458.5977 | BK23: =BJ23*(BJ23/BE23) -> 6004.4575 | BL23: =BK23*(BK23/BJ23) -> 6604.9032 | BM23: =BL23*(BL23/BK23) -> 7265.3936
A24: Acquisitions, Net of Cash Acquired, & Other | E24: -494 | F24: -40 | G24: -352 | H24: -705 | I24: -745 | J24: -312 | K24: -979 | L24: -795 | M24: -16 | N24: -14 | O24: -84 | P24: -3 | Q24: -117 | R24: -45 | S24: -633 | T24: -13213 | U24: -81 | V24: -13972 | W24: -13 | X24: -866 | Y24: -976 | Z24: -331 | AA24: -2186 | AB24: -1169 | AC24: -117 | AD24: -398 | AE24: -777 | AF24: -2461 | AG24: -91 | AH24: -118 | AI24: -1735 | AJ24: -380 | AK24: -2324 | AL24: -630 | AM24: -320 | AN24: -654 | AO24: -381 | AP24: -1985 | AQ24: -6341 | AR24: -259 | AS24: -885 | AT24: -831 | AU24: =SUM(AQ24:AT24) -> -8316 | AV24: -3513 | AW24: -316 | AX24: -1629 | AY24: -381 | AZ24: =SUM(AV24:AY24) -> -5839 | BA24: -3354 | BB24: -571 | BC24: -622 | BD24: =BC24*(AY24/AX24) -> -145.47698 | BE24: =SUM(BA24:BD24) -> -4692.477 | BF24: =(BA24/BE24)*(BE24*1.1) -> -3689.4 | BG24: =BF24*(BB24/BA24) -> -628.1 | BH24: =BG24*(BC24/BB24) -> -684.2 | BI24: =BH24*(BD24/BC24) -> -160.02468 | BJ24: =SUM(BF24:BI24) -> -5161.7247 | BK24: =BJ24*(BJ24/BE24) -> -5677.8971 | BL24: =BK24*(BK24/BJ24) -> -6245.6869 | BM24: =BL24*(BL24/BK24) -> -6870.2555
A25: Sales and Maturities of Marketable Securities | E25: 1305 | F25: 1966 | G25: 4250 | H25: 6843 | I25: 4237 | J25: 2306 | K25: 3349 | L25: 3025 | M25: 1138 | N25: 931 | O25: 1431 | P25: 1233 | Q25: 4733 | R25: 1910 | S25: 2070 | T25: 2211 | U25: 3485 | V25: 9676 | W25: 2677 | X25: 1660 | Y25: 1964 | Z25: 1938 | AA25: 8239 | AB25: 2643 | AC25: 5161 | AD25: 7251 | AE25: 7626 | AF25: 22681 | AG25: 11626 | AH25: 8138 | AI25: 13135 | AJ25: 17338 | AK25: 50237 | AL25: 17826 | AM25: 13213 | AN25: 15808 | AO25: 12537 | AP25: 59384 | AQ25: 22753 | AR25: 2608 | AS25: 557 | AT25: 5683 | AU25: =SUM(AQ25:AT25) -> 31601 | AV25: 1115 | AW25: 1551 | AX25: 1393 | AY25: 1568 | AZ25: =SUM(AV25:AY25) -> 5627 | BA25: 1392 | BB25: 3265 | BC25: 8069 | BD25: =BC25*(AY25/AX25) -> 9082.6935 | BE25: =SUM(BA25:BD25) -> 21808.693 | BF25: =(BA25/BE25)*(BE25*1.1) -> 1531.2 | BG25: =BF25*(BB25/BA25) -> 3591.5 | BH25: =BG25*(BC25/BB25) -> 8875.9 | BI25: =BH25*(BD25/BC25) -> 9990.9628 | BJ25: =SUM(BF25:BI25) -> 23989.563 | BK25: =BJ25*(BJ25/BE25) -> 26388.519 | BL25: =BK25*(BK25/BJ25) -> 29027.371 | BM25: =BL25*(BL25/BK25) -> 31930.108
A26: Purchases of Marketable Securities | E26: -1677 | F26: -3890 | G26: -6279 | H26: -6257 | I26: -3302 | J26: -2826 | K26: -2542 | L26: -4091 | M26: -636 | N26: -1645 | O26: -2076 | P26: -3399 | Q26: -7756 | R26: -1354 | S26: -4210 | T26: -4817 | U26: -2349 | V26: -12730 | W26: -470 | X26: -537 | Y26: -4033 | Z26: -2060 | AA26: -7100 | AB26: -6876 | AC26: -9950 | AD26: -8542 | AE26: -6444 | AF26: -31812 | AG26: -15001 | AH26: -19209 | AI26: -17468 | AJ26: -20801 | AK26: -72479 | AL26: -14675 | AM26: -21985 | AN26: -15231 | AO26: -8266 | AP26: -60157 | AQ26: -1764 | AR26: -329 | AS26: -239 | AT26: -233 | AU26: =SUM(AQ26:AT26) -> -2565 | AV26: -338 | AW26: -496 | AX26: -219 | AY26: -435 | AZ26: =SUM(AV26:AY26) -> -1488 | BA26: -1965 | BB26: -8439 | BC26: -3068 | BD26: =BC26*(AY26/AX26) -> -6093.9726 | BE26: =SUM(BA26:BD26) -> -19565.973 | BF26: =(BA26/BE26)*(BE26*1.1) -> -2161.5 | BG26: =BF26*(BB26/BA26) -> -9282.9 | BH26: =BG26*(BC26/BB26) -> -3374.8 | BI26: =BH26*(BD26/BC26) -> -6703.3699 | BJ26: =SUM(BF26:BI26) -> -21522.57 | BK26: =BJ26*(BJ26/BE26) -> -23674.827 | BL26: =BK26*(BK26/BJ26) -> -26042.31 | BM26: =BL26*(BL26/BK26) -> -28646.54
A27: Cash Flow from Investing | E27: =SUM(E22:E26) -> -1199 | F27: =SUM(F22:F26) -> -2337 | G27: =SUM(G22:G26) -> -3360 | H27: =SUM(H22:H26) -> -1930 | I27: =SUM(I22:I26) -> -3595 | J27: =SUM(J22:J26) -> -4276 | K27: =SUM(K22:K26) -> -5065 | L27: =SUM(L22:L26) -> -6450 | ... BM27: =SUM(BM22:BM26) -> -106806.23
A29: Proceeds from Short-Term Debt, and Other | E29: - | F29: - | G29: - | H29: - | I29: - | J29: - | K29: - | L29: - | M29: - | N29: - | O29: - | P29: - | Q29: - | R29: - | S29: - | T29: - | U29: - | V29: - | W29: - | X29: - | Y29: - | Z29: - | AA29: - | AB29: - | AC29: 222 | AD29: 415 | AE29: - | AF29: 637 | AG29: - | AH29: 2433 | AI29: 1311 | AJ29: 2434 | AK29: 6178 | AL29: 1926 | AM29: 1176 | AN29: 2187 | AO29: 2667 | AP29: 7956 | AQ29: 13743 | AR29: 4865 | AS29: 12338 | AT29: 10607 | AU29: =SUM(AQ29:AT29) -> 41553 | AV29: 12780 | AW29: 4399 | AX29: 216 | AY29: 734 | AZ29: =SUM(AV29:AY29) -> 18129 | BA29: 338 | BB29: 525 | BC29: 1725 | BD29: =AVERAGE(BA29:BC29,AV29:AY29) -> 2959.5714 | BE29: =SUM(BA29:BD29) -> 5547.5714 | BF29: =(BA29/BE29)*(BE29*1.1) -> 371.8 | BG29: =BF29*(BB29/BA29) -> 577.5 | BH29: =BG29*(BC29/BB29) -> 1897.5 | BI29: =BH29*(BD29/BC29) -> 3255.5286 | BJ29: =SUM(BF29:BI29) -> 6102.3286 | BK29: =BJ29*(BJ29/BE29) -> 6712.5614 | BL29: =BK29*(BK29/BJ29) -> 7383.8176 | BM29: =BL29*(BL29/BK29) -> 8122.1993
A30: Repayments of Short-Term Debt, and Other | E30: - | F30: - | G30: - | H30: - | I30: - | J30: - | K30: - | L30: - | M30: - | N30: - | O30: - | P30: - | Q30: - | R30: - | S30: - | T30: - | U30: - | V30: - | W30: - | X30: - | Y30: - | Z30: - | AA30: - | AB30: - | AC30: -73 | AD30: -341 | AE30: - | AF30: -414 | AG30: - | AH30: -1906 | AI30: -1349 | AJ30: -2291 | AK30: -5546 | AL30: -2001 | AM30: -1176 | AN30: -1917 | AO30: -2659 | AP30: -7753 | AQ30: -6231 | AR30: -7610 | AS30: -7916 | AT30: -15797 | AU30: =SUM(AQ30:AT30) -> -37554 | AV30: -3603 | AW30: -7641 | AX30: -8095 | AY30: -6338 | AZ30: =SUM(AV30:AY30) -> -25677 | BA30: -404 | BB30: -229 | BC30: -1820 | BD30: =AVERAGE(BA30:BC30,AV30:AY30) -> -4018.5714 | BE30: =SUM(BA30:BD30) -> -6471.5714 | BF30: =(BA30/BE30)*(BE30*1.1) -> -444.4 | BG30: =BF30*(BB30/BA30) -> -251.9 | BH30: =BG30*(BC30/BB30) -> -2002 | BI30: =BH30*(BD30/BC30) -> -4420.4286 | BJ30: =SUM(BF30:BI30) -> -7118.7286 | BK30: =BJ30*(BJ30/BE30) -> -7830.6014 | BL30: =BK30*(BK30/BJ30) -> -8613.6616 | BM30: =BL30*(BL30/BK30) -> -9475.0277
A31: Proceeds from Long Term Debt | E31: 98 | F31: 87 | G31: 143 | H31: 177 | I31: 3378 | J31: 394 | K31: 6359 | L31: 353 | M31: 9 | N31: 66 | O31: 8 | P31: 537 | Q31: 620 | R31: 21 | S31: 49 | T31: 16049 | U31: 109 | V31: 16228 | W31: 125 | X31: 96 | Y31: 143 | Z31: 406 | AA31: 770 | AB31: 190 | AC31: 61 | AD31: 287 | AE31: 1098 | AF31: 1636 | AG31: 693 | AH31: 9918 | AI31: - | AJ31: 531 | AK31: 11142 | AL31: 111 | AM31: 18516 | AN31: 176 | AO31: 200 | AP31: 19003 | AQ31: - | AR31: 12824 | AS31: 107 | AT31: 8235 | AU31: =SUM(AQ31:AT31) -> 21166 | AV31: 0 | AW31: 0 | AX31: 0 | AY31: 0 | AZ31: =SUM(AV31:AY31) -> 0 | BA31: 0 | BB31: 0 | BC31: 0 | BD31: 0 | BE31: =SUM(BA31:BD31) -> 0 | BF31: 0 | BG31: 0 | BH31: 0 | BI31: 0 | BJ31: =SUM(BF31:BI31) -> 0 | BK31: 0 | BL31: 0 | BM31: 0
A32: Repayments of Long-Term Debt | E32: -355 | F32: -472 | G32: -221 | H32: -444 | I32: -82 | J32: -231 | K32: -513 | L32: -1652 | M32: -175 | N32: -70 | O32: -26 | P32: -84 | Q32: -355 | R32: -40 | S32: -48 | T32: -71 | U32: -1142 | V32: -1301 | W32: -202 | X32: -149 | Y32: -183 | Z32: -134 | AA32: -668 | AB32: -351 | AC32: -39 | AD32: -14 | AE32: -1865 | AF32: -2269 | AG32: -667 | AH32: -205 | AI32: -1198 | AJ32: -113 | AK32: -2183 | AL32: -39 | AM32: -41 | AN32: -509 | AO32: -1001 | AP32: -1590 | AQ32: - | AR32: -1 | AS32: - | AT32: -1257 | AU32: =SUM(AQ32:AT32) -> -1258 | AV32: -1386 | AW32: -2000 | AX32: 0 | AY32: -290 | AZ32: =SUM(AV32:AY32) -> -3676 | BA32: -330 | BB32: -4169 | BC32: -2183 | BD32: =AVERAGE(BA32:BC32,AV32:AY32) -> -1479.7143 | BE32: =SUM(BA32:BD32) -> -8161.7143 | BF32: =(BA32/BE32)*(BE32*1.1) -> -363 | BG32: =BF32*(BB32/BA32) -> -4585.9 | BH32: =BG32*(BC32/BB32) -> -2401.3 | BI32: =BH32*(BD32/BC32) -> -1627.6857 | BJ32: =SUM(BF32:BI32) -> -8977.8857 | BK32: =BJ32*(BJ32/BE32) -> -9875.6743 | BL32: =BK32*(BK32/BJ32) -> -10863.242 | BM32: =BL32*(BL32/BK32) -> -11949.566
A33: Principal Repayments of Finance Leases | E33: - | F33: - | G33: - | H33: - | I33: -486 | J33: -775 | K33: -1285 | L33: -2462 | M33: -801 | N33: -1116 | O33: -938 | P33: -1004 | Q33: -3859 | R33: -832 | S33: -1228 | T33: -1267 | U33: -1472 | V33: -4799 | W33: -2015 | X33: -1284 | Y33: -2247 | Z33: -1906 | AA33: -7452 | AB33: -2214 | AC33: -2327 | AD33: -2307 | AE33: -2780 | AF33: -9628 | AG33: -2600 | AH33: -2817 | AI33: -2857 | AJ33: -2368 | AK33: -10642 | AL33: -3406 | AM33: -2804 | AN33: -2693 | AO33: -2260 | AP33: -11163 | AQ33: -2777 | AR33: -2059 | AS33: -1465 | AT33: -1640 | AU33: =SUM(AQ33:AT33) -> -7941 | AV33: -1380 | AW33: -1220 | AX33: -1005 | AY33: -779 | AZ33: =SUM(AV33:AY33) -> -4384 | BA33: -770 | BB33: -538 | BC33: -402 | BD33: =AVERAGE(BA33:BC33,AV33:AY33) -> -870.57143 | BE33: =SUM(BA33:BD33) -> -2580.5714 | BF33: =(BA33/BE33)*(BE33*1.1) -> -847 | BG33: =BF33*(BB33/BA33) -> -591.8 | BH33: =BG33*(BC33/BB33) -> -442.2 | BI33: =BH33*(BD33/BC33) -> -957.62857 | BJ33: =SUM(BF33:BI33) -> -2838.6286 | BK33: =BJ33*(BJ33/BE33) -> -3122.4914 | BL33: =BK33*(BK33/BJ33) -> -3434.7406 | BM33: =BL33*(BL33/BK33) -> -3778.2146
A34: Principal Repayments of Financing Obligations | E34: - | F34: - | G34: - | H34: - | I34: -20 | J34: -5 | K34: -135 | L34: -121 | M34: -29 | N34: -32 | O34: -44 | P34: -41 | Q34: -146 | R34: -37 | S34: -47 | T34: -49 | U34: -66 | V34: -199 | W34: -72 | X34: -57 | Y34: -82 | Z34: -126 | AA34: -337 | AB34: -2 | AC34: -2 | AD34: - | AE34: -24 | AF34: -28 | AG34: -17 | AH34: -15 | AI34: -12 | AJ34: -9 | AK34: -53 | AL34: -67 | AM34: -28 | AN34: -20 | AO34: -47 | AP34: -162 | AQ34: -79 | AR34: -59 | AS34: -48 | AT34: -62 | AU34: =SUM(AQ34:AT34) -> -248 | AV34: -57 | AW34: -77 | AX34: -64 | AY34: -73 | AZ34: =SUM(AV34:AY34) -> -271 | BA34: -90 | BB34: -79 | BC34: -78 | BD34: =AVERAGE(BA34:BC34,AV34:AY34) -> -74 | BE34: =SUM(BA34:BD34) -> -321 | BF34: =(BA34/BE34)*(BE34*1.1) -> -99 | BG34: =BF34*(BB34/BA34) -> -86.9 | BH34: =BG34*(BC34/BB34) -> -85.8 | BI34: =BH34*(BD34/BC34) -> -81.4 | BJ34: =SUM(BF34:BI34) -> -353.1 | BK34: =BJ34*(BJ34/BE34) -> -388.41 | BL34: =BK34*(BK34/BJ34) -> -427.251 | BM34: =BL34*(BL34/BK34) -> -469.9761
A35: Other Cash Flows from Financing | E35: 59 | F35: 105 | G35: 259 | H35: -215 | I35: -531 | J35: 78 | K35: 6 | L35: 119 | Q35: - | V35: - | AA35: - | AF35: - | AG35: - | AH35: - | AI35: - | AJ35: - | AK35: - | AL35: - | AM35: - | AN35: - | AO35: - | AP35: - | AQ35: -2666 | AR35: -3334 | AS35: - | AT35: - | AU35: =SUM(AQ35:AT35) -> -6000 | AV35: - | AW35: - | AX35: - | AY35: - | AZ35: =SUM(AV35:AY35) -> 0 | BA35: - | BB35: - | BC35: - | BD35: 0 | BE35: =SUM(BA35:BD35) -> 0 | BF35: 0 | BG35: 0 | BH35: 0 | BI35: 0 | BJ35: =SUM(BF35:BI35) -> 0 | BK35: 0 | BL35: 0 | BM35: 0
A36: Cash Flow from Financing | E36: =SUM(E29:E35) -> -198 | F36: =SUM(F29:F35) -> -280 | G36: =SUM(G29:G35) -> 181 | H36: =SUM(H29:H35) -> -482 | I36: =SUM(I29:I35) -> 2259 | J36: =SUM(J29:J35) -> -539 | K36: =SUM(K29:K35) -> 4432 | L36: =SUM(L29:L35) -> -3763 | ... BM36: =SUM(BM29:BM35) -> -17550.585
AH37: 127
A38: Foreign Exchange Impact | E38: -70 | F38: -1 | G38: 17 | H38: 1 | I38: -29 | J38: -86 | K38: -310 | L38: -374 | M38: 222 | N38: 64 | O38: 46 | P38: -543 | Q38: -211 | R38: 224 | S38: 248 | T38: 148 | U38: 90 | V38: 710 | W38: 248 | X38: -443 | Y38: -151 | Z38: -5 | AA38: -351 | AB38: -12 | AC38: 47 | AD38: -269 | AE38: 304 | AF38: 70 | AG38: -484 | AH38: 127 | AI38: 377 | AJ38: 599 | AK38: 619 | AL38: -293 | AM38: 234 | AN38: -199 | AO38: -106 | AP38: -364 | AQ38: 16 | AR38: -412 | AS38: -1334 | AT38: 637 | AU38: -1093 | AV38: 145 | AW38: 69 | AX38: -502 | AY38: 691 | AZ38: 403 | BA38: -429 | BB38: -312 | BC38: 690 | BD38: =AVERAGE(BA38:BC38) -> -17 | BE38: =SUM(BA38:BD38) -> -68 | BF38: 0 | BG38: 0 | BH38: 0 | BI38: 0 | BJ38: =SUM(BF38:BI38) -> 0 | BK38: =SUM(BG38:BJ38) -> 0 | BL38: =SUM(BH38:BK38) -> 0 | BM38: =SUM(BI38:BL38) -> 0
A40: Cash Balance, Beginning of Period | E40: 2539 | F40: 2769 | G40: 3444 | H40: 3777 | I40: 5269 | J40: 8084 | K40: 8658 | L40: 14557 | M40: 15890 | N40: 12470 | O40: 12521 | P40: 13656 | Q40: 15890 | R40: 19934 | S40: 16301 | T40: 13851 | U40: 13960 | V40: 19934 | W40: 21856 | X40: 17616 | Y40: 20536 | Z40: 21032 | AA40: 21856 | AB40: 32173 | AC40: 23507 | AD40: 22965 | AE40: 23554 | AF40: 32173 | AG40: =AE42 -> 36410 | AH40: =AG42 -> 27505 | AI40: =AH42 -> 37842 | AJ40: =AI42 -> 30202 | AK40: 36410 | AL40: =AJ42 -> 42377 | AM40: =AL42 -> 34155 | AN40: =AM42 -> 40667 | AO40: =AN42 -> 30177 | AP40: 42377 | AQ40: =AO42 -> 36477 | AR40: =AQ42 -> 36599 | AS40: =AR42 -> 37700 | AT40: =AS42 -> 35178 | AU40: 36477 | AV40: =AT42 -> 54253 | AW40: =AV42 -> 49734 | AX40: =AW42 -> 50067 | AY40: =AX42 -> 50081 | AZ40: =AU42 -> 54253 | BA40: =AY42 -> 73890 | BB40: =BA42 -> 73332 | BC40: =BB42 -> 71673 | BD40: =BC42 -> 78677 | BE40: =AZ42 -> 73890 | BF40: =BD42 -> 91901.414 | BG40: =BF42 -> 90135.67 | BH40: =BG42 -> 94065.885 | BI40: =BH42 -> 109433.92 | BJ40: =BE42 -> 91901.414 | BK40: =BF42 -> 90135.67 | BL40: =BG42 -> 94065.885 | BM40: =BH42 -> 109433.92
A41: Change in Cash | E41: =E20+E27+E36+E38 -> 230 | F41: =F20+F27+F36+F38 -> 675 | G41: =G20+G27+G36+G38 -> 333 | H41: =H20+H27+H36+H38 -> 1492 | I41: =I20+I27+I36+I38 -> 2815 | J41: =J20+J27+J36+J38 -> 574 | K41: =K20+K27+K36+K38 -> 5899 | L41: =L20+L27+L36+L38 -> 1333 | ... BM41: =BM20+BM27+BM36+BM38 -> 41391.016
A42: Cash Balance, Ending of Period | E42: =E40+E41 -> 2769 | F42: =F40+F41 -> 3444 | G42: =G40+G41 -> 3777 | H42: =H40+H41 -> 5269 | I42: =I40+I41 -> 8084 | J42: =J40+J41 -> 8658 | K42: =K40+K41 -> 14557 | L42: =L40+L41 -> 15890 | ... BM42: =BM40+BM41 -> 150824.94
A44: Key Metrics
A45: Free Cash Flow to Equity | E45: =E20+E22-SUM(E15:E19) -> 650 | F45: =F20+F22-SUM(F15:F19) -> 1308 | G45: =G20+G22-SUM(G15:G19) -> 935 | H45: =H20+H22-SUM(H15:H19) -> 628 | I45: =I20+I22-SUM(I15:I19) -> -1128 | J45: =J20+J22-SUM(J15:J19) -> 1264 | K45: =K20+K22-SUM(K15:K19) -> 975 | L45: =L20+L22-SUM(L15:L19) -> 4774 | ... BM45: =BM20+BM22-SUM(BM15:BM19) -> 69752.465
A46: Free Cash Flow (Method Amazon) | AP46: =AP20+AP22+AP23 -> -9069 | AU46: =AU20+AU22+AU23 -> -11569 | AZ46: =AZ20+AZ22+AZ23 -> 36813 | BE46: =BE20+BE22+BE23 -> 32516.456 | BJ46: =BJ20+BJ22+BJ23 -> 42853.701 | BK46: =BK20+BK22+BK23 -> 56636.788 | BL46: =BL20+BL22+BL23 -> 57614.428 | BM46: =BM20+BM22+BM23 -> 62528.289
A47: Free Cash Flow to Firm (Method - Morningstar) | AF47: =IS!AF24+IS!AF29-(-SUM(IS!AF25:AF27)*IS!AF90)+(BS!AF52+CF!AF22+CF!AF9+AF23+AF24)+(AF10+AF13+AF11+AF12) -> 26286.061 | AK47: =IS!AK24+IS!AK29-(-SUM(IS!AK25:AK27)*IS!AK90)+(BS!AK52+CF!AK22+CF!AK9+AK23+AK24)+(AK10+AK13+AK11+AK12) -> 11895.451 | AP47: =IS!AP24+IS!AP29-(-SUM(IS!AP25:AP27)*IS!AP90)+(BS!AP52+CF!AP22+CF!AP9+AP23+AP24)+(AP10+AP13+AP11+AP12) -> 9913.6969 | AU47: =IS!AU24+IS!AU29-(-SUM(IS!AU25:AU27)*IS!AU90)+(BS!AU52+CF!AU22+CF!AU9+AU23+AU24)+(AU10+AU13+AU11+AU12) -> -18582.772 | AZ47: =IS!AZ24+IS!AZ29-(-SUM(IS!AZ25:AZ27)*IS!AZ90)+(BS!AZ52+CF!AZ22+CF!AZ9+AZ23+AZ24)+(AZ10+AZ13+AZ11+AZ12) -> 57991.653 | BE47: =IS!BE24+IS!BE29-(-SUM(IS!BE25:BE27)*IS!BE90)+BS!BE52+(BE22+BE9+BE23+BE24)+(BE10+BE13+BE11+BE12) -> 74015.257 | BJ47: =IS!BJ24+IS!BJ29-(-SUM(IS!BJ25:BJ27)*IS!BJ90)+(BS!BJ52+CF!BJ22+CF!BJ9+BJ23+BJ24)+(BJ10+BJ13+BJ11+BJ12) -> 93066.037 | BK47: =IS!BK24+IS!BK29-(-SUM(IS!BK25:BK27)*IS!BK90)+(BS!BK52+CF!BK22+CF!BK9+BK23+BK24)+(BK10+BK13+BK11+BK12) -> 148711.46 | BL47: =IS!BL24+IS!BL29-(-SUM(IS!BL25:BL27)*IS!BL90)+(BS!BL52+CF!BL22+CF!BL9+BL23+BL24)+(BL10+BL13+BL11+BL12) -> 201887.61 | BM47: =IS!BM24+IS!BM29-(-SUM(IS!BM25:BM27)*IS!BM90)+(BS!BM52+CF!BM22+CF!BM9+BM23+BM24)+(BM10+BM13+BM11+BM12) -> 263017.23
A48: Free Cash Flow to Firm (Method - PitchBook) | AF48: =AF20-SUM(AF15:AF19)+AF22+(-IS!AF26*(1-IS!AF90)) -> 25421.315 | AK48: =AK20-SUM(AK15:AK19)+AK22+(-IS!AK26*(1-IS!AK90)) -> 13893.973 | AP48: =AP20-SUM(AP15:AP19)+AP22+(-IS!AP26*(1-IS!AP90)) -> 6466.8259 | AU48: =AU20-SUM(AU15:AU19)+AU22+(-IS!AU26*(1-IS!AU90)) -> 5077.2104 | AZ48: =AZ20-SUM(AZ15:AZ19)+AZ22+(-IS!AZ26*(1-IS!AZ90)) -> 46336.761 | BE48: =BE20-SUM(BE15:BE19)+BE22+(-IS!BE26*(1-IS!BE90)) -> 55781.703 | BJ48: =BJ20-SUM(BJ15:BJ19)+BJ22+(-IS!BJ26*(1-IS!BJ90)) -> 53249.548 | BK48: =BK20-SUM(BK15:BK19)+BK22+(-IS!BK26*(1-IS!BK90)) -> 66962.28 | BL48: =BL20-SUM(BL15:BL19)+BL22+(-IS!BL26*(1-IS!BL90)) -> 70731.131 | BM48: =BM20-SUM(BM15:BM19)+BM22+(-IS!BM26*(1-IS!BM90)) -> 78959.543
A49: Free Cash Flow to Firm (Formula) | AF49: =AF20+(-(IS!AF26+IS!AF25)*(1-IS!AF90))+AF22 -> 22290.761 | AK49: =AK20+(-(IS!AK26+IS!AK25)*(1-IS!AK90))+AK22 -> 26885.693 | AP49: =AP20+(-(IS!AP26+IS!AP25)*(1-IS!AP90))+AP22 -> -13535.914 | AU49: =AU20+(-(IS!AU26+IS!AU25)*(1-IS!AU90))+AU22 -> -16261.804 | AZ49: =AZ20+(-(IS!AZ26+IS!AZ25)*(1-IS!AZ90))+AZ22 -> 32405.828 | BE49: =BE20+(-(IS!BE26+IS!BE25)*(1-IS!BE90))+BE22 -> 26900.476 | BJ49: =BJ20+(-(IS!BJ26+IS!BJ25)*(1-IS!BJ90))+BJ22 -> 40901.886 | BK49: =BK20+(-(IS!BK26+IS!BK25)*(1-IS!BK90))+BK22 -> 54466.739 | BL49: =BL20+(-(IS!BL26+IS!BL25)*(1-IS!BL90))+BL22 -> 55208.001 | BM49: =BM20+(-(IS!BM26+IS!BM25)*(1-IS!BM90))+BM22 -> 59866.435

Sheet Ratios
B1: Amazon.com Inc. (AMZN)
F3: Estimates | G3: Estimates | H3: Estimates | I3: Estimates | J3: Estimates
B4: Liquidity Ratios | C4: 2021 | D4: 2022 | E4: 2023 | F4: 2024 | G4: 2025 | H4: 2026 | I4: 2027 | J4: 2028
B6: Current Ratio | C6: =BS!AP12/BS!AP25 -> 1.1357598 | D6: =BS!AU12/BS!AU25 -> 0.94464358 | E6: =BS!AZ12/BS!AZ25 -> 1.0450772 | F6: =BS!BE12/BS!BE25 -> 1.159854 | G6: =BS!BJ12/BS!BJ25 -> 1.4050785 | H6: =BS!BK12/BS!BK25 -> 1.6794837 | I6: =BS!BL12/BS!BL25 -> 1.9608242 | J6: =BS!BM12/BS!BM25 -> 2.2730218
B7: Quick Ratio | C7: =(BS!AP12-BS!AP10)/BS!AP25 -> 0.9063304 | D7: =(BS!AU12-BS!AU10)/BS!AU25 -> 0.72323721 | E7: =(BS!AZ12-BS!AZ10)/BS!AZ25 -> 0.84304832 | F7: =(BS!BE12-BS!BE10)/BS!BE25 -> 0.94329756 | G7: =(BS!BJ12-BS!BJ10)/BS!BJ25 -> 1.1778942 | H7: =(BS!BK12-BS!BK10)/BS!BK25 -> 1.4555069 | I7: =(BS!BL12-BS!BL10)/BS!BL25 -> 1.7397622 | J7: =(BS!BM12-BS!BM10)/BS!BM25 -> 2.0546078
B8: Cash Ratio | C8: =(BS!AP8+BS!AP9)/BS!AP25 -> 0.67513672 | D8: =(BS!AU8+BS!AU9)/BS!AU25 -> 0.45063806 | E8: =(BS!AZ8+BS!AZ9)/BS!AZ25 -> 0.52620409 | F8: =(BS!BE8+BS!BE9)/BS!BE25 -> 0.5799927 | G8: =(BS!BJ8+BS!BJ9)/BS!BJ25 -> 0.76077993 | H8: =(BS!BK8+BS!BK9)/BS!BK25 -> 0.9760392 | I8: =(BS!BL8+BS!BL9)/BS!BL25 -> 1.1880027 | J8: =(BS!BM8+BS!BM9)/BS!BM25 -> 1.4189909
B9: Cash to Assets | C9: =BS!AP46/BS!AP20 -> 0.22838956 | D9: =BS!AU46/BS!AU20 -> 0.1513503 | E9: =BS!AZ46/BS!AZ20 -> 0.16440152 | F9: =BS!BE46/BS!BE20 -> 0.16162344 | G9: =BS!BJ46/BS!BJ20 -> 0.19331452 | H9: =BS!BK46/BS!BK20 -> 0.229724 | I9: =BS!BL46/BS!BL20 -> 0.26084051 | J9: =BS!BM46/BS!BM20 -> 0.29108442
B10: Cash Turnover | C10: =IS!AP15/AVERAGE(BS!AK46:AO46) -> 5.5587475 | D10: =IS!AU15/AVERAGE(BS!AP46:AT46) -> 7.3043811 | E10: =IS!AZ15/AVERAGE(BS!AU46:AY46) -> 8.2264921 | F10: =IS!BE15/AVERAGE(BS!AZ46:BD46) -> 7.1177793 | G10: =IS!BJ15/AVERAGE(BS!BE46:BI46) -> 6.1166168 | H10: =IS!BK15/AVERAGE(BS!BJ46:BK46) -> 4.889038 | I10: =IS!BL15/AVERAGE(BS!BK46:BL46) -> 4.1571232 | J10: =IS!BM15/AVERAGE(BS!BL46:BM46) -> 3.663934
B11: Inventory Turnover | C11: =(IS!AP16+IS!AP18+IS!AP19)/AVERAGE(BS!AK10:AO10) -> 14.9076 | D11: =(IS!AU16+IS!AU18+IS!AU19)/AVERAGE(BS!AP10:AT10) -> 12.620538 | E11: =(IS!AZ16+IS!AZ18+IS!AZ19)/AVERAGE(BS!AU10:AY10) -> 13.830326 | F11: =(IS!BE16+IS!BE18+IS!BE19)/AVERAGE(BS!AZ10:BD10) -> 15.019984 | G11: =(IS!BJ16+IS!BJ18+IS!BJ19)/AVERAGE(BS!BE10:BI10) -> 14.597056 | H11: =(IS!BK16+IS!BK18+IS!BK19)/AVERAGE(BS!BJ10:BK10) -> 14.901861 | I11: =(IS!BL16+IS!BL18+IS!BL19)/AVERAGE(BS!BK10:BL10) -> 15.99682 | J11: =(IS!BM16+IS!BM18+IS!BM19)/AVERAGE(BS!BL10:BM10) -> 17.196243
B12: Receivable Turnover | C12: =IS!AP15/AVERAGE(BS!AK11:AO11) -> 17.125912 | D12: =IS!AU15/AVERAGE(BS!AP11:AT11) -> 14.380123 | E12: =IS!AZ15/AVERAGE(BS!AU11:AY11) -> 13.329646 | F12: =IS!BE15/AVERAGE(BS!AZ11:BD11) -> 12.088376 | G12: =IS!BJ15/AVERAGE(BS!BE11:BI11) -> 11.173188 | H12: =IS!BK15/AVERAGE(BS!BJ11:BK11) -> 9.479581 | I12: =IS!BL15/AVERAGE(BS!BK11:BL11) -> 8.7277611 | J12: =IS!BM15/AVERAGE(BS!BL11:BM11) -> 8.0468028
B13: Payable Turnover | C13: =(IS!AP16+IS!AP18+IS!AP19)/AVERAGE(BS!AK22:AO22) -> 5.7203715 | D13: =(IS!AU16+IS!AU18+IS!AU19)/AVERAGE(BS!AP22:AT22) -> 6.1010826 | E13: =(IS!AZ16+IS!AZ18+IS!AZ19)/AVERAGE(BS!AU22:AY22) -> 6.4479198 | F13: =(IS!BE16+IS!BE18+IS!BE19)/AVERAGE(BS!AZ22:BD22) -> 6.2624781 | G13: =(IS!BJ16+IS!BJ18+IS!BJ19)/AVERAGE(BS!BE22:BI22) -> 6.649266 | H13: =(IS!BK16+IS!BK18+IS!BK19)/AVERAGE(BS!BJ22:BK22) -> 6.6526043 | I13: =(IS!BL16+IS!BL18+IS!BL19)/AVERAGE(BS!BK22:BL22) -> 7.0945834 | J13: =(IS!BM16+IS!BM18+IS!BM19)/AVERAGE(BS!BL22:BM22) -> 7.5816451
B14: Fixed Asset Turnover | C14: =IS!AP15/AVERAGE(BS!AK50:AO50) -> 2.5986592 | D14: =IS!AU15/AVERAGE(BS!AP50:AT50) -> 2.2055683 | E14: =IS!AZ15/AVERAGE(BS!AU50:AY50) -> 2.177404 | F14: =IS!BE15/AVERAGE(BS!AZ50:BD50) -> 2.1438162 | G14: =IS!BJ15/AVERAGE(BS!BE50:BI50) -> 2.1184584 | H14: =IS!BK15/AVERAGE(BS!BJ50:BK50) -> 2.1694787 | I14: =IS!BL15/AVERAGE(BS!BK50:BL50) -> 2.2796383 | J14: =IS!BM15/AVERAGE(BS!BL50:BM50) -> 2.4223026
B15: Total Asset Turnover | C15: =IS!AP15/AVERAGE(BS!AK20:AO20) -> 1.2996128 | D15: =IS!AU15/AVERAGE(BS!AP20:AT20) -> 1.1997282 | E15: =IS!AZ15/AVERAGE(BS!AU20:AY20) -> 1.1878683 | F15: =IS!BE15/AVERAGE(BS!AZ20:BD20) -> 1.1344678 | G15: =IS!BJ15/AVERAGE(BS!BE20:BI20) -> 1.0848143 | H15: =IS!BK15/AVERAGE(BS!BJ20:BK20) -> 1.0390435 | I15: =IS!BL15/AVERAGE(BS!BK20:BL20) -> 1.022977 | J15: =IS!BM15/AVERAGE(BS!BL20:BM20) -> 1.0138713
B16: Equity Turnover | C16: =IS!AP15/AVERAGE(BS!AK40:AO40) -> 4.1188177 | D16: =IS!AU15/AVERAGE(BS!AP40:AT40) -> 3.7397989 | E16: =IS!AZ15/AVERAGE(BS!AU40:AY40) -> 3.3651769 | F16: =IS!BE15/AVERAGE(BS!AZ40:BD40) -> 2.6906035 | G16: =IS!BJ15/AVERAGE(BS!BE40:BI40) -> 2.3477567 | H16: =IS!BK15/AVERAGE(BS!BJ40:BK40) -> 2.135952 | I16: =IS!BL15/AVERAGE(BS!BK40:BL40) -> 1.9915295 | J16: =IS!BM15/AVERAGE(BS!BL40:BM40) -> 1.8842143
B17: Days In Sales | C17: =365/C12 -> 21.312733 | D17: =365/D12 -> 25.382258 | E17: =365/E12 -> 27.382573 | F17: =365/F12 -> 30.194295 | G17: =365/G12 -> 32.66749 | H17: =365/H12 -> 38.503812 | I17: =365/I12 -> 41.820576 | J17: =365/J12 -> 45.35963
B18: Days In Inventory | C18: =365/C11 -> 24.484155 | D18: =365/D11 -> 28.921112 | E18: =365/E11 -> 26.39128 | F18: =365/F11 -> 24.300958 | G18: =365/G11 -> 25.005043 | H18: =365/H11 -> 24.493585 | I18: =365/I11 -> 22.817036 | J18: =365/J11 -> 21.225567
B19: Days In Payment | C19: =365/C13 -> 63.807044 | D19: =365/D13 -> 59.825448 | E19: =365/E13 -> 56.607404 | F19: =365/F13 -> 58.283637 | G19: =365/G13 -> 54.893277 | H19: =365/H13 -> 54.865731 | I19: =365/I13 -> 51.4477 | J19: =365/J13 -> 48.142586
B20: Cash Conversion Cycle | C20: =C17+C18-C19 -> -18.010156 | D20: =D17+D18-D19 -> -5.5220781 | E20: =E17+E18-E19 -> -2.8335507 | F20: =F17+F18-F19 -> -3.7883849 | G20: =G17+G18-G19 -> 2.7792557 | H20: =H17+H18-H19 -> 8.131665 | I20: =I17+I18-I19 -> 13.189912 | J20: =J17+J18-J19 -> 18.442611
B22: Financial Health | C22: 2021 | D22: 2022 | E22: 2023 | F22: =F4 -> 2024 | G22: =G4 -> 2025 | H22: 2026 | I22: 2027 | J22: 2028
B24: Cash Flow to Debt | C24: =BS!AP46/BS!AP47 -> 0.82519868 | D24: =BS!AU46/BS!AU47 -> 0.49976448 | E24: =BS!AZ46/BS!AZ47 -> 0.63991859 | F24: =BS!BE46/BS!BE47 -> 0.71804496 | G24: =BS!BJ46/BS!BJ47 -> 0.89186635 | H24: =BS!BK46/BS!BK47 -> 1.1357628 | I24: =BS!BL46/BS!BL47 -> 1.372145 | J24: =BS!BM46/BS!BM47 -> 1.6266809
B25: Free Cash Flow to Debt | C25: =CF!AP45/BS!AP47 -> 0.041969157 | D25: =CF!AU45/BS!AU47 -> 0.028497409 | E25: =CF!AZ45/BS!AZ47 -> 0.32267294 | F25: =CF!BE45/BS!BE47 -> 0.37685263 | G25: =CF!BJ45/BS!BJ47 -> 0.3059183 | H25: =CF!BK45/BS!BK47 -> 0.37638866 | I25: =CF!BL45/BS!BL47 -> 0.38003974 | J25: =CF!BM45/BS!BM47 -> 0.40885433
B26: Interest Coverage | C26: =IS!AP95/-IS!AP26 -> 21.841902 | D26: =IS!AU95/-IS!AU26 -> -1.9256443 | E26: =IS!AZ95/-IS!AZ26 -> 11.876179 | F26: =IS!BE95/-IS!BE26 -> 16.931362 | G26: =IS!BJ95/-IS!BJ26 -> 10.7 | H26: =IS!BK95/-IS!BK26 -> 10.6 | I26: =IS!BL95/-IS!BL26 -> 10.1 | J26: =IS!BM95/-IS!BM26 -> 10.1
B27: EBITDA Interest Coverage | C27: =IS!AP94/-IS!AP26 -> 40.876175 | D27: =IS!AU94/-IS!AU26 -> 15.78496 | E27: =IS!AZ94/-IS!AZ26 -> 27.16939 | F27: =IS!BE94/-IS!BE26 -> 31.05811 | G27: =IS!BJ94/-IS!BJ26 -> 18.990902 | H27: =IS!BK94/-IS!BK26 -> 20.6 | I27: =IS!BL94/-IS!BL26 -> 20.6 | J27: =IS!BM94/-IS!BM26 -> 21.1
B28: Capital Expenditure to EBITDA | C28: =-CF!AP22/IS!AP94 -> 0.8256542 | D28: =-CF!AU22/IS!AU94 -> 1.7034232 | E28: =-CF!AZ22/IS!AZ94 -> 0.60991521 | F28: =-CF!BE22/IS!BE94 -> 0.64098439 | G28: =-CF!BJ22/IS!BJ94 -> 0.63188153 | H28: =-CF!BK22/IS!BK94 -> 0.58252427 | I28: =-CF!BL22/IS!BL94 -> 0.58252427 | J28: =-CF!BM22/IS!BM94 -> 0.56872038
B29: Free Cash Flow to Net Income | C29: =CF!AP45/IS!AP31 -> 0.1464153 | D29: =CF!AU45/IS!AU31 -> -1.4669361 | E29: =CF!AZ45/IS!AZ31 -> 1.4382251 | F29: =CF!BE45/IS!BE31 -> 0.98427348 | G29: =CF!BJ45/IS!BJ31 -> 0.81811415 | H29: =CF!BK45/IS!BK31 -> 0.96901372 | I29: =CF!BL45/IS!BL31 -> 0.97882757 | J29: =CF!BM45/IS!BM31 -> 0.99894003
B30: Free Cash Flow to Equity | C30: =CF!AP45/BS!AP40 -> 0.035335817 | D30: =CF!AU45/BS!AU40 -> 0.027341263 | E30: =CF!AZ45/BS!AZ40 -> 0.21675789 | F30: =CF!BE45/BS!BE40 -> 0.19173683 | G30: =CF!BJ45/BS!BJ40 -> 0.14082736 | H30: =CF!BK45/BS!BK40 -> 0.15213068 | I30: =CF!BL45/BS!BL40 -> 0.13744732 | J30: =CF!BM45/BS!BM40 -> 0.13317324 | P30: =TRIM(AB11) | Q30: =TRIM(AC11) | R30: =TRIM(AD11) | S30: =TRIM(AE11) | T30: =TRIM(AF11) | U30: =TRIM(AG11) | V30: =TRIM(AH11) | W30: =TRIM(AI11) | ... XDY30: =TRIM(XEK11)
B31: Book Value to EBITDA | C31: =AVERAGE(BS!AK40:AO40)/IS!AP94 -> 1.5425952 | D31: =AVERAGE(BS!AP40:AT40)/IS!AU94 -> 3.6783984 | E31: =AVERAGE(BS!AU40:AY40)/IS!AZ94 -> 1.9756839 | F31: =AVERAGE(BS!AZ40:BD40)/IS!BE94 -> 2.0553902 | G31: =AVERAGE(BS!BE40:BI40)/IS!BJ94 -> 2.2428556 | H31: =AVERAGE(BS!BJ40:BK40)/IS!BK94 -> 2.2726957 | I31: =AVERAGE(BS!BK40:BL40)/IS!BL94 -> 2.4375079 | J31: =AVERAGE(BS!BL40:BM40)/IS!BM94 -> 2.5152853
B32: Book Value to Revenue | C32: =AVERAGE(BS!AK40:AO40)/IS!AP15 -> 0.24278812 | D32: =AVERAGE(BS!AP40:AT40)/IS!AU15 -> 0.26739406 | E32: =AVERAGE(BS!AU40:AY40)/IS!AZ15 -> 0.2971612 | F32: =AVERAGE(BS!AZ40:BD40)/IS!BE15 -> 0.37166382 | G32: =AVERAGE(BS!BE40:BI40)/IS!BJ15 -> 0.42593851 | H32: =AVERAGE(BS!BJ40:BK40)/IS!BK15 -> 0.46817532 | I32: =AVERAGE(BS!BK40:BL40)/IS!BL15 -> 0.50212663 | J32: =AVERAGE(BS!BL40:BM40)/IS!BM15 -> 0.53072519
H33: =TRIM(AD17) | I33: =TRIM(AE17) | J33: =TRIM(AF17) | P33: =TRIM(AG17) | Q33: =TRIM(AH17) | R33: =TRIM(AI17) | S33: =TRIM(AJ17) | T33: =TRIM(AK17) | U33: =TRIM(AL17) | V33: =TRIM(AM17) | W33: =TRIM(AN17) | ... XDX33: =TRIM(XEO17) | XDY33: =TRIM(#REF!) -> #REF!
B34: Profitability Ratios | C34: 2021 | D34: 2022 | E34: 2023 | F34: =F4 -> 2024 | G34: =G4 -> 2025 | H34: 2026 | I34: 2027 | J34: 2028
B36: Revenue Growth | C36: =IS!AP46 -> 0.21695367 | D36: =IS!AU46 -> 0.093995173 | E36: =IS!AZ46 -> 0.11829574 | F36: =IS!BE46 -> 0.11005571 | G36: =IS!BJ46 -> 0.099230361 | H36: =IS!BK46 -> 0.093426267 | I36: =IS!BL46 -> 0.094947516 | J36: =IS!BM46 -> 0.096478448
B37: EBITDA Growth | C37: =IS!AP94/IS!AK94-1 -> 0.46570862 | D37: =IS!AU94/IS!AP94-1 -> -0.49471905 | E37: =IS!AZ94/IS!AU94-1 -> 1.3138667 | F37: =IS!BE94/IS!AZ94-1 -> 0.33452325 | G37: =IS!BJ94/IS!BE94-1 -> 0.1544584 | H37: =IS!BK94/IS!BF94-1 -> 4.3007126 | I37: =IS!BL94/IS!BG94-1 -> 4.6235956 | J37: =IS!BM94/IS!BH94-1 -> 4.7837843
B38: Gross Proit Margin | C38: =IS!AP17/IS!AP15 -> 0.42032514 | D38: =IS!AU17/IS!AU15 -> 0.4380534 | E38: =IS!AZ17/IS!AZ15 -> 0.46982089 | F38: =IS!BE17/IS!BE15 -> 0.48754349 | G38: =IS!BJ17/IS!BJ15 -> 0.48 | H38: =IS!BK17/IS!BK15 -> 0.49 | I38: =IS!BL17/IS!BL15 -> 0.5 | J38: =IS!BM17/IS!BM15 -> 0.51
B39: Selling, General and Admin Expense Margin | C39: =(IS!AP20+IS!AP21)/IS!AP15 -> 0.088063139 | D39: =(IS!AU20+IS!AU21)/IS!AU15 -> 0.10531282 | E39: =(IS!AZ20+IS!AZ21)/IS!AZ15 -> 0.097751333 | F39: =(IS!BE20+IS!BE21)/IS!BE15 -> 0.088062781 | G39: =(IS!BJ20+IS!BJ21)/IS!BJ15 -> 0.09 | H39: =(IS!BK20+IS!BK21)/IS!BK15 -> 0.105 | I39: =(IS!BL20+IS!BL21)/IS!BL15 -> 0.11 | J39: =(IS!BM20+IS!BM21)/IS!BM15 -> 0.11
B40: EBITDA Margin | C40: =IS!AP94/IS!AP15 -> 0.15738939 | D40: =IS!AU94/IS!AU15 -> 0.072693066 | E40: =IS!AZ94/IS!AZ15 -> 0.15040928 | F40: =IS!BE94/IS!BE15 -> 0.18082398 | G40: =IS!BJ94/IS!BJ15 -> 0.18990902 | H40: =IS!BK94/IS!BK15 -> 0.206 | I40: =IS!BL94/IS!BL15 -> 0.206 | J40: =IS!BM94/IS!BM15 -> 0.211
B41: EBIT Margin | C41: =IS!AP95/IS!AP15 -> 0.084099936 | D41: =IS!AU95/IS!AU15 -> -0.0088679976 | E41: =IS!AZ95/IS!AZ15 -> 0.065746323 | F41: =IS!BE95/IS!BE15 -> 0.098576383 | G41: =IS!BJ95/IS!BJ15 -> 0.107 | H41: =IS!BK95/IS!BK15 -> 0.106 | I41: =IS!BL95/IS!BL15 -> 0.101 | J41: =IS!BM95/IS!BM15 -> 0.101
B42: EBT Margin | C42: =IS!AP28/IS!AP15 -> 0.081203094 | D42: =IS!AU28/IS!AU15 -> -0.01154902 | E42: =IS!AZ28/IS!AZ15 -> 0.065340954 | F42: =IS!BE28/IS!BE15 -> 0.099600794 | G42: =IS!BJ28/IS!BJ15 -> 0.102 | H42: =IS!BK28/IS!BK15 -> 0.101 | I42: =IS!BL28/IS!BL15 -> 0.096 | J42: =IS!BM28/IS!BM15 -> 0.096
B43: Operating Profit Margin | C43: =IS!AP24/IS!AP15 -> 0.052954098 | D43: =IS!AU24/IS!AU15 -> 0.023829582 | E43: =IS!AZ24/IS!AZ15 -> 0.064114408 | F43: =IS!BE24/IS!BE15 -> 0.10224737 | G43: =IS!BJ24/IS!BJ15 -> 0.105 | H43: =IS!BK24/IS!BK15 -> 0.104 | I43: =IS!BL24/IS!BL15 -> 0.099 | J43: =IS!BM24/IS!BM15 -> 0.099
B44: Net Profit Margin | C44: =IS!AP31/IS!AP15 -> 0.071014129 | D44: =IS!AU31/IS!AU15 -> -0.005295895 | E44: =IS!AZ31/IS!AZ15 -> 0.052932836 | F44: =IS!BE31/IS!BE15 -> 0.082907929 | G44: =IS!BJ31/IS!BJ15 -> 0.08058 | H44: =IS!BK31/IS!BK15 -> 0.07979 | I44: =IS!BL31/IS!BL15 -> 0.07584 | J44: =IS!BM31/IS!BM15 -> 0.07584
B45: Return On Equity (ROE) | C45: =IS!AP31/AVERAGE(BS!AK40:AO40) -> 0.29249425 | D45: =IS!AU31/AVERAGE(BS!AP40:AT40) -> -0.019805582 | E45: =IS!AZ31/AVERAGE(BS!AU40:AY40) -> 0.17812836 | F45: =IS!BE31/AVERAGE(BS!AZ40:BD40) -> 0.22307237 | G45: =IS!BJ31/AVERAGE(BS!BE40:BI40) -> 0.18918224 | H45: =IS!BK31/AVERAGE(BS!BJ40:BK40) -> 0.17042761 | I45: =IS!BL31/AVERAGE(BS!BK40:BL40) -> 0.1510376 | J45: =IS!BM31/AVERAGE(BS!BL40:BM40) -> 0.14289881
B46: Return On Asset (ROA) | C46: =IS!AP31/AVERAGE(BS!AK20:AO20) -> 0.092290874 | D46: =IS!AU31/AVERAGE(BS!AP20:AT20) -> -0.0063536346 | E46: =IS!AZ31/AVERAGE(BS!AU20:AY20) -> 0.062877238 | F46: =IS!BE31/AVERAGE(BS!AZ20:BD20) -> 0.094056373 | G46: =IS!BJ31/AVERAGE(BS!BE20:BI20) -> 0.087414339 | H46: =IS!BK31/AVERAGE(BS!BJ20:BK20) -> 0.08290528 | I46: =IS!BL31/AVERAGE(BS!BK20:BL20) -> 0.077582579 | J46: =IS!BM31/AVERAGE(BS!BL20:BM20) -> 0.076892001
B47: Return On Invested Capital (ROIC) | C47: =(IS!AP31+(-IS!AP26-IS!AP25)*(1-IS!AP90))/AVERAGE(BS!AK49:AO49) -> 0.16048767 | D47: =(IS!AU31+(-IS!AU26-IS!AU25)*(1-IS!AU90))/AVERAGE(BS!AP49:AT49) -> -0.0079813361 | E47: =(IS!AZ31+(-IS!AZ26-IS!AZ25)*(1-IS!AZ90))/AVERAGE(BS!AU49:AY49) -> 0.098945665 | F47: =(IS!BE31+(-IS!BE26-IS!BE25)*(1-IS!BE90))/AVERAGE(BS!AZ49:BD49) -> 0.14030744 | G47: =(IS!BJ31+(-IS!BJ26-IS!BJ25)*(1-IS!BJ90))/AVERAGE(BS!BE49:BI49) -> 0.13557033 | H47: =(IS!BK31+(-IS!BK26-IS!BK25)*(1-IS!BK90))/AVERAGE(BS!BJ49:BK49) -> 0.12666076 | I47: =(IS!BL31+(-IS!BL26-IS!BL25)*(1-IS!BL90))/AVERAGE(BS!BK49:BL49) -> 0.11655192 | J47: =(IS!BM31+(-IS!BM26-IS!BM25)*(1-IS!BM90))/AVERAGE(BS!BL49:BM49) -> 0.11346814
B49: Leverage Ratios | C49: 2021 | D49: 2022 | E49: 2023 | F49: =F4 -> 2024 | G49: =G4 -> 2025 | H49: 2026 | I49: 2027 | J49: 2028
B51: Degree of Operational Leverage | C51: =((IS!AP95-IS!AP96)/IS!AP96)/((IS!AP15-IS!AP97)/IS!AP97) -> 8.6342798 | D51: =((IS!AU95-IS!AU96)/IS!AU96)/((IS!AU15-IS!AU97)/IS!AU97) -> -59.536137 | E51: =((IS!AZ95-IS!AZ96)/IS!AZ96)/((IS!AZ15-IS!AZ97)/IS!AZ97) -> 16.086679 | F51: =((IS!BE95-IS!BE96)/IS!BE96)/((IS!BE15-IS!BE97)/IS!BE97) -> 2.8122308 | G51: =((IS!BJ95-IS!BJ96)/IS!BJ96)/((IS!BJ15-IS!BJ97)/IS!BJ97) -> 2.0043467 | H51: =((IS!BK95-IS!BK96)/IS!BK96)/((IS!BK15-IS!BK97)/IS!BK97) -> 0.8906203 | I51: =((IS!BL95-IS!BL96)/IS!BL96)/((IS!BL15-IS!BL97)/IS!BL97) -> 0.4560314 | J51: =((IS!BM95-IS!BM96)/IS!BM96)/((IS!BM15-IS!BM97)/IS!BM97) -> 1
B52: Degree of Financial Leverage | C52: =((IS!AP31-IS!AP98)/IS!AP98)/((IS!AP95-IS!AP96)/IS!AP96) -> 1.2095018 | D52: =((IS!AU31-IS!AU98)/IS!AU98)/((IS!AU95-IS!AU96)/IS!AU96) -> 0.88728071 | E52: =((IS!AZ31-IS!AZ98)/IS!AZ98)/((IS!AZ95-IS!AZ96)/IS!AZ96) -> 0.85493114 | F52: =((IS!BE31-IS!BE98)/IS!BE98)/((IS!BE95-IS!BE96)/IS!BE96) -> 0.74807952 | G52: =((IS!BJ31-IS!BJ98)/IS!BJ98)/((IS!BJ95-IS!BJ96)/IS!BJ96) -> 1.0252438 | H52: =((IS!BK31-IS!BK98)/IS!BK98)/((IS!BK95-IS!BK96)/IS!BK96) -> 0.99397976 | I52: =((IS!BL31-IS!BL98)/IS!BL98)/((IS!BL95-IS!BL96)/IS!BL96) -> 0.94094894 | J52: =((IS!BM31-IS!BM98)/IS!BM98)/((IS!BM95-IS!BM96)/IS!BM96) -> 1
B53: Degree of Combined Leverage | C53: =((IS!AP31-IS!AP98)/IS!AP98)/((IS!AP15-IS!AP97)/IS!AP97) -> 10.443177 | D53: =((IS!AU31-IS!AU98)/IS!AU98)/((IS!AU15-IS!AU97)/IS!AU97) -> -52.825266 | E53: =((IS!AZ31-IS!AZ98)/IS!AZ98)/((IS!AZ15-IS!AZ97)/IS!AZ97) -> 13.753003 | F53: =((IS!BE31-IS!BE98)/IS!BE98)/((IS!BE15-IS!BE97)/IS!BE97) -> 2.1037723 | G53: =((IS!BJ31-IS!BJ98)/IS!BJ98)/((IS!BJ15-IS!BJ97)/IS!BJ97) -> 2.054944 | H53: =((IS!BK31-IS!BK98)/IS!BK98)/((IS!BK15-IS!BK97)/IS!BK97) -> 0.88525855 | I53: =((IS!BL31-IS!BL98)/IS!BL98)/((IS!BL15-IS!BL97)/IS!BL97) -> 0.42910226 | J53: =((IS!BM31-IS!BM98)/IS!BM98)/((IS!BM15-IS!BM97)/IS!BM97) -> 1
B54: Debt-to-Equity Ratio | C54: =BS!AP47/BS!AP40 -> 0.84194727 | D54: =BS!AU47/BS!AU40 -> 0.95942976 | E54: =BS!AZ47/BS!AZ40 -> 0.67175728 | F54: =BS!BE47/BS!BE40 -> 0.50878464 | G54: =BS!BJ47/BS!BJ40 -> 0.46034304 | H54: =BS!BK47/BS!BK40 -> 0.40418507 | I54: =BS!BL47/BS!BL40 -> 0.36166564 | J54: =BS!BM47/BS!BM40 -> 0.32572294
B55: Debt-to Capital Ratio | C55: =BS!AP47/BS!AP49 -> 0.45709629 | D55: =BS!AU47/BS!AU49 -> 0.48964744 | E55: =BS!AZ47/BS!AZ49 -> 0.40182704 | F55: =BS!BE47/BS!BE49 -> 0.33721489 | G55: =BS!BJ47/BS!BJ49 -> 0.31522939 | H55: =BS!BK47/BS!BK49 -> 0.28784316 | I55: =BS!BL47/BS!BL49 -> 0.26560532 | J55: =BS!BM47/BS!BM49 -> 0.24569458
B56: Debt-to-EBTIDA Ratio | C56: =BS!AP47/IS!AP94 -> 1.5740753 | D56: =BS!AU47/IS!AU94 -> 3.7501807 | E56: =BS!AZ47/IS!AZ94 -> 1.5686095 | F56: =BS!BE47/IS!BE94 -> 1.1975242 | G56: =BS!BJ47/IS!BJ94 -> 1.1347237 | H56: =BS!BK47/IS!BK94 -> 0.99718249 | I56: =BS!BL47/IS!BL94 -> 0.94821819 | J56: =BS!BM47/IS!BM94 -> 0.87818635
B57: Debt-to-Assets | C57: =BS!AP47/BS!AP20 -> 0.27676918 | D57: =BS!AU47/BS!AU20 -> 0.30284325 | E57: =BS!AZ47/BS!AZ20 -> 0.25691005 | F57: =BS!BE47/BS!BE20 -> 0.22508819 | G57: =BS!BJ47/BS!BJ20 -> 0.21675279 | H57: =BS!BK47/BS!BK20 -> 0.20226406 | I57: =BS!BL47/BS!BL20 -> 0.1900969 | J57: =BS!BM47/BS!BM20 -> 0.17894378
B58: Asset-to-Equity Ratio | C58: =BS!AP20/BS!AP40 -> 3.0420558 | D58: =BS!AU20/BS!AU40 -> 3.1680738 | E58: =BS!AZ20/BS!AZ40 -> 2.6147567 | F58: =BS!BE20/BS!BE40 -> 2.2603791 | G58: =BS!BJ20/BS!BJ40 -> 2.1238159 | H58: =BS!BK20/BS!BK40 -> 1.9983039 | I58: =BS!BL20/BS!BL40 -> 1.9025331 | J58: =BS!BM20/BS!BM40 -> 1.820253
B60: Price Multiples | C60: 2021 | D60: 2022 | E60: 2023 | F60: =F4 -> 2024
B61: Stock Price | C61: 166.72 | D61: 84 | E61: 151.94 | F61: =Valuation!M13 -> 227.46
B62: Market Cap | C62: =C61*IS!AP36 -> 1716549.1 | D62: =D61*IS!AU36 -> 855876 | E62: =E61*IS!AZ36 -> 1594154.5 | F62: =F61*IS!BE36 -> 2437973.1
B63: Price to Earnings | C63: =C61/IS!AP33 -> 51.45679 | D63: =D61/IS!AU33 -> -311.11111 | E63: =E61/IS!AZ33 -> 52.393103 | F63: =F61/IS!BE33 -> 46.044534
B64: Price to Revenues | C64: =C61/(IS!AP15/IS!AP36) -> 3.6536159 | D64: =D61/(IS!AU15/IS!AU36) -> 1.6651835 | E64: =E61/(IS!AZ15/IS!AZ36) -> 2.7734796 | F64: =F61/(IS!BE15/IS!BE36) -> 3.8210148
B65: Prices to EBITDA | C65: =C61/(IS!AP94/IS!AP36) -> 23.213863 | D65: =D61/(IS!AU94/IS!AU36) -> 22.907047 | E65: =E61/(IS!AZ94/IS!AZ36) -> 18.439551 | F65: =F61/(IS!BE94/IS!BE36) -> 21.131129
B66: Price to Free Cash Flow | C66: =C61/(CF!AP45/IS!AP36) -> 351.39184 | D66: =D61/(CF!AU45/IS!AU36) -> 214.3441 | E66: =E61/(CF!AZ45/IS!AZ36) -> 36.431155 | F66: =F61/(CF!BE45/IS!BE36) -> 46.823823
B67: Price to Book Value | C67: =C61/(BS!AP40/IS!AP36) -> 12.416718 | D67: =D61/(BS!AU40/IS!AU36) -> 5.8604384 | E67: =E61/(BS!AZ40/IS!AZ36) -> 7.8967405 | F67: =F61/(BS!BE40/IS!BE36) -> 8.9778514

Sheet Amazon Forecast
A1: Amazon.com Inc. (AMZN)
A4: Forecast | B4: 44286 | C4: 44377 | D4: 44469 | E4: 44561 | F4: 2021 | G4: 44651 | H4: 44742 | I4: 44834 | J4: 44926 | K4: 2022 | L4: 45016 | M4: 45107 | N4: 45199 | O4: 45291 | P4: 2023 | Q4: 45382 | R4: 45473 | S4: 45565 | T4: 45657 | U4: 2024
A5: Net Sales Min | B5: 100000 | C5: 110000 | D5: 106000 | E5: 130000 | F5: =SUM(B5:E5) -> 446000 | G5: 112000 | H5: 116000 | I5: 125000 | J5: 140000 | K5: =SUM(G5:J5) -> 493000 | L5: 121000 | M5: 127000 | N5: 138000 | O5: 160000 | P5: =SUM(L5:O5) -> 546000 | Q5: 138000 | R5: 144000 | S5: 154000 | T5: 181500 | U5: =SUM(Q5:T5) -> 617500
A6: Net Sales Max | B6: 106000 | C6: 116000 | D6: 112000 | E6: 140000 | F6: =SUM(B6:E6) -> 474000 | G6: 117000 | H6: 121000 | I6: 130000 | J6: 148000 | K6: =SUM(G6:J6) -> 516000 | L6: 126000 | M6: 133000 | N6: 143000 | O6: 167000 | P6: =SUM(L6:O6) -> 569000 | Q6: 143500 | R6: 149000 | S6: 158500 | T6: 188500 | U6: =SUM(Q6:T6) -> 639500
A8: Operating Income Min | B8: 3000 | C8: 4500 | D8: 2500 | E8: 0 | F8: =SUM(B8:E8) -> 10000 | G8: 3000 | H8: -1000 | I8: 0 | J8: 0 | K8: =SUM(G8:J8) -> 2000 | L8: 0 | M8: 2000 | N8: 5500 | O8: 7000 | P8: =SUM(L8:O8) -> 14500 | Q8: 8000 | R8: 10000 | S8: 11500 | T8: 16000 | U8: =SUM(Q8:T8) -> 45500
A9: Operating Income Max | B9: 6500 | C9: 8000 | D9: 6000 | E9: 3000 | F9: =SUM(B9:E9) -> 23500 | G9: 6000 | H9: 3000 | I9: 3500 | J9: 4000 | K9: =SUM(G9:J9) -> 16500 | L9: 4000 | M9: 5500 | N9: 8500 | O9: 11000 | P9: =SUM(L9:O9) -> 29000 | Q9: 12000 | R9: 14000 | S9: 15000 | T9: 20000 | U9: =SUM(Q9:T9) -> 61000
A11: Realized | B11: 44286 | C11: 44377 | D11: 44469 | E11: 44561 | F11: 2021 | G11: 44651 | H11: 44742 | I11: 44834 | J11: 44926 | K11: 2022 | L11: 45016 | M11: 45107 | N11: 45199 | O11: 45291 | P11: 2023 | Q11: 45382 | R11: 45473 | S11: 45565 | T11: 45657 | U11: 2024
A12: Net Sales | B12: 108518 | C12: 113080 | D12: 110812 | E12: 137412 | F12: 469822 | G12: 116444 | H12: 121234 | I12: 127101 | J12: 149204 | K12: 513983 | L12: 127358 | M12: 134383 | N12: 143083 | O12: 169961 | P12: 574785 | Q12: 143313 | R12: 147977 | S12: 158877
A13: Operating Income | B13: 8865 | C13: 7702 | D13: 4852 | E13: 3460 | F13: 24879 | G13: 3669 | H13: 3317 | I13: 2525 | J13: 2737 | K13: 12248 | L13: 4774 | M13: 7681 | N13: 11188 | O13: 13209 | P13: 36852 | Q13: 15307 | R13: 14672 | S13: 17411
A15: Difference | B15: 44286 | C15: 44377 | D15: 44469 | E15: 44561 | F15: 2021 | G15: 44651 | H15: 44742 | I15: 44834 | J15: 44926 | K15: 2022 | L15: 45016 | M15: 45107 | N15: 45199 | O15: 45291 | P15: 2023 | Q15: 45382 | R15: 45473 | S15: 45565 | T15: 45657 | U15: 2024
A16: Net Sales | B16: =B12-AVERAGE(B5:B6) -> 5518 | C16: =C12-AVERAGE(C5:C6) -> 80 | D16: =D12-AVERAGE(D5:D6) -> 1812 | E16: =E12-AVERAGE(E5:E6) -> 2412 | F16: =F12-AVERAGE(F5:F6) -> 9822 | G16: =G12-AVERAGE(G5:G6) -> 1944 | H16: =H12-AVERAGE(H5:H6) -> 2734 | I16: =I12-AVERAGE(I5:I6) -> -399 | ... S16: =S12-AVERAGE(S5:S6) -> 2627
A17: Net Sales % | B17: =B16/AVERAGE(B5:B6) -> 0.053572816 | C17: =C16/AVERAGE(C5:C6) -> 0.0007079646 | D17: =D16/AVERAGE(D5:D6) -> 0.016623853 | E17: =E16/AVERAGE(E5:E6) -> 0.017866667 | F17: =F16/AVERAGE(F5:F6) -> 0.021352174 | G17: =G16/AVERAGE(G5:G6) -> 0.016978166 | H17: =H16/AVERAGE(H5:H6) -> 0.02307173 | I17: =I16/AVERAGE(I5:I6) -> -0.0031294118 | ... S17: =S16/AVERAGE(S5:S6) -> 0.0168128
A19: Operating Income | B19: =B13-AVERAGE(B8:B9) -> 4115 | C19: =C13-AVERAGE(C8:C9) -> 1452 | D19: =D13-AVERAGE(D8:D9) -> 602 | E19: =E13-AVERAGE(E8:E9) -> 1960 | F19: =F13-AVERAGE(F8:F9) -> 8129 | G19: =G13-AVERAGE(G8:G9) -> -831 | H19: =H13-AVERAGE(H8:H9) -> 2317 | I19: =I13-AVERAGE(I8:I9) -> 775 | ... S19: =S13-AVERAGE(S8:S9) -> 4161
A20: Operating Income% | B20: =B19/AVERAGE(B8:B9) -> 0.86631579 | C20: =C19/AVERAGE(C8:C9) -> 0.23232 | D20: =D19/AVERAGE(D8:D9) -> 0.14164706 | E20: =E19/AVERAGE(E8:E9) -> 1.3066667 | F20: =F19/AVERAGE(F8:F9) -> 0.48531343 | G20: =G19/AVERAGE(G8:G9) -> -0.18466667 | H20: =H19/AVERAGE(H8:H9) -> 2.317 | I20: =I19/AVERAGE(I8:I9) -> 0.44285714 | ... S20: =S19/AVERAGE(S8:S9) -> 0.31403774

Sheet Valuation
B1: Amazon.com Inc. (AMZN)
C4: 2024 | D4: 2025 | E4: 2026 | F4: 2027 | G4: 2028 | I4: Cost of Capital | L4: Equity | O4: Debt
B5: EBIT | C5: =IS!BE95 -> 62896.008 | D5: =IS!BJ95 -> 75045.161 | E5: =IS!BK95 -> 81289.468 | F5: =IS!BL95 -> 84809.225 | G5: =IS!BM95 -> 92991.487 | I5: Cost of Equity | J5: =M9 -> 0.1434 | L5: Cost of Equity (CAPM) | O5: Interest rate | P5: Debt Amount | Q5: Interest rate × Debt amount
B6: Tax Rate | C6: 0.21 | D6: 0.21 | E6: 0.21 | F6: 0.21 | G6: 0.21 | I6: Cost of Debt | J6: =P17 -> 0.037613411 | L6: Risk-Free | M6: =(4.75%+4.5%)/2 -> 0.04625 | O6: 0.0512 | P6: 4000 | Q6: =P6*O6 -> 204.8
B7: EBIT * (1 - Tax Rate) | C7: =C5*(1-C6) -> 49687.846 | D7: =D5*(1-D6) -> 59285.677 | E7: =E5*(1-E6) -> 64218.68 | F7: =F5*(1-F6) -> 66999.288 | G7: =G5*(1-G6) -> 73463.275 | L7: Beta (AMZ) | M7: 1.16 | O7: 0.0433 | P7: 15000 | Q7: =P7*O7 -> 649.5
B8: Depreciation | C8: =CF!BE9 -> 52477.531 | D8: =CF!BJ9 -> 58148.79 | E8: =CF!BK9 -> 76688.178 | F8: =CF!BL9 -> 88168.006 | G8: =CF!BM9 -> 101277.86 | I8: Equity Share | J8: =M14/(M14+P16) -> 0.96854872 | L8: Expected Return of the Market | M8: 0.13 | O8: 0.0277 | P8: 9000 | Q8: =P8*O8 -> 249.3
B9: Purchases of PP&E | C9: =CF!BE22 -> -73952.637 | D9: =CF!BJ22 -> -84162.797 | E9: =CF!BK22 -> -92025.813 | F9: =CF!BL22 -> -100763.44 | G9: =CF!BM22 -> -110484.94 | I9: Debt Share | J9: =P16/(M14+P16) -> 0.031451277 | L9: Cost of Equity | M9: =M6+M7*(M8-M6) -> 0.1434 | O9: 0.0331 | P9: 17500 | Q9: =P9*O9 -> 579.25
B10: Chg. Working Capital | C10: =BS!BE52 -> 19908.803 | D10: =BS!BJ52 -> 44429.112 | E10: =D10*(1+$J$14) -> 48819.726 | F10: =E10*(1+$J$14) -> 53644.233 | G10: =F10*(1+$J$14) -> 58945.512 | O10: 0.0415 | P10: 12750 | Q10: =P10*O10 -> 529.125
B11: Free Cash Flow to Firm | C11: =SUM(C7:C10) -> 48121.543 | D11: =SUM(D7:D10) -> 77700.781 | E11: =SUM(E7:E10) -> 97700.77 | F11: =SUM(F7:F10) -> 108048.09 | G11: =SUM(G7:G10) -> 123201.71 | I11: Tax Rate | J11: 0.21 | L11: Equity Share | O11: 0.0483 | P11: 8250 | Q11: =P11*O11 -> 398.475
B12: Terminal Value | G12: =G11*(1+J14)/(J12-J14) -> 3301750.2 | I12: WACC | J12: =(J5*J8)+(J6*(1-J11)*J9) -> 0.13982445 | L12: Number of Shares Outstanding | M12: =IS!BC36 -> 10735 | O12: 0.066 | P12: 682 | Q12: =P12*O12 -> 45.012
B13: WACC | C13: =$J$12*(1/4) -> 0.034956112 | D13: =$J$12 -> 0.13982445 | E13: =$J$12 -> 0.13982445 | F13: =$J$12 -> 0.13982445 | G13: =$J$12 -> 0.13982445 | L13: Last Share Price | M13: 227.46 | O13: 0.027 | P13: 12109 | Q13: =P13*O13 -> 326.943
B14: Cumulative WACC | C14: =1+C13 -> 1.0349561 | D14: =C14*(1+D13) -> 1.1796683 | E14: =D14*(1+E13) -> 1.3446147 | F14: =E14*(1+F13) -> 1.5326248 | G14: =F14*(1+G13) -> 1.7469232 | I14: Growth Rate | J14: =AVERAGE('Assumptions + Estimates'!J18:R18) -> 0.098822904 | L14: Equity Fair Value | M14: =M13*M12 -> 2441783.1 | O14: Total | P14: =SUM(P6:P13) -> 79291 | Q14: =SUM(Q6:Q13) -> 2982.405
B15: PV of FCFF | C15: =C11/C14 -> 46496.216 | D15: =D11/D14 -> 65866.636 | E15: =E11/E14 -> 72660.79 | F15: =F11/F14 -> 70498.725 | G15: =(G11+G12)/G14 -> 1960562.4
O16: Debt Fair Value | P16: =P14 -> 79291
B17: Value of Firm | C17: =SUM(C15:G15) -> 2216084.8 | O17: Debt Avg Cost | P17: =Q14/P14 -> 0.037613411
B18: +Value of Cash | C18: =BS!BC46 -> 88051
B19: - Value of Debt | C19: =P16 -> 79291
B20: Value of Equity | C20: =C17+C18-C19 -> 2224844.8
B21: Shares Outstanding | C21: =M12 -> 10735
B22: Value of Equity per Share | C22: =C20/C21 -> 207.25149
B24: AMZN Closing Price | C24: =M13 -> 227.46
B25: Over (Under) valued | C25: =C22/M13-1 -> -0.088844225
